Workbook
Name \B: '[1]EXH4A '!#REF!
Name \B: '[1]EXH4A '!#REF!
Name \C: '[1]EXH4A '!#REF!
Name \C: '[1]EXH4A '!#REF!
Name \D: #REF!
Name \D: #REF!
Name \E: #REF!
Name \F: #REF!
Name \G: '[2]EXH-B'!#REF!
Name \I: #REF!
Name \M: '[1]EXH4A '!#REF!
Name \N: '[1]EXH4A '!#REF!
Name \p: #REF!
Name \R: #REF!
Name \S: '[2]EXH-B'!#REF!
Name \T: '[1]EXH4A '!#REF!
Name \W: '[1]EXH4A '!#REF!
Name _1: '[1]EXH4A '!#REF!
Name _2: '[1]EXH4A '!#REF!
Name _3: '[1]EXH4A '!#REF!
Name _4: '[1]EXH4A '!#REF!
Name _5: '[1]EXH4A '!#REF!
Name _6: '[1]EXH4A '!#REF!
Name _7: '[1]EXH4A '!#REF!
Name _8: '[1]EXH4A '!#REF!
Name _RTR1: #N/A
Name A: #REF!
Name AG: #REF!
Name ARL_RBR: #REF!
Name asasd: #REF!
Name Average_Annual_Capacities___Metric_Units: #REF!
Name bgp: '[2]EXH-B'!#REF!
Name BORDER1: '[3]ASC OP Rev 2 Regular Staff'!#REF!
Name C_00_RR: #REF!
Name C_02_RR: #REF!
Name C_98_RR: #REF!
Name CARH_RHS_RTR: #REF!
Name CARH_RTR: #REF!
Name case_title: '[4]Macro Inputs'!$I$4
Name cases: #REF!
Name CAT1_RHS_RBR: #REF!
Name CAT1_RHS_RTR: #REF!
Name CAT1_RHS_YR: #REF!
Name CAT2_RHS_JR: #REF!
Name CAT2_RHS_RR: #REF!
Name CAT2_RHS_RTR: #REF!
Name CatList: [5]Products!$I$5:$I$234
Name CAXL_RBR: #REF!
Name CAXL_RHS_RBR: #REF!
Name CCCR_RHS_RR: #REF!
Name CCCR_RHS_RTR: #REF!
Name CCCR_RHS_YR: #REF!
Name CCCU_RHS_JR: #REF!
Name CCCU_RHS_RTR: #REF!
Name CCR100_RTR: #REF!
Name CCR101_RTR: #REF!
Name CCR102_RTR: #REF!
Name CCR104_RTR: #REF!
Name CCR98_RTR: #REF!
Name CCRC00_YR: #REF!

Sheet Example
A2: Division | B2: SSD
A3: Function | B3: (All)
A5: Division and Function | B5: YE Headcount | C5: Workload Per Employee | D5: Cost Per Workload/Employee
A6: Domestic Recruitment
A7: 2022 | B7: 3 | C7: 34.666667 | D7: 4396.8269
A8: 2023 | B8: 5 | C8: 32.2 | D8: 4468.1988
A9: 2024 | B9: 6 | C9: 40.333333 | D9: 3086.7769
A10: 2025 | B10: 7 | C10: 23.285714 | D10: 4783.865
A11: Expat Recruitment
A12: 2022 | B12: 21 | C12: 23.809524 | D12: 9965.72
A13: 2023 | B13: 26 | C13: 18.461538 | D13: 11452.125
A14: 2024 | B14: 25 | C14: 24 | D14: 8478.3333
A15: 2025 | B15: 22 | C15: 18.181818 | D15: 11779.95

Sheet Cost Analysis Sheet
A1: Year | B1: Division | C1: Unit | D1: Function | E1: Support Group | F1: # WLD (Units or Users) | G1: Total Annual Labor Budget (by business unit) | H1: Total Annual Controllable Expenses (by business unit) | I1: Total Combined Expenses | J1: YE Unit Labor Headcount (FTE & SMP) | K1: Cost Per Support | L1: Cost per WLD/yr | M1: Cost per WLD/mo | N1: WL per Employee | O1: Cost Per WLD per Emmployee | P1: Cost per Employee | Q1: Total Function WLD | R1: Existing Direct Chargebacks - 3rd party invoices | S1: WL/T (Support Group) | T1: Est. Allocations Recorded by PAPM* | U1: Annual Projected Allocation per Model | V1: Remaining to be Allocated per Model | W1: WL/T (Total Function) | X1: Description
A2: 2022 | B2: ATPD | C2: HR Support Services | D2: CH8 Support | E2: ASC + RD | F2: ='Support Numbers'!B2 -> 40 | G2: ='Support Numbers'!B64+('BUDGET-22-25 ATPD'!Z11*0.5) -> 150000 | H2: =('BUDGET-22-25 ATPD'!Z22-'BUDGET-22-25 ATPD'!Z13-'BUDGET-22-25 ATPD'!Z12)*0.5+'Support Numbers'!B80 -> 108400 | I2: =Table1[[#This Row],[Total Annual Labor Budget (by business unit)]]+Table1[[#This Row],[Total Annual Controllable Expenses (by business unit)]] -> 258400 | J2: 2 | K2: =Table1[[#This Row],['# WLD (Units or Users)]]*Table1[[#This Row],[Cost per WLD/yr]] -> 65417.722 | L2: =(G2+H2)/Q2 -> 1635.443 | M2: =L2/12 -> 136.28692 | N2: =Q2/J2 -> 79 | O2: =IF(Table1[[#This Row],[WL per Employee]]<=0,0,Table1[[#This Row],[Total Combined Expenses]]/Table1[[#This Row],[WL per Employee]]/Table1[[#This Row],[YE Unit Labor Headcount (FTE & SMP)]]) -> 1635.443 | P2: =G2/J2 -> 75000 | Q2: ='Support Numbers'!B12 -> 158 | S2: =IF(Table1[[#This Row],['# WLD (Units or Users)]]=0,0,(G2+H2)/F2) -> 6460 | W2: =(G2+H2)/Q2 -> 1635.443 | X2: Onboarding, ongoing, and offboarding support of seconded CH8 employees
A3: 2022 | B3: ATPD | C3: HR Support Services | D3: CH8 Support | E3: SAEV | F3: ='Support Numbers'!B4 -> 0 | G3: ='Support Numbers'!B64+('BUDGET-22-25 ATPD'!Z11*0.5) -> 150000 | H3: =('BUDGET-22-25 ATPD'!Z22-'BUDGET-22-25 ATPD'!Z13-'BUDGET-22-25 ATPD'!Z12)*0.5+'Support Numbers'!B80 -> 108400 | I3: =Table1[[#This Row],[Total Annual Labor Budget (by business unit)]]+Table1[[#This Row],[Total Annual Controllable Expenses (by business unit)]] -> 258400 | J3: 2 | K3: =Table1[[#This Row],['# WLD (Units or Users)]]*Table1[[#This Row],[Cost per WLD/yr]] -> 0 | L3: =(G3+H3)/Q3 -> 1635.443 | M3: =L3/12 -> 136.28692 | N3: =Q3/J3 -> 79 | O3: =IF(Table1[[#This Row],[WL per Employee]]<=0,0,Table1[[#This Row],[Total Combined Expenses]]/Table1[[#This Row],[WL per Employee]]/Table1[[#This Row],[YE Unit Labor Headcount (FTE & SMP)]]) -> 1635.443 | P3: =G3/J3 -> 75000 | Q3: ='Support Numbers'!B12 -> 158 | S3: =IF(Table1[[#This Row],['# WLD (Units or Users)]]=0,0,(G3+H3)/F3) -> 0 | W3: =(G3+H3)/Q3 -> 1635.443 | X3: Onboarding, ongoing, and offboarding support of seconded CH8 employees
A4: 2022 | B4: ATPD | C4: HR Support Services | D4: CH8 Support | E4: VGO | F4: ='Support Numbers'!B10 -> 0 | G4: ='Support Numbers'!B64+('BUDGET-22-25 ATPD'!Z11*0.5) -> 150000 | H4: =('BUDGET-22-25 ATPD'!Z22-'BUDGET-22-25 ATPD'!Z13-'BUDGET-22-25 ATPD'!Z12)*0.5+'Support Numbers'!B80 -> 108400 | I4: =Table1[[#This Row],[Total Annual Labor Budget (by business unit)]]+Table1[[#This Row],[Total Annual Controllable Expenses (by business unit)]] -> 258400 | J4: 2 | K4: =Table1[[#This Row],['# WLD (Units or Users)]]*Table1[[#This Row],[Cost per WLD/yr]] -> 0 | L4: =(G4+H4)/Q4 -> 1635.443 | M4: =L4/12 -> 136.28692 | N4: =Q4/J4 -> 79 | O4: =IF(Table1[[#This Row],[WL per Employee]]<=0,0,Table1[[#This Row],[Total Combined Expenses]]/Table1[[#This Row],[WL per Employee]]/Table1[[#This Row],[YE Unit Labor Headcount (FTE & SMP)]]) -> 1635.443 | P4: =G4/J4 -> 75000 | Q4: ='Support Numbers'!B12 -> 158 | S4: =IF(Table1[[#This Row],['# WLD (Units or Users)]]=0,0,(G4+H4)/F4) -> 0 | W4: =(G4+H4)/Q4 -> 1635.443 | X4: Onboarding, ongoing, and offboarding support of seconded CH8 employees
A5: 2022 | B5: ATPD | C5: HR Support Services | D5: CH8 Support | E5: Motiva | F5: ='Support Numbers'!B7 -> 2 | G5: ='Support Numbers'!B64+('BUDGET-22-25 ATPD'!Z11*0.5) -> 150000 | H5: =('BUDGET-22-25 ATPD'!Z22-'BUDGET-22-25 ATPD'!Z13-'BUDGET-22-25 ATPD'!Z12)*0.5+'Support Numbers'!B80 -> 108400 | I5: =Table1[[#This Row],[Total Annual Labor Budget (by business unit)]]+Table1[[#This Row],[Total Annual Controllable Expenses (by business unit)]] -> 258400 | J5: 2 | K5: =Table1[[#This Row],['# WLD (Units or Users)]]*Table1[[#This Row],[Cost per WLD/yr]] -> 3270.8861 | L5: =(G5+H5)/Q5 -> 1635.443 | M5: =L5/12 -> 136.28692 | N5: =Q5/J5 -> 79 | O5: =IF(Table1[[#This Row],[WL per Employee]]<=0,0,Table1[[#This Row],[Total Combined Expenses]]/Table1[[#This Row],[WL per Employee]]/Table1[[#This Row],[YE Unit Labor Headcount (FTE & SMP)]]) -> 1635.443 | P5: =G5/J5 -> 75000 | Q5: ='Support Numbers'!B12 -> 158 | S5: =IF(Table1[[#This Row],['# WLD (Units or Users)]]=0,0,(G5+H5)/F5) -> 129200 | W5: =(G5+H5)/Q5 -> 1635.443 | X5: Onboarding, ongoing, and offboarding support of seconded CH8 employees
A6: 2022 | B6: ATPD | C6: HR Support Services | D6: CH8 Support | E6: PMT | F6: ='Support Numbers'!B9 -> 30 | G6: ='Support Numbers'!B64+('BUDGET-22-25 ATPD'!Z11*0.5) -> 150000 | H6: =('BUDGET-22-25 ATPD'!Z22-'BUDGET-22-25 ATPD'!Z13-'BUDGET-22-25 ATPD'!Z12)*0.5+'Support Numbers'!B80 -> 108400 | I6: =Table1[[#This Row],[Total Annual Labor Budget (by business unit)]]+Table1[[#This Row],[Total Annual Controllable Expenses (by business unit)]] -> 258400 | J6: 2 | K6: =Table1[[#This Row],['# WLD (Units or Users)]]*Table1[[#This Row],[Cost per WLD/yr]] -> 49063.291 | L6: =(G6+H6)/Q6 -> 1635.443 | M6: =L6/12 -> 136.28692 | N6: =Q6/J6 -> 79 | O6: =IF(Table1[[#This Row],[WL per Employee]]<=0,0,Table1[[#This Row],[Total Combined Expenses]]/Table1[[#This Row],[WL per Employee]]/Table1[[#This Row],[YE Unit Labor Headcount (FTE & SMP)]]) -> 1635.443 | P6: =G6/J6 -> 75000 | Q6: ='Support Numbers'!B12 -> 158 | S6: =IF(Table1[[#This Row],['# WLD (Units or Users)]]=0,0,(G6+H6)/F6) -> 8613.3333 | W6: =(G6+H6)/Q6 -> 1635.443 | X6: Onboarding, ongoing, and offboarding support of seconded CH8 employees
A7: 2022 | B7: ATPD | C7: HR Support Services | D7: CH8 Support | E7: SRI | F7: ='Support Numbers'!B6 -> 2 | G7: ='Support Numbers'!B64+('BUDGET-22-25 ATPD'!Z11*0.5) -> 150000 | H7: =('BUDGET-22-25 ATPD'!Z22-'BUDGET-22-25 ATPD'!Z13-'BUDGET-22-25 ATPD'!Z12)*0.5+'Support Numbers'!B80 -> 108400 | I7: =Table1[[#This Row],[Total Annual Labor Budget (by business unit)]]+Table1[[#This Row],[Total Annual Controllable Expenses (by business unit)]] -> 258400 | J7: 2 | K7: =Table1[[#This Row],['# WLD (Units or Users)]]*Table1[[#This Row],[Cost per WLD/yr]] -> 3270.8861 | L7: =(G7+H7)/Q7 -> 1635.443 | M7: =L7/12 -> 136.28692 | N7: =Q7/J7 -> 79 | O7: =IF(Table1[[#This Row],[WL per Employee]]<=0,0,Table1[[#This Row],[Total Combined Expenses]]/Table1[[#This Row],[WL per Employee]]/Table1[[#This Row],[YE Unit Labor Headcount (FTE & SMP)]]) -> 1635.443 | P7: =G7/J7 -> 75000 | Q7: ='Support Numbers'!B12 -> 158 | S7: =IF(Table1[[#This Row],['# WLD (Units or Users)]]=0,0,(G7+H7)/F7) -> 129200 | W7: =(G7+H7)/Q7 -> 1635.443 | X7: Onboarding, ongoing, and offboarding support of seconded CH8 employees
A8: 2022 | B8: ATPD | C8: HR Support Services | D8: CH8 Support | E8: SPII | F8: ='Support Numbers'!B8 -> 3 | G8: ='Support Numbers'!B64+('BUDGET-22-25 ATPD'!Z11*0.5) -> 150000 | H8: =('BUDGET-22-25 ATPD'!Z22-'BUDGET-22-25 ATPD'!Z13-'BUDGET-22-25 ATPD'!Z12)*0.5+'Support Numbers'!B80 -> 108400 | I8: =Table1[[#This Row],[Total Annual Labor Budget (by business unit)]]+Table1[[#This Row],[Total Annual Controllable Expenses (by business unit)]] -> 258400 | J8: 2 | K8: =Table1[[#This Row],['# WLD (Units or Users)]]*Table1[[#This Row],[Cost per WLD/yr]] -> 4906.3291 | L8: =(G8+H8)/Q8 -> 1635.443 | M8: =L8/12 -> 136.28692 | N8: =Q8/J8 -> 79 | O8: =IF(Table1[[#This Row],[WL per Employee]]<=0,0,Table1[[#This Row],[Total Combined Expenses]]/Table1[[#This Row],[WL per Employee]]/Table1[[#This Row],[YE Unit Labor Headcount (FTE & SMP)]]) -> 1635.443 | P8: =G8/J8 -> 75000 | Q8: ='Support Numbers'!B12 -> 158 | S8: =IF(Table1[[#This Row],['# WLD (Units or Users)]]=0,0,(G8+H8)/F8) -> 86133.333 | W8: =(G8+H8)/Q8 -> 1635.443 | X8: Onboarding, ongoing, and offboarding support of seconded CH8 employees
A9: 2022 | B9: ATPD | C9: HR Support Services | D9: CH8 Support | E9: NEX | F9: ='Support Numbers'!B5 -> 1 | G9: ='Support Numbers'!B64+('BUDGET-22-25 ATPD'!Z11*0.5) -> 150000 | H9: =('BUDGET-22-25 ATPD'!Z22-'BUDGET-22-25 ATPD'!Z13-'BUDGET-22-25 ATPD'!Z12)*0.5+'Support Numbers'!B80 -> 108400 | I9: =Table1[[#This Row],[Total Annual Labor Budget (by business unit)]]+Table1[[#This Row],[Total Annual Controllable Expenses (by business unit)]] -> 258400 | J9: 2 | K9: =Table1[[#This Row],['# WLD (Units or Users)]]*Table1[[#This Row],[Cost per WLD/yr]] -> 1635.443 | L9: =(G9+H9)/Q9 -> 1635.443 | M9: =L9/12 -> 136.28692 | N9: =Q9/J9 -> 79 | O9: =IF(Table1[[#This Row],[WL per Employee]]<=0,0,Table1[[#This Row],[Total Combined Expenses]]/Table1[[#This Row],[WL per Employee]]/Table1[[#This Row],[YE Unit Labor Headcount (FTE & SMP)]]) -> 1635.443 | P9: =G9/J9 -> 75000 | Q9: ='Support Numbers'!B12 -> 158 | S9: =IF(Table1[[#This Row],['# WLD (Units or Users)]]=0,0,(G9+H9)/F9) -> 258400 | W9: =(G9+H9)/Q9 -> 1635.443 | X9: Onboarding, ongoing, and offboarding support of seconded CH8 employees
A10: 2022 | B10: ATPD | C10: HR Support Services | D10: CH8 Support | E10: Internships | F10: ='Support Numbers'!B11 -> 80 | G10: ='Support Numbers'!B64+('BUDGET-22-25 ATPD'!Z11*0.5) -> 150000 | H10: =('BUDGET-22-25 ATPD'!Z22-'BUDGET-22-25 ATPD'!Z13-'BUDGET-22-25 ATPD'!Z12)*0.5+'Support Numbers'!B80 -> 108400 | I10: =Table1[[#This Row],[Total Annual Labor Budget (by business unit)]]+Table1[[#This Row],[Total Annual Controllable Expenses (by business unit)]] -> 258400 | J10: 2 | K10: =Table1[[#This Row],['# WLD (Units or Users)]]*Table1[[#This Row],[Cost per WLD/yr]] -> 130835.44 | L10: =(G10+H10)/Q10 -> 1635.443 | M10: =L10/12 -> 136.28692 | N10: =Q10/J10 -> 79 | O10: =IF(Table1[[#This Row],[WL per Employee]]<=0,0,Table1[[#This Row],[Total Combined Expenses]]/Table1[[#This Row],[WL per Employee]]/Table1[[#This Row],[YE Unit Labor Headcount (FTE & SMP)]]) -> 1635.443 | P10: =G10/J10 -> 75000 | Q10: ='Support Numbers'!B12 -> 158 | S10: =IF(Table1[[#This Row],['# WLD (Units or Users)]]=0,0,(G10+H10)/F10) -> 3230 | W10: =(G10+H10)/Q10 -> 1635.443 | X10: Onboarding, ongoing, and offboarding support of seconded CH8 employees
A11: 2022 | B11: ATPD | C11: HR Support Services | D11: Medical Referral | E11: Medical Referrals | F11: ='Support Numbers'!B19 -> 50 | G11: ='Support Numbers'!B65 -> 110000 | H11: =('BUDGET-22-25 ATPD'!Z22-'BUDGET-22-25 ATPD'!Z13-'BUDGET-22-25 ATPD'!Z12)*0.5 -> 33400 | I11: =Table1[[#This Row],[Total Annual Labor Budget (by business unit)]]+Table1[[#This Row],[Total Annual Controllable Expenses (by business unit)]] -> 143400 | J11: 1 | K11: =Table1[[#This Row],['# WLD (Units or Users)]]*Table1[[#This Row],[Cost per WLD/yr]] -> 143400 | L11: =(G11+H11)/Q11 -> 2868 | M11: =L11/12 -> 239 | N11: =Q11/J11 -> 50 | O11: =IF(Table1[[#This Row],[WL per Employee]]<=0,0,Table1[[#This Row],[Total Combined Expenses]]/Table1[[#This Row],[WL per Employee]]/Table1[[#This Row],[YE Unit Labor Headcount (FTE & SMP)]]) -> 2868 | P11: =G11/J11 -> 110000 | Q11: ='Support Numbers'!B19 -> 50 | S11: =IF(Table1[[#This Row],['# WLD (Units or Users)]]=0,0,(G11+H11)/F11) -> 2868 | W11: =(G11+H11)/Q11 -> 2868 | X11: Coordination of medical referral patience and programs
A12: 2022 | B12: ATPD | C12: HR Support Services | D12: CH14 Fin Support | E12: All Students | F12: ='Support Numbers'!B18 -> 1080 | G12: ='Support Numbers'!B66+('BUDGET-22-25 ATPD'!Z11*0.5) -> 110000 | H12: =('BUDGET-22-25 ATPD'!Z22-'BUDGET-22-25 ATPD'!Z13-'BUDGET-22-25 ATPD'!Z12)*0.5 -> 33400 | I12: =Table1[[#This Row],[Total Annual Labor Budget (by business unit)]]+Table1[[#This Row],[Total Annual Controllable Expenses (by business unit)]] -> 143400 | J12: 2.5 | K12: =Table1[[#This Row],['# WLD (Units or Users)]]*Table1[[#This Row],[Cost per WLD/yr]] -> 143400 | L12: =(G12+H12)/Q12 -> 132.77778 | M12: =L12/12 -> 11.064815 | N12: =Q12/J12 -> 432 | O12: =IF(Table1[[#This Row],[WL per Employee]]<=0,0,Table1[[#This Row],[Total Combined Expenses]]/Table1[[#This Row],[WL per Employee]]/Table1[[#This Row],[YE Unit Labor Headcount (FTE & SMP)]]) -> 132.77778 | P12: =G12/J12 -> 44000 | Q12: =F12 -> 1080 | S12: =IF(Table1[[#This Row],['# WLD (Units or Users)]]=0,0,(G12+H12)/F12) -> 132.77778 | W12: =(G12+H12)/Q12 -> 132.77778 | X12: Help desk for all students inqueries
A13: 2022 | B13: ATPD | C13: Academic Prog | D13: CH14 Advisory | E13: Undergrad | F13: ='Support Numbers'!B15 -> 800 | G13: ='BUDGET-22-25 ATPD'!N8+'BUDGET-22-25 ATPD'!N12 -> 1012000 | H13: =('BUDGET-22-25 ATPD'!N9+'BUDGET-22-25 ATPD'!N22)-'BUDGET-22-25 ATPD'!N12-'BUDGET-22-25 ATPD'!N13+'Support Numbers'!B78 -> 490800 | I13: =Table1[[#This Row],[Total Annual Labor Budget (by business unit)]]+Table1[[#This Row],[Total Annual Controllable Expenses (by business unit)]] -> 1502800 | J13: ='BUDGET-22-25 ATPD'!N40+'BUDGET-22-25 ATPD'!N42 -> 9 | K13: =Table1[[#This Row],['# WLD (Units or Users)]]*Table1[[#This Row],[Cost per WLD/yr]] -> 1113185.2 | L13: =(G13+H13)/Q13 -> 1391.4815 | M13: =L13/12 -> 115.95679 | N13: =Q13/J13 -> 120 | O13: =IF(Table1[[#This Row],[WL per Employee]]<=0,0,Table1[[#This Row],[Total Combined Expenses]]/Table1[[#This Row],[WL per Employee]]/Table1[[#This Row],[YE Unit Labor Headcount (FTE & SMP)]]) -> 1391.4815 | P13: =G13/J13 -> 112444.44 | Q13: ='Support Numbers'!B18 -> 1080 | S13: =IF(Table1[[#This Row],['# WLD (Units or Users)]]=0,0,(G13+H13)/F13) -> 1878.5 | W13: =(G13+H13)/Q13 -> 1391.4815 | X13: Academic advisory for SAO sponsored students in an Undergrad program
A14: 2022 | B14: ATPD | C14: Academic Prog | D14: CH14 Advisory | E14: Associates | F14: ='Support Numbers'!B16 -> 30 | G14: ='BUDGET-22-25 ATPD'!N8+'BUDGET-22-25 ATPD'!N12 -> 1012000 | H14: =('BUDGET-22-25 ATPD'!N9+'BUDGET-22-25 ATPD'!N22)-'BUDGET-22-25 ATPD'!N12-'BUDGET-22-25 ATPD'!N13+'Support Numbers'!B78 -> 490800 | I14: =Table1[[#This Row],[Total Annual Labor Budget (by business unit)]]+Table1[[#This Row],[Total Annual Controllable Expenses (by business unit)]] -> 1502800 | J14: ='BUDGET-22-25 ATPD'!N40+'BUDGET-22-25 ATPD'!N42 -> 9 | K14: =Table1[[#This Row],['# WLD (Units or Users)]]*Table1[[#This Row],[Cost per WLD/yr]] -> 41744.444 | L14: =(G14+H14)/Q14 -> 1391.4815 | M14: =L14/12 -> 115.95679 | N14: =Q14/J14 -> 120 | O14: =IF(Table1[[#This Row],[WL per Employee]]<=0,0,Table1[[#This Row],[Total Combined Expenses]]/Table1[[#This Row],[WL per Employee]]/Table1[[#This Row],[YE Unit Labor Headcount (FTE & SMP)]]) -> 1391.4815 | P14: =G14/J14 -> 112444.44 | Q14: ='Support Numbers'!B18 -> 1080 | S14: =IF(Table1[[#This Row],['# WLD (Units or Users)]]=0,0,(G14+H14)/F14) -> 50093.333 | W14: =(G14+H14)/Q14 -> 1391.4815 | X14: Academic advisory for SAO sponsored students in an Associates program
A15: 2022 | B15: ATPD | C15: Academic Prog | D15: CH14 Advisory | E15: Advanced | F15: ='Support Numbers'!B17 -> 250 | G15: ='BUDGET-22-25 ATPD'!N8+'BUDGET-22-25 ATPD'!N12 -> 1012000 | H15: =('BUDGET-22-25 ATPD'!N9+'BUDGET-22-25 ATPD'!N22)-'BUDGET-22-25 ATPD'!N12-'BUDGET-22-25 ATPD'!N13+'Support Numbers'!B78 -> 490800 | I15: =Table1[[#This Row],[Total Annual Labor Budget (by business unit)]]+Table1[[#This Row],[Total Annual Controllable Expenses (by business unit)]] -> 1502800 | J15: ='BUDGET-22-25 ATPD'!N40+'BUDGET-22-25 ATPD'!N42 -> 9 | K15: =Table1[[#This Row],['# WLD (Units or Users)]]*Table1[[#This Row],[Cost per WLD/yr]] -> 347870.37 | L15: =(G15+H15)/Q15 -> 1391.4815 | M15: =L15/12 -> 115.95679 | N15: =Q15/J15 -> 120 | O15: =IF(Table1[[#This Row],[WL per Employee]]<=0,0,Table1[[#This Row],[Total Combined Expenses]]/Table1[[#This Row],[WL per Employee]]/Table1[[#This Row],[YE Unit Labor Headcount (FTE & SMP)]]) -> 1391.4815 | P15: =G15/J15 -> 112444.44 | Q15: ='Support Numbers'!B18 -> 1080 | S15: =IF(Table1[[#This Row],['# WLD (Units or Users)]]=0,0,(G15+H15)/F15) -> 6011.2 | W15: =(G15+H15)/Q15 -> 1391.4815 | X15: Academic advisory for SAO sponsored students in an Advanced degree program
A16: 2022 | B16: ATPD | C16: Tech Professional Unit | D16: Trainees Support | E16: CH14 | F16: ='Support Numbers'!B22 -> 25 | G16: ='BUDGET-22-25 ATPD'!T8+'BUDGET-22-25 ATPD'!T12 -> 439000 | H16: ='BUDGET-22-25 ATPD'!T9+'BUDGET-22-25 ATPD'!T22-'BUDGET-22-25 ATPD'!T12-'BUDGET-22-25 ATPD'!T13+'Support Numbers'!B79 -> 156800 | I16: =Table1[[#This Row],[Total Annual Labor Budget (by business unit)]]+Table1[[#This Row],[Total Annual Controllable Expenses (by business unit)]] -> 595800 | J16: ='BUDGET-22-25 ATPD'!T39 -> 3 | K16: =Table1[[#This Row],['# WLD (Units or Users)]]*Table1[[#This Row],[Cost per WLD/yr]] -> 297900 | L16: =(G16+H16)/Q16 -> 11916 | M16: =L16/12 -> 993 | N16: =Q16/J16 -> 16.666667 | O16: =IF(Table1[[#This Row],[WL per Employee]]<=0,0,Table1[[#This Row],[Total Combined Expenses]]/Table1[[#This Row],[WL per Employee]]/Table1[[#This Row],[YE Unit Labor Headcount (FTE & SMP)]]) -> 11916 | P16: =G16/J16 -> 146333.33 | Q16: ='Support Numbers'!B24 -> 50 | S16: =IF(Table1[[#This Row],['# WLD (Units or Users)]]=0,0,(G16+H16)/F16) -> 23832 | W16: =(G16+H16)/Q16 -> 11916 | X16: Coordination and support for sponsored CH14 trainee programs
A17: 2022 | B17: ATPD | C17: Tech Professional Unit | D17: Trainees Support | E17: CH8 | F17: ='Support Numbers'!B23 -> 25 | G17: ='BUDGET-22-25 ATPD'!T8+'BUDGET-22-25 ATPD'!T12 -> 439000 | H17: ='BUDGET-22-25 ATPD'!T9+'BUDGET-22-25 ATPD'!T22-'BUDGET-22-25 ATPD'!T12-'BUDGET-22-25 ATPD'!T13+'Support Numbers'!B79 -> 156800 | I17: =Table1[[#This Row],[Total Annual Labor Budget (by business unit)]]+Table1[[#This Row],[Total Annual Controllable Expenses (by business unit)]] -> 595800 | J17: ='BUDGET-22-25 ATPD'!T39 -> 3 | K17: =Table1[[#This Row],['# WLD (Units or Users)]]*Table1[[#This Row],[Cost per WLD/yr]] -> 297900 | L17: =(G17+H17)/Q17 -> 11916 | M17: =L17/12 -> 993 | N17: =Q17/J17 -> 16.666667 | O17: =IF(Table1[[#This Row],[WL per Employee]]<=0,0,Table1[[#This Row],[Total Combined Expenses]]/Table1[[#This Row],[WL per Employee]]/Table1[[#This Row],[YE Unit Labor Headcount (FTE & SMP)]]) -> 11916 | P17: =G17/J17 -> 146333.33 | Q17: ='Support Numbers'!B24 -> 50 | S17: =IF(Table1[[#This Row],['# WLD (Units or Users)]]=0,0,(G17+H17)/F17) -> 23832 | W17: =(G17+H17)/Q17 -> 11916 | X17: Coordination and support for sponsored CH8 trainee programs
A18: 2022 | B18: HRS | C18: All HRS | D18: HR Support Services | E18: ASC + RD | F18: ='Support Numbers'!B30 -> 500 | G18: =('BUDGET-22-25 HRS & CIG'!B8-'BUDGET-22-25 HRS & CIG'!B4) +'BUDGET-22-25 HRS & CIG'!H8+'BUDGET-22-25 HRS & CIG'!N8+'BUDGET-22-25 HRS & CIG'!T8 +'BUDGET-22-25 HRS & CIG'!B12 +'BUDGET-22-25 HRS & CIG'!H12+'BUDGET-22-25 HRS & CIG'!N12+'BUDGET-22-25 HRS & CIG'!T12 -> 2400600 | H18: =('BUDGET-22-25 HRS & CIG'!$B$22-'BUDGET-22-25 HRS & CIG'!$B$12-'BUDGET-22-25 HRS & CIG'!$B$13)+('BUDGET-22-25 HRS & CIG'!$H$22-'BUDGET-22-25 HRS & CIG'!$H$12-'BUDGET-22-25 HRS & CIG'!$H$13)+('BUDGET-22-25 HRS & CIG'!$N$22-'BUDGET-22-25 HRS & CIG'!$N$12-'BUDGET-22-25 HRS & CIG'!$N$13)+('BUDGET-22-25 HRS & CIG'!$T$22-'BUDGET-22-25 HRS & CIG'!$T$12-'BUDGET-22-25 HRS & CIG'!$T$13) -> 533500 | I18: =Table1[[#This Row],[Total Annual Labor Budget (by business unit)]]+Table1[[#This Row],[Total Annual Controllable Expenses (by business unit)]] -> 2934100 | J18: ='BUDGET-22-25 HRS & CIG'!B37+'BUDGET-22-25 HRS & CIG'!H37+'BUDGET-22-25 HRS & CIG'!N37+'BUDGET-22-25 HRS & CIG'!T37 -> 16 | K18: =Table1[[#This Row],['# WLD (Units or Users)]]*Table1[[#This Row],[Cost per WLD/yr]] -> 2629121.9 | L18: =(G18+H18)/Q18 -> 5258.2437 | M18: =L18/12 -> 438.18698 | N18: =Q18/J18 -> 34.875 | O18: =IF(Table1[[#This Row],[WL per Employee]]<=0,0,Table1[[#This Row],[Total Combined Expenses]]/Table1[[#This Row],[WL per Employee]]/Table1[[#This Row],[YE Unit Labor Headcount (FTE & SMP)]]) -> 5258.2437 | P18: =G18/J18 -> 150037.5 | Q18: ='Support Numbers'!B36 -> 558 | S18: =IF(Table1[[#This Row],['# WLD (Units or Users)]]=0,0,(G18+H18)/F18) -> 5868.2 | W18: =(G18+H18)/Q18 -> 5258.2437 | X18: Full life cycle HR support - hire to retire (onboarding, HRIS, personnel, training, offboarding) for ASC/RD employees, temps, independent contractors
A19: 2022 | B19: HRS | C19: All HRS | D19: HR Support Services | E19: AAC | F19: ='Support Numbers'!B27 -> 10 | G19: =('BUDGET-22-25 HRS & CIG'!B8-'BUDGET-22-25 HRS & CIG'!B4) +'BUDGET-22-25 HRS & CIG'!H8+'BUDGET-22-25 HRS & CIG'!N8+'BUDGET-22-25 HRS & CIG'!T8 +'BUDGET-22-25 HRS & CIG'!B12 +'BUDGET-22-25 HRS & CIG'!H12+'BUDGET-22-25 HRS & CIG'!N12+'BUDGET-22-25 HRS & CIG'!T12 -> 2400600 | H19: =('BUDGET-22-25 HRS & CIG'!$B$22-'BUDGET-22-25 HRS & CIG'!$B$12-'BUDGET-22-25 HRS & CIG'!$B$13)+('BUDGET-22-25 HRS & CIG'!$H$22-'BUDGET-22-25 HRS & CIG'!$H$12-'BUDGET-22-25 HRS & CIG'!$H$13)+('BUDGET-22-25 HRS & CIG'!$N$22-'BUDGET-22-25 HRS & CIG'!$N$12-'BUDGET-22-25 HRS & CIG'!$N$13)+('BUDGET-22-25 HRS & CIG'!$T$22-'BUDGET-22-25 HRS & CIG'!$T$12-'BUDGET-22-25 HRS & CIG'!$T$13) -> 533500 | I19: =Table1[[#This Row],[Total Annual Labor Budget (by business unit)]]+Table1[[#This Row],[Total Annual Controllable Expenses (by business unit)]] -> 2934100 | J19: ='BUDGET-22-25 HRS & CIG'!B37+'BUDGET-22-25 HRS & CIG'!H37+'BUDGET-22-25 HRS & CIG'!N37+'BUDGET-22-25 HRS & CIG'!T37 -> 16 | K19: =Table1[[#This Row],['# WLD (Units or Users)]]*Table1[[#This Row],[Cost per WLD/yr]] -> 52582.437 | L19: =(G19+H19)/Q19 -> 5258.2437 | M19: =L19/12 -> 438.18698 | N19: =Q19/J19 -> 34.875 | O19: =IF(Table1[[#This Row],[WL per Employee]]<=0,0,Table1[[#This Row],[Total Combined Expenses]]/Table1[[#This Row],[WL per Employee]]/Table1[[#This Row],[YE Unit Labor Headcount (FTE & SMP)]]) -> 5258.2437 | P19: =G19/J19 -> 150037.5 | Q19: ='Support Numbers'!B36 -> 558 | S19: =IF(Table1[[#This Row],['# WLD (Units or Users)]]=0,0,(G19+H19)/F19) -> 293410 | W19: =(G19+H19)/Q19 -> 5258.2437 | X19: Full life cycle HR support - hire to retire (onboarding, HRIS, personnel, training, offboarding) for AAC employees, temps, independent contractors
A20: 2022 | B20: HRS | C20: All HRS | D20: HR Support Services | E20: ASBCO | F20: ='Support Numbers'!B29 -> 6 | G20: =('BUDGET-22-25 HRS & CIG'!B8-'BUDGET-22-25 HRS & CIG'!B4) +'BUDGET-22-25 HRS & CIG'!H8+'BUDGET-22-25 HRS & CIG'!N8+'BUDGET-22-25 HRS & CIG'!T8 +'BUDGET-22-25 HRS & CIG'!B12 +'BUDGET-22-25 HRS & CIG'!H12+'BUDGET-22-25 HRS & CIG'!N12+'BUDGET-22-25 HRS & CIG'!T12 -> 2400600 | H20: =('BUDGET-22-25 HRS & CIG'!$B$22-'BUDGET-22-25 HRS & CIG'!$B$12-'BUDGET-22-25 HRS & CIG'!$B$13)+('BUDGET-22-25 HRS & CIG'!$H$22-'BUDGET-22-25 HRS & CIG'!$H$12-'BUDGET-22-25 HRS & CIG'!$H$13)+('BUDGET-22-25 HRS & CIG'!$N$22-'BUDGET-22-25 HRS & CIG'!$N$12-'BUDGET-22-25 HRS & CIG'!$N$13)+('BUDGET-22-25 HRS & CIG'!$T$22-'BUDGET-22-25 HRS & CIG'!$T$12-'BUDGET-22-25 HRS & CIG'!$T$13) -> 533500 | I20: =Table1[[#This Row],[Total Annual Labor Budget (by business unit)]]+Table1[[#This Row],[Total Annual Controllable Expenses (by business unit)]] -> 2934100 | J20: ='BUDGET-22-25 HRS & CIG'!B37+'BUDGET-22-25 HRS & CIG'!H37+'BUDGET-22-25 HRS & CIG'!N37+'BUDGET-22-25 HRS & CIG'!T37 -> 16 | K20: =Table1[[#This Row],['# WLD (Units or Users)]]*Table1[[#This Row],[Cost per WLD/yr]] -> 31549.462 | L20: =(G20+H20)/Q20 -> 5258.2437 | M20: =L20/12 -> 438.18698 | N20: =Q20/J20 -> 34.875 | O20: =IF(Table1[[#This Row],[WL per Employee]]<=0,0,Table1[[#This Row],[Total Combined Expenses]]/Table1[[#This Row],[WL per Employee]]/Table1[[#This Row],[YE Unit Labor Headcount (FTE & SMP)]]) -> 5258.2437 | P20: =G20/J20 -> 150037.5 | Q20: ='Support Numbers'!B36 -> 558 | S20: =IF(Table1[[#This Row],['# WLD (Units or Users)]]=0,0,(G20+H20)/F20) -> 489016.67 | W20: =(G20+H20)/Q20 -> 5258.2437 | X20: Full life cycle HR support - hire to retire (onboarding, HRIS, personnel, training, offboarding) for ASBCO employees, temps, independent contractors
A21: 2022 | B21: HRS | C21: All HRS | D21: HR Support Services | E21: APM | F21: ='Support Numbers'!B28 -> 11 | G21: =('BUDGET-22-25 HRS & CIG'!B8-'BUDGET-22-25 HRS & CIG'!B4) +'BUDGET-22-25 HRS & CIG'!H8+'BUDGET-22-25 HRS & CIG'!N8+'BUDGET-22-25 HRS & CIG'!T8 +'BUDGET-22-25 HRS & CIG'!B12 +'BUDGET-22-25 HRS & CIG'!H12+'BUDGET-22-25 HRS & CIG'!N12+'BUDGET-22-25 HRS & CIG'!T12 -> 2400600 | H21: =('BUDGET-22-25 HRS & CIG'!$B$22-'BUDGET-22-25 HRS & CIG'!$B$12-'BUDGET-22-25 HRS & CIG'!$B$13)+('BUDGET-22-25 HRS & CIG'!$H$22-'BUDGET-22-25 HRS & CIG'!$H$12-'BUDGET-22-25 HRS & CIG'!$H$13)+('BUDGET-22-25 HRS & CIG'!$N$22-'BUDGET-22-25 HRS & CIG'!$N$12-'BUDGET-22-25 HRS & CIG'!$N$13)+('BUDGET-22-25 HRS & CIG'!$T$22-'BUDGET-22-25 HRS & CIG'!$T$12-'BUDGET-22-25 HRS & CIG'!$T$13) -> 533500 | I21: =Table1[[#This Row],[Total Annual Labor Budget (by business unit)]]+Table1[[#This Row],[Total Annual Controllable Expenses (by business unit)]] -> 2934100 | J21: ='BUDGET-22-25 HRS & CIG'!B37+'BUDGET-22-25 HRS & CIG'!H37+'BUDGET-22-25 HRS & CIG'!N37+'BUDGET-22-25 HRS & CIG'!T37 -> 16 | K21: =Table1[[#This Row],['# WLD (Units or Users)]]*Table1[[#This Row],[Cost per WLD/yr]] -> 57840.681 | L21: =(G21+H21)/Q21 -> 5258.2437 | M21: =L21/12 -> 438.18698 | N21: =Q21/J21 -> 34.875 | O21: =IF(Table1[[#This Row],[WL per Employee]]<=0,0,Table1[[#This Row],[Total Combined Expenses]]/Table1[[#This Row],[WL per Employee]]/Table1[[#This Row],[YE Unit Labor Headcount (FTE & SMP)]]) -> 5258.2437 | P21: =G21/J21 -> 150037.5 | Q21: ='Support Numbers'!B36 -> 558 | S21: =IF(Table1[[#This Row],['# WLD (Units or Users)]]=0,0,(G21+H21)/F21) -> 266736.36 | W21: =(G21+H21)/Q21 -> 5258.2437 | X21: Full life cycle HR support - hire to retire (onboarding, HRIS, personnel, training, offboarding) for APM employees, temps, independent contractors
A22: 2022 | B22: HRS | C22: All HRS | D22: HR Support Services | E22: ATA | F22: ='Support Numbers'!B31 -> 0 | G22: =('BUDGET-22-25 HRS & CIG'!B8-'BUDGET-22-25 HRS & CIG'!B4) +'BUDGET-22-25 HRS & CIG'!H8+'BUDGET-22-25 HRS & CIG'!N8+'BUDGET-22-25 HRS & CIG'!T8 +'BUDGET-22-25 HRS & CIG'!B12 +'BUDGET-22-25 HRS & CIG'!H12+'BUDGET-22-25 HRS & CIG'!N12+'BUDGET-22-25 HRS & CIG'!T12 -> 2400600 | H22: =('BUDGET-22-25 HRS & CIG'!$B$22-'BUDGET-22-25 HRS & CIG'!$B$12-'BUDGET-22-25 HRS & CIG'!$B$13)+('BUDGET-22-25 HRS & CIG'!$H$22-'BUDGET-22-25 HRS & CIG'!$H$12-'BUDGET-22-25 HRS & CIG'!$H$13)+('BUDGET-22-25 HRS & CIG'!$N$22-'BUDGET-22-25 HRS & CIG'!$N$12-'BUDGET-22-25 HRS & CIG'!$N$13)+('BUDGET-22-25 HRS & CIG'!$T$22-'BUDGET-22-25 HRS & CIG'!$T$12-'BUDGET-22-25 HRS & CIG'!$T$13) -> 533500 | I22: =Table1[[#This Row],[Total Annual Labor Budget (by business unit)]]+Table1[[#This Row],[Total Annual Controllable Expenses (by business unit)]] -> 2934100 | J22: ='BUDGET-22-25 HRS & CIG'!B37+'BUDGET-22-25 HRS & CIG'!H37+'BUDGET-22-25 HRS & CIG'!N37+'BUDGET-22-25 HRS & CIG'!T37 -> 16 | K22: =Table1[[#This Row],['# WLD (Units or Users)]]*Table1[[#This Row],[Cost per WLD/yr]] -> 0 | L22: =(G22+H22)/Q22 -> 5258.2437 | M22: =L22/12 -> 438.18698 | N22: =Q22/J22 -> 34.875 | O22: =IF(Table1[[#This Row],[WL per Employee]]<=0,0,Table1[[#This Row],[Total Combined Expenses]]/Table1[[#This Row],[WL per Employee]]/Table1[[#This Row],[YE Unit Labor Headcount (FTE & SMP)]]) -> 5258.2437 | P22: =G22/J22 -> 150037.5 | Q22: ='Support Numbers'!B36 -> 558 | S22: =IF(Table1[[#This Row],['# WLD (Units or Users)]]=0,0,(G22+H22)/F22) -> 0 | W22: =(G22+H22)/Q22 -> 5258.2437 | X22: Full life cycle HR support - hire to retire (onboarding, HRIS, personnel, training, offboarding) for ATA employees, temps, independent contractors
A23: 2022 | B23: HRS | C23: All HRS | D23: HR Support Services | E23: AVMCC | F23: ='Support Numbers'!B32 -> 5 | G23: =('BUDGET-22-25 HRS & CIG'!B8-'BUDGET-22-25 HRS & CIG'!B4) +'BUDGET-22-25 HRS & CIG'!H8+'BUDGET-22-25 HRS & CIG'!N8+'BUDGET-22-25 HRS & CIG'!T8 +'BUDGET-22-25 HRS & CIG'!B12 +'BUDGET-22-25 HRS & CIG'!H12+'BUDGET-22-25 HRS & CIG'!N12+'BUDGET-22-25 HRS & CIG'!T12 -> 2400600 | H23: =('BUDGET-22-25 HRS & CIG'!$B$22-'BUDGET-22-25 HRS & CIG'!$B$12-'BUDGET-22-25 HRS & CIG'!$B$13)+('BUDGET-22-25 HRS & CIG'!$H$22-'BUDGET-22-25 HRS & CIG'!$H$12-'BUDGET-22-25 HRS & CIG'!$H$13)+('BUDGET-22-25 HRS & CIG'!$N$22-'BUDGET-22-25 HRS & CIG'!$N$12-'BUDGET-22-25 HRS & CIG'!$N$13)+('BUDGET-22-25 HRS & CIG'!$T$22-'BUDGET-22-25 HRS & CIG'!$T$12-'BUDGET-22-25 HRS & CIG'!$T$13) -> 533500 | I23: =Table1[[#This Row],[Total Annual Labor Budget (by business unit)]]+Table1[[#This Row],[Total Annual Controllable Expenses (by business unit)]] -> 2934100 | J23: ='BUDGET-22-25 HRS & CIG'!B37+'BUDGET-22-25 HRS & CIG'!H37+'BUDGET-22-25 HRS & CIG'!N37+'BUDGET-22-25 HRS & CIG'!T37 -> 16 | K23: =Table1[[#This Row],['# WLD (Units or Users)]]*Table1[[#This Row],[Cost per WLD/yr]] -> 26291.219 | L23: =(G23+H23)/Q23 -> 5258.2437 | M23: =L23/12 -> 438.18698 | N23: =Q23/J23 -> 34.875 | O23: =IF(Table1[[#This Row],[WL per Employee]]<=0,0,Table1[[#This Row],[Total Combined Expenses]]/Table1[[#This Row],[WL per Employee]]/Table1[[#This Row],[YE Unit Labor Headcount (FTE & SMP)]]) -> 5258.2437 | P23: =G23/J23 -> 150037.5 | Q23: ='Support Numbers'!B36 -> 558 | S23: =IF(Table1[[#This Row],['# WLD (Units or Users)]]=0,0,(G23+H23)/F23) -> 586820 | W23: =(G23+H23)/Q23 -> 5258.2437 | X23: Full life cycle HR support - hire to retire (onboarding, HRIS, personnel, training, offboarding) for AVMCC employees, temps, independent contractors
A24: 2022 | B24: HRS | C24: All HRS | D24: HR Support Services | E24: SAEV | F24: ='Support Numbers'!B33 -> 10 | G24: =('BUDGET-22-25 HRS & CIG'!B8-'BUDGET-22-25 HRS & CIG'!B4) +'BUDGET-22-25 HRS & CIG'!H8+'BUDGET-22-25 HRS & CIG'!N8+'BUDGET-22-25 HRS & CIG'!T8 +'BUDGET-22-25 HRS & CIG'!B12 +'BUDGET-22-25 HRS & CIG'!H12+'BUDGET-22-25 HRS & CIG'!N12+'BUDGET-22-25 HRS & CIG'!T12 -> 2400600 | H24: =('BUDGET-22-25 HRS & CIG'!$B$22-'BUDGET-22-25 HRS & CIG'!$B$12-'BUDGET-22-25 HRS & CIG'!$B$13)+('BUDGET-22-25 HRS & CIG'!$H$22-'BUDGET-22-25 HRS & CIG'!$H$12-'BUDGET-22-25 HRS & CIG'!$H$13)+('BUDGET-22-25 HRS & CIG'!$N$22-'BUDGET-22-25 HRS & CIG'!$N$12-'BUDGET-22-25 HRS & CIG'!$N$13)+('BUDGET-22-25 HRS & CIG'!$T$22-'BUDGET-22-25 HRS & CIG'!$T$12-'BUDGET-22-25 HRS & CIG'!$T$13) -> 533500 | I24: =Table1[[#This Row],[Total Annual Labor Budget (by business unit)]]+Table1[[#This Row],[Total Annual Controllable Expenses (by business unit)]] -> 2934100 | J24: ='BUDGET-22-25 HRS & CIG'!B37+'BUDGET-22-25 HRS & CIG'!H37+'BUDGET-22-25 HRS & CIG'!N37+'BUDGET-22-25 HRS & CIG'!T37 -> 16 | K24: =Table1[[#This Row],['# WLD (Units or Users)]]*Table1[[#This Row],[Cost per WLD/yr]] -> 52582.437 | L24: =(G24+H24)/Q24 -> 5258.2437 | M24: =L24/12 -> 438.18698 | N24: =Q24/J24 -> 34.875 | O24: =IF(Table1[[#This Row],[WL per Employee]]<=0,0,Table1[[#This Row],[Total Combined Expenses]]/Table1[[#This Row],[WL per Employee]]/Table1[[#This Row],[YE Unit Labor Headcount (FTE & SMP)]]) -> 5258.2437 | P24: =G24/J24 -> 150037.5 | Q24: ='Support Numbers'!B36 -> 558 | S24: =IF(Table1[[#This Row],['# WLD (Units or Users)]]=0,0,(G24+H24)/F24) -> 293410 | W24: =(G24+H24)/Q24 -> 5258.2437 | X24: Full life cycle HR support - hire to retire (onboarding, HRIS, personnel, training, offboarding) for SAEV employees, temps, independent contractors
A25: 2022 | B25: HRS | C25: All HRS | D25: HR Support Services | E25: SRI | F25: ='Support Numbers'!B34 -> 4 | G25: =('BUDGET-22-25 HRS & CIG'!B8-'BUDGET-22-25 HRS & CIG'!B4) +'BUDGET-22-25 HRS & CIG'!H8+'BUDGET-22-25 HRS & CIG'!N8+'BUDGET-22-25 HRS & CIG'!T8 +'BUDGET-22-25 HRS & CIG'!B12 +'BUDGET-22-25 HRS & CIG'!H12+'BUDGET-22-25 HRS & CIG'!N12+'BUDGET-22-25 HRS & CIG'!T12 -> 2400600 | H25: =('BUDGET-22-25 HRS & CIG'!$B$22-'BUDGET-22-25 HRS & CIG'!$B$12-'BUDGET-22-25 HRS & CIG'!$B$13)+('BUDGET-22-25 HRS & CIG'!$H$22-'BUDGET-22-25 HRS & CIG'!$H$12-'BUDGET-22-25 HRS & CIG'!$H$13)+('BUDGET-22-25 HRS & CIG'!$N$22-'BUDGET-22-25 HRS & CIG'!$N$12-'BUDGET-22-25 HRS & CIG'!$N$13)+('BUDGET-22-25 HRS & CIG'!$T$22-'BUDGET-22-25 HRS & CIG'!$T$12-'BUDGET-22-25 HRS & CIG'!$T$13) -> 533500 | I25: =Table1[[#This Row],[Total Annual Labor Budget (by business unit)]]+Table1[[#This Row],[Total Annual Controllable Expenses (by business unit)]] -> 2934100 | J25: ='BUDGET-22-25 HRS & CIG'!B37+'BUDGET-22-25 HRS & CIG'!H37+'BUDGET-22-25 HRS & CIG'!N37+'BUDGET-22-25 HRS & CIG'!T37 -> 16 | K25: =Table1[[#This Row],['# WLD (Units or Users)]]*Table1[[#This Row],[Cost per WLD/yr]] -> 21032.975 | L25: =(G25+H25)/Q25 -> 5258.2437 | M25: =L25/12 -> 438.18698 | N25: =Q25/J25 -> 34.875 | O25: =IF(Table1[[#This Row],[WL per Employee]]<=0,0,Table1[[#This Row],[Total Combined Expenses]]/Table1[[#This Row],[WL per Employee]]/Table1[[#This Row],[YE Unit Labor Headcount (FTE & SMP)]]) -> 5258.2437 | P25: =G25/J25 -> 150037.5 | Q25: ='Support Numbers'!B36 -> 558 | S25: =IF(Table1[[#This Row],['# WLD (Units or Users)]]=0,0,(G25+H25)/F25) -> 733525 | W25: =(G25+H25)/Q25 -> 5258.2437 | X25: Full life cycle HR support - hire to retire (onboarding, HRIS, personnel, training, offboarding) for SRI employees, temps, independent contractors
A26: 2022 | B26: HRS | C26: All HRS | D26: HR Support Services | E26: SPII | F26: ='Support Numbers'!B35 -> 12 | G26: =('BUDGET-22-25 HRS & CIG'!B8-'BUDGET-22-25 HRS & CIG'!B4) +'BUDGET-22-25 HRS & CIG'!H8+'BUDGET-22-25 HRS & CIG'!N8+'BUDGET-22-25 HRS & CIG'!T8 +'BUDGET-22-25 HRS & CIG'!B12 +'BUDGET-22-25 HRS & CIG'!H12+'BUDGET-22-25 HRS & CIG'!N12+'BUDGET-22-25 HRS & CIG'!T12 -> 2400600 | H26: =('BUDGET-22-25 HRS & CIG'!$B$22-'BUDGET-22-25 HRS & CIG'!$B$12-'BUDGET-22-25 HRS & CIG'!$B$13)+('BUDGET-22-25 HRS & CIG'!$H$22-'BUDGET-22-25 HRS & CIG'!$H$12-'BUDGET-22-25 HRS & CIG'!$H$13)+('BUDGET-22-25 HRS & CIG'!$N$22-'BUDGET-22-25 HRS & CIG'!$N$12-'BUDGET-22-25 HRS & CIG'!$N$13)+('BUDGET-22-25 HRS & CIG'!$T$22-'BUDGET-22-25 HRS & CIG'!$T$12-'BUDGET-22-25 HRS & CIG'!$T$13) -> 533500 | I26: =Table1[[#This Row],[Total Annual Labor Budget (by business unit)]]+Table1[[#This Row],[Total Annual Controllable Expenses (by business unit)]] -> 2934100 | J26: ='BUDGET-22-25 HRS & CIG'!B37+'BUDGET-22-25 HRS & CIG'!H37+'BUDGET-22-25 HRS & CIG'!N37+'BUDGET-22-25 HRS & CIG'!T37 -> 16 | K26: =Table1[[#This Row],['# WLD (Units or Users)]]*Table1[[#This Row],[Cost per WLD/yr]] -> 63098.925 | L26: =(G26+H26)/Q26 -> 5258.2437 | M26: =L26/12 -> 438.18698 | N26: =Q26/J26 -> 34.875 | O26: =IF(Table1[[#This Row],[WL per Employee]]<=0,0,Table1[[#This Row],[Total Combined Expenses]]/Table1[[#This Row],[WL per Employee]]/Table1[[#This Row],[YE Unit Labor Headcount (FTE & SMP)]]) -> 5258.2437 | P26: =G26/J26 -> 150037.5 | Q26: ='Support Numbers'!B36 -> 558 | S26: =IF(Table1[[#This Row],['# WLD (Units or Users)]]=0,0,(G26+H26)/F26) -> 244508.33 | W26: =(G26+H26)/Q26 -> 5258.2437 | X26: Full life cycle HR support - hire to retire (onboarding, HRIS, personnel, training, offboarding)
A27: 2022 | B27: SSD | C27: Expat Recruitment | D27: Bundled Recruitment | E27: SAO | F27: ='Support Numbers'!B50 -> 500 | G27: ='BUDGET-22-25 SSD'!B8+'BUDGET-22-25 SSD'!B12+'BUDGET-22-25 SSD'!H8+'BUDGET-22-25 SSD'!H12+'BUDGET-22-25 SSD'!N8+'BUDGET-22-25 SSD'!N12+'BUDGET-22-25 SSD'!T8+'BUDGET-22-25 SSD'!T12+'BUDGET-22-25 SSD'!Z8+'BUDGET-22-25 SSD'!Z12 -> 2337500 | H27: =('BUDGET-22-25 SSD'!B9+'BUDGET-22-25 SSD'!B22+'BUDGET-22-25 SSD'!H9+'BUDGET-22-25 SSD'!H22+'BUDGET-22-25 SSD'!N9+'BUDGET-22-25 SSD'!N22+'BUDGET-22-25 SSD'!T9+'BUDGET-22-25 SSD'!T22+'BUDGET-22-25 SSD'!Z9+'BUDGET-22-25 SSD'!Z22) -'BUDGET-22-25 SSD'!B12-'BUDGET-22-25 SSD'!B13-'BUDGET-22-25 SSD'!H12-'BUDGET-22-25 SSD'!H13-'BUDGET-22-25 SSD'!N12-'BUDGET-22-25 SSD'!N13-'BUDGET-22-25 SSD'!T12-'BUDGET-22-25 SSD'!T13-'BUDGET-22-25 SSD'!Z12-'BUDGET-22-25 SSD'!Z13 -> 2645360 | I27: =Table1[[#This Row],[Total Annual Labor Budget (by business unit)]]+Table1[[#This Row],[Total Annual Controllable Expenses (by business unit)]] -> 4982860 | J27: ='BUDGET-22-25 SSD'!B40+'BUDGET-22-25 SSD'!B42 +'BUDGET-22-25 SSD'!H40+'BUDGET-22-25 SSD'!H42 +'BUDGET-22-25 SSD'!N40+'BUDGET-22-25 SSD'!N42 +'BUDGET-22-25 SSD'!T40+'BUDGET-22-25 SSD'!T42 +'BUDGET-22-25 SSD'!Z40+'BUDGET-22-25 SSD'!Z42 -> 21 | K27: =Table1[[#This Row],['# WLD (Units or Users)]]*Table1[[#This Row],[Cost per WLD/yr]] -> 4982860 | L27: =(G27+H27)/Q27 -> 9965.72 | M27: =L27/12 -> 830.47667 | N27: =Q27/J27 -> 23.809524 | O27: =IF(Table1[[#This Row],[WL per Employee]]<=0,0,Table1[[#This Row],[Total Combined Expenses]]/Table1[[#This Row],[WL per Employee]]/Table1[[#This Row],[YE Unit Labor Headcount (FTE & SMP)]]) -> 9965.72 | P27: =G27/J27 -> 111309.52 | Q27: =F27 -> 500 | S27: =IF(Table1[[#This Row],['# WLD (Units or Users)]]=0,0,(G27+H27)/F27) -> 9965.72 | W27: =(G27+H27)/Q27 -> 9965.72 | X27: International recruitment services (sourcing, attracting, full life cycle candidate management, workshop coordination)
A28: 2022 | B28: SSD | C28: Domestic Recruitment | D28: FTE SMP Recruitment | E28: ASC + RD | F28: ='Support Numbers'!B53 -> 60 | G28: ='BUDGET-22-25 SSD'!AF8+'BUDGET-22-25 SSD'!AF12 -> 395000 | H28: =('BUDGET-22-25 SSD'!AF9+'BUDGET-22-25 SSD'!AF22)-'BUDGET-22-25 SSD'!AF12-'BUDGET-22-25 SSD'!AF13 -> 62270 | I28: =Table1[[#This Row],[Total Annual Labor Budget (by business unit)]]+Table1[[#This Row],[Total Annual Controllable Expenses (by business unit)]] -> 457270 | J28: ='BUDGET-22-25 SSD'!AF40+'BUDGET-22-25 SSD'!AF42 -> 3 | K28: =Table1[[#This Row],['# WLD (Units or Users)]]*Table1[[#This Row],[Cost per WLD/yr]] -> 263809.62 | L28: =(G28+H28)/Q28 -> 4396.8269 | M28: =L28/12 -> 366.40224 | N28: =Q28/J28 -> 34.666667 | O28: =IF(Table1[[#This Row],[WL per Employee]]<=0,0,Table1[[#This Row],[Total Combined Expenses]]/Table1[[#This Row],[WL per Employee]]/Table1[[#This Row],[YE Unit Labor Headcount (FTE & SMP)]]) -> 4396.8269 | P28: =G28/J28 -> 131666.67 | Q28: ='Support Numbers'!B61 -> 104 | S28: =IF(Table1[[#This Row],['# WLD (Units or Users)]]=0,0,(G28+H28)/F28) -> 7621.1667 | W28: =(G28+H28)/Q28 -> 4396.8269 | X28: International recruitment services (sourcing, attracting, full life cycle candidate management, workshop coordination)
A29: 2022 | B29: SSD | C29: Domestic Recruitment | D29: SMP Recruitment | E29: PMT | F29: ='Support Numbers'!B54 -> 40 | G29: ='BUDGET-22-25 SSD'!AF8+'BUDGET-22-25 SSD'!AF12 -> 395000 | H29: =('BUDGET-22-25 SSD'!AF9+'BUDGET-22-25 SSD'!AF22)-'BUDGET-22-25 SSD'!AF12-'BUDGET-22-25 SSD'!AF13 -> 62270 | I29: =Table1[[#This Row],[Total Annual Labor Budget (by business unit)]]+Table1[[#This Row],[Total Annual Controllable Expenses (by business unit)]] -> 457270 | J29: ='BUDGET-22-25 SSD'!AF40+'BUDGET-22-25 SSD'!AF42 -> 3 | K29: =Table1[[#This Row],['# WLD (Units or Users)]]*Table1[[#This Row],[Cost per WLD/yr]] -> 175873.08 | L29: =(G29+H29)/Q29 -> 4396.8269 | M29: =L29/12 -> 366.40224 | N29: =Q29/J29 -> 34.666667 | O29: =IF(Table1[[#This Row],[WL per Employee]]<=0,0,Table1[[#This Row],[Total Combined Expenses]]/Table1[[#This Row],[WL per Employee]]/Table1[[#This Row],[YE Unit Labor Headcount (FTE & SMP)]]) -> 4396.8269 | P29: =G29/J29 -> 131666.67 | Q29: ='Support Numbers'!B61 -> 104 | S29: =IF(Table1[[#This Row],['# WLD (Units or Users)]]=0,0,(G29+H29)/F29) -> 11431.75 | W29: =(G29+H29)/Q29 -> 4396.8269 | X29: Full life cycle recruitment - sourcing, attraction, proponent and candidate management
A30: 2022 | B30: SSD | C30: Domestic Recruitment | D30: FTE SMP Recruitment | E30: AVMCC | F30: ='Support Numbers'!B55 -> 0 | G30: ='BUDGET-22-25 SSD'!AF8+'BUDGET-22-25 SSD'!AF12 -> 395000 | H30: =('BUDGET-22-25 SSD'!AF9+'BUDGET-22-25 SSD'!AF22)-'BUDGET-22-25 SSD'!AF12-'BUDGET-22-25 SSD'!AF13 -> 62270 | I30: =Table1[[#This Row],[Total Annual Labor Budget (by business unit)]]+Table1[[#This Row],[Total Annual Controllable Expenses (by business unit)]] -> 457270 | J30: ='BUDGET-22-25 SSD'!AF40+'BUDGET-22-25 SSD'!AF42 -> 3 | K30: =Table1[[#This Row],['# WLD (Units or Users)]]*Table1[[#This Row],[Cost per WLD/yr]] -> 0 | L30: =(G30+H30)/Q30 -> 4396.8269 | M30: =L30/12 -> 366.40224 | N30: =Q30/J30 -> 34.666667 | O30: =IF(Table1[[#This Row],[WL per Employee]]<=0,0,Table1[[#This Row],[Total Combined Expenses]]/Table1[[#This Row],[WL per Employee]]/Table1[[#This Row],[YE Unit Labor Headcount (FTE & SMP)]]) -> 4396.8269 | P30: =G30/J30 -> 131666.67 | Q30: ='Support Numbers'!B61 -> 104 | S30: =IF(Table1[[#This Row],['# WLD (Units or Users)]]=0,0,(G30+H30)/F30) -> 0 | W30: =(G30+H30)/Q30 -> 4396.8269 | X30: Managing recruitment for temporary PMT needs - sourcing, management of agency, candidates, and proponents
A31: 2022 | B31: SSD | C31: Domestic Recruitment | D31: FTE SMP Recruitment | E31: SAEV | F31: ='Support Numbers'!B56 -> 3 | G31: ='BUDGET-22-25 SSD'!AF8+'BUDGET-22-25 SSD'!AF12 -> 395000 | H31: =('BUDGET-22-25 SSD'!AF9+'BUDGET-22-25 SSD'!AF22)-'BUDGET-22-25 SSD'!AF12-'BUDGET-22-25 SSD'!AF13 -> 62270 | I31: =Table1[[#This Row],[Total Annual Labor Budget (by business unit)]]+Table1[[#This Row],[Total Annual Controllable Expenses (by business unit)]] -> 457270 | J31: ='BUDGET-22-25 SSD'!AF40+'BUDGET-22-25 SSD'!AF42 -> 3 | K31: =Table1[[#This Row],['# WLD (Units or Users)]]*Table1[[#This Row],[Cost per WLD/yr]] -> 13190.481 | L31: =(G31+H31)/Q31 -> 4396.8269 | M31: =L31/12 -> 366.40224 | N31: =Q31/J31 -> 34.666667 | O31: =IF(Table1[[#This Row],[WL per Employee]]<=0,0,Table1[[#This Row],[Total Combined Expenses]]/Table1[[#This Row],[WL per Employee]]/Table1[[#This Row],[YE Unit Labor Headcount (FTE & SMP)]]) -> 4396.8269 | P31: =G31/J31 -> 131666.67 | Q31: ='Support Numbers'!B61 -> 104 | S31: =IF(Table1[[#This Row],['# WLD (Units or Users)]]=0,0,(G31+H31)/F31) -> 152423.33 | W31: =(G31+H31)/Q31 -> 4396.8269 | X31: Full life cycle recruitment - sourcing, attraction, proponent and candidate management
A32: 2022 | B32: SSD | C32: Domestic Recruitment | D32: FTE SMP Recruitment | E32: SPII | F32: ='Support Numbers'!B57 -> 0 | G32: ='BUDGET-22-25 SSD'!AF8+'BUDGET-22-25 SSD'!AF12 -> 395000 | H32: =('BUDGET-22-25 SSD'!AF9+'BUDGET-22-25 SSD'!AF22)-'BUDGET-22-25 SSD'!AF12-'BUDGET-22-25 SSD'!AF13 -> 62270 | I32: =Table1[[#This Row],[Total Annual Labor Budget (by business unit)]]+Table1[[#This Row],[Total Annual Controllable Expenses (by business unit)]] -> 457270 | J32: ='BUDGET-22-25 SSD'!AF40+'BUDGET-22-25 SSD'!AF42 -> 3 | K32: =Table1[[#This Row],['# WLD (Units or Users)]]*Table1[[#This Row],[Cost per WLD/yr]] -> 0 | L32: =(G32+H32)/Q32 -> 4396.8269 | M32: =L32/12 -> 366.40224 | N32: =Q32/J32 -> 34.666667 | O32: =IF(Table1[[#This Row],[WL per Employee]]<=0,0,Table1[[#This Row],[Total Combined Expenses]]/Table1[[#This Row],[WL per Employee]]/Table1[[#This Row],[YE Unit Labor Headcount (FTE & SMP)]]) -> 4396.8269 | P32: =G32/J32 -> 131666.67 | Q32: ='Support Numbers'!B61 -> 104 | S32: =IF(Table1[[#This Row],['# WLD (Units or Users)]]=0,0,(G32+H32)/F32) -> 0 | W32: =(G32+H32)/Q32 -> 4396.8269 | X32: Full life cycle recruitment - sourcing, attraction, proponent and candidate management
A33: 2022 | B33: SSD | C33: Domestic Recruitment | D33: FTE SMP Recruitment | E33: SRI | F33: ='Support Numbers'!B58 -> 0 | G33: ='BUDGET-22-25 SSD'!AF8+'BUDGET-22-25 SSD'!AF12 -> 395000 | H33: =('BUDGET-22-25 SSD'!AF9+'BUDGET-22-25 SSD'!AF22)-'BUDGET-22-25 SSD'!AF12-'BUDGET-22-25 SSD'!AF13 -> 62270 | I33: =Table1[[#This Row],[Total Annual Labor Budget (by business unit)]]+Table1[[#This Row],[Total Annual Controllable Expenses (by business unit)]] -> 457270 | J33: ='BUDGET-22-25 SSD'!AF40+'BUDGET-22-25 SSD'!AF42 -> 3 | K33: =Table1[[#This Row],['# WLD (Units or Users)]]*Table1[[#This Row],[Cost per WLD/yr]] -> 0 | L33: =(G33+H33)/Q33 -> 4396.8269 | M33: =L33/12 -> 366.40224 | N33: =Q33/J33 -> 34.666667 | O33: =IF(Table1[[#This Row],[WL per Employee]]<=0,0,Table1[[#This Row],[Total Combined Expenses]]/Table1[[#This Row],[WL per Employee]]/Table1[[#This Row],[YE Unit Labor Headcount (FTE & SMP)]]) -> 4396.8269 | P33: =G33/J33 -> 131666.67 | Q33: ='Support Numbers'!B61 -> 104 | S33: =IF(Table1[[#This Row],['# WLD (Units or Users)]]=0,0,(G33+H33)/F33) -> 0 | W33: =(G33+H33)/Q33 -> 4396.8269 | X33: Full life cycle recruitment - sourcing, attraction, proponent and candidate management
A34: 2022 | B34: SSD | C34: Domestic Recruitment | D34: FTE SMP Recruitment | E34: ASBCO | F34: ='Support Numbers'!B59 -> 1 | G34: ='BUDGET-22-25 SSD'!AF8+'BUDGET-22-25 SSD'!AF12 -> 395000 | H34: =('BUDGET-22-25 SSD'!AF9+'BUDGET-22-25 SSD'!AF22)-'BUDGET-22-25 SSD'!AF12-'BUDGET-22-25 SSD'!AF13 -> 62270 | I34: =Table1[[#This Row],[Total Annual Labor Budget (by business unit)]]+Table1[[#This Row],[Total Annual Controllable Expenses (by business unit)]] -> 457270 | J34: ='BUDGET-22-25 SSD'!AF40+'BUDGET-22-25 SSD'!AF42 -> 3 | K34: =Table1[[#This Row],['# WLD (Units or Users)]]*Table1[[#This Row],[Cost per WLD/yr]] -> 4396.8269 | L34: =(G34+H34)/Q34 -> 4396.8269 | M34: =L34/12 -> 366.40224 | N34: =Q34/J34 -> 34.666667 | O34: =IF(Table1[[#This Row],[WL per Employee]]<=0,0,Table1[[#This Row],[Total Combined Expenses]]/Table1[[#This Row],[WL per Employee]]/Table1[[#This Row],[YE Unit Labor Headcount (FTE & SMP)]]) -> 4396.8269 | P34: =G34/J34 -> 131666.67 | Q34: ='Support Numbers'!B61 -> 104 | S34: =IF(Table1[[#This Row],['# WLD (Units or Users)]]=0,0,(G34+H34)/F34) -> 457270 | W34: =(G34+H34)/Q34 -> 4396.8269 | X34: Full life cycle recruitment - sourcing, attraction, proponent and candidate management
A35: 2022 | B35: SSD | C35: Domestic Recruitment | D35: FTE SMP Recruitment | E35: ATA | F35: ='Support Numbers'!B60 -> 0 | G35: ='BUDGET-22-25 SSD'!AF8+'BUDGET-22-25 SSD'!AF12 -> 395000 | H35: =('BUDGET-22-25 SSD'!AF9+'BUDGET-22-25 SSD'!AF22)-'BUDGET-22-25 SSD'!AF12-'BUDGET-22-25 SSD'!AF13 -> 62270 | I35: =Table1[[#This Row],[Total Annual Labor Budget (by business unit)]]+Table1[[#This Row],[Total Annual Controllable Expenses (by business unit)]] -> 457270 | J35: ='BUDGET-22-25 SSD'!AF40+'BUDGET-22-25 SSD'!AF42 -> 3 | K35: =Table1[[#This Row],['# WLD (Units or Users)]]*Table1[[#This Row],[Cost per WLD/yr]] -> 0 | L35: =(G35+H35)/Q35 -> 4396.8269 | M35: =L35/12 -> 366.40224 | N35: =Q35/J35 -> 34.666667 | O35: =IF(Table1[[#This Row],[WL per Employee]]<=0,0,Table1[[#This Row],[Total Combined Expenses]]/Table1[[#This Row],[WL per Employee]]/Table1[[#This Row],[YE Unit Labor Headcount (FTE & SMP)]]) -> 4396.8269 | P35: =G35/J35 -> 131666.67 | Q35: ='Support Numbers'!B61 -> 104 | S35: =IF(Table1[[#This Row],['# WLD (Units or Users)]]=0,0,(G35+H35)/F35) -> 0 | W35: =(G35+H35)/Q35 -> 4396.8269 | X35: Full life cycle recruitment - sourcing, attraction, proponent and candidate management
A36: 2022 | B36: CIG | C36: Background Investigations | D36: Expat Hiring | E36: SAO HR SSD | F36: ='Support Numbers'!B70 -> 300 | G36: ='BUDGET-22-25 HRS & CIG'!AF8+'BUDGET-22-25 HRS & CIG'!AF12 -> 410000 | H36: ='BUDGET-22-25 HRS & CIG'!AF9+'BUDGET-22-25 HRS & CIG'!AF22-'BUDGET-22-25 HRS & CIG'!AF12 -> 2004900 | I36: =Table1[[#This Row],[Total Annual Labor Budget (by business unit)]]+Table1[[#This Row],[Total Annual Controllable Expenses (by business unit)]] -> 2414900 | J36: ='BUDGET-22-25 HRS & CIG'!AF38-'BUDGET-22-25 HRS & CIG'!AF40 -> 4 | K36: =Table1[[#This Row],['# WLD (Units or Users)]]*Table1[[#This Row],[Cost per WLD/yr]] -> 452793.75 | L36: =(G36+H36)/Q36 -> 1509.3125 | M36: =L36/12 -> 125.77604 | N36: =Q36/J36 -> 400 | O36: =IF(Table1[[#This Row],[WL per Employee]]<=0,0,Table1[[#This Row],[Total Combined Expenses]]/Table1[[#This Row],[WL per Employee]]/Table1[[#This Row],[YE Unit Labor Headcount (FTE & SMP)]]) -> 1509.3125 | P36: =G36/J36 -> 102500 | Q36: ='Support Numbers'!B74 -> 1600 | S36: =IF(Table1[[#This Row],['# WLD (Units or Users)]]=0,0,(G36+H36)/F36) -> 8049.6667 | W36: =(G36+H36)/Q36 -> 1509.3125 | X36: Background checks initated for candidates consenting to checking at time of technically qualified and all candidates at offer accepted.
A37: 2022 | B37: CIG | C37: Background Investigations | D37: Domestic | E37: ASC+ATA | F37: ='Support Numbers'!B71 -> 150 | G37: ='BUDGET-22-25 HRS & CIG'!AF8+'BUDGET-22-25 HRS & CIG'!AF12 -> 410000 | H37: ='BUDGET-22-25 HRS & CIG'!AF9+'BUDGET-22-25 HRS & CIG'!AF22-'BUDGET-22-25 HRS & CIG'!AF12 -> 2004900 | I37: =Table1[[#This Row],[Total Annual Labor Budget (by business unit)]]+Table1[[#This Row],[Total Annual Controllable Expenses (by business unit)]] -> 2414900 | J37: ='BUDGET-22-25 HRS & CIG'!AF38-'BUDGET-22-25 HRS & CIG'!AF40 -> 4 | K37: =Table1[[#This Row],['# WLD (Units or Users)]]*Table1[[#This Row],[Cost per WLD/yr]] -> 226396.88 | L37: =(G37+H37)/Q37 -> 1509.3125 | M37: =L37/12 -> 125.77604 | N37: =Q37/J37 -> 400 | O37: =IF(Table1[[#This Row],[WL per Employee]]<=0,0,Table1[[#This Row],[Total Combined Expenses]]/Table1[[#This Row],[WL per Employee]]/Table1[[#This Row],[YE Unit Labor Headcount (FTE & SMP)]]) -> 1509.3125 | P37: =G37/J37 -> 102500 | Q37: ='Support Numbers'!B74 -> 1600 | S37: =IF(Table1[[#This Row],['# WLD (Units or Users)]]=0,0,(G37+H37)/F37) -> 16099.333 | W37: =(G37+H37)/Q37 -> 1509.3125 | X37: Background checks for all domestic hiring efforts
A38: 2022 | B38: CIG | C38: Background Investigations | D38: SAO Corp Security | E38: SAO Corp Security | F38: ='Support Numbers'!B72 -> 1000 | G38: ='BUDGET-22-25 HRS & CIG'!AF8+'BUDGET-22-25 HRS & CIG'!AF12 -> 410000 | H38: ='BUDGET-22-25 HRS & CIG'!AF9+'BUDGET-22-25 HRS & CIG'!AF22-'BUDGET-22-25 HRS & CIG'!AF12 -> 2004900 | I38: =Table1[[#This Row],[Total Annual Labor Budget (by business unit)]]+Table1[[#This Row],[Total Annual Controllable Expenses (by business unit)]] -> 2414900 | J38: ='BUDGET-22-25 HRS & CIG'!AF38-'BUDGET-22-25 HRS & CIG'!AF40 -> 4 | K38: =Table1[[#This Row],['# WLD (Units or Users)]]*Table1[[#This Row],[Cost per WLD/yr]] -> 1509312.5 | L38: =(G38+H38)/Q38 -> 1509.3125 | M38: =L38/12 -> 125.77604 | N38: =Q38/J38 -> 400 | O38: =IF(Table1[[#This Row],[WL per Employee]]<=0,0,Table1[[#This Row],[Total Combined Expenses]]/Table1[[#This Row],[WL per Employee]]/Table1[[#This Row],[YE Unit Labor Headcount (FTE & SMP)]]) -> 1509.3125 | P38: =G38/J38 -> 102500 | Q38: ='Support Numbers'!B74 -> 1600 | S38: =IF(Table1[[#This Row],['# WLD (Units or Users)]]=0,0,(G38+H38)/F38) -> 2414.9 | W38: =(G38+H38)/Q38 -> 1509.3125 | X38: Background checks initiated and completed for Saudi students who studied in the US/Canada and applied for jobs at Saudi Aramco upon returning home.
A39: 2022 | B39: CIG | C39: Background Investigations | D39: Special Inv. Requests | E39: Misc. | F39: ='Support Numbers'!B73 -> 150 | G39: ='BUDGET-22-25 HRS & CIG'!AF8+'BUDGET-22-25 HRS & CIG'!AF12 -> 410000 | H39: ='BUDGET-22-25 HRS & CIG'!AF9+'BUDGET-22-25 HRS & CIG'!AF22-'BUDGET-22-25 HRS & CIG'!AF12 -> 2004900 | I39: =Table1[[#This Row],[Total Annual Labor Budget (by business unit)]]+Table1[[#This Row],[Total Annual Controllable Expenses (by business unit)]] -> 2414900 | J39: ='BUDGET-22-25 HRS & CIG'!AF38-'BUDGET-22-25 HRS & CIG'!AF40 -> 4 | K39: =Table1[[#This Row],['# WLD (Units or Users)]]*Table1[[#This Row],[Cost per WLD/yr]] -> 226396.88 | L39: =(G39+H39)/Q39 -> 1509.3125 | M39: =L39/12 -> 125.77604 | N39: =Q39/J39 -> 400 | O39: =IF(Table1[[#This Row],[WL per Employee]]<=0,0,Table1[[#This Row],[Total Combined Expenses]]/Table1[[#This Row],[WL per Employee]]/Table1[[#This Row],[YE Unit Labor Headcount (FTE & SMP)]]) -> 1509.3125 | P39: =G39/J39 -> 102500 | Q39: ='Support Numbers'!B74 -> 1600 | S39: =IF(Table1[[#This Row],['# WLD (Units or Users)]]=0,0,(G39+H39)/F39) -> 16099.333 | W39: =(G39+H39)/Q39 -> 1509.3125 | X39: Includes criminal history reports for consulates, help with relocating employees' families, and investigative consultation for stakeholders like SAEV and Audit.
A40: 2023 | B40: ATPD | C40: HR Support Services | D40: CH8 Support | E40: ASC + RD | F40: ='Support Numbers'!C2 -> 50 | G40: ='Support Numbers'!C64+('BUDGET-22-25 ATPD'!AA11*0.5) -> 245000 | H40: =(('BUDGET-22-25 ATPD'!AA22-'BUDGET-22-25 ATPD'!AA13-'BUDGET-22-25 ATPD'!AA12)*0.5)+'Support Numbers'!C80 -> 109500 | I40: =Table1[[#This Row],[Total Annual Labor Budget (by business unit)]]+Table1[[#This Row],[Total Annual Controllable Expenses (by business unit)]] -> 354500 | J40: 2.5 | K40: =Table1[[#This Row],['# WLD (Units or Users)]]*Table1[[#This Row],[Cost per WLD/yr]] -> 94786.096 | L40: =(G40+H40)/Q40 -> 1895.7219 | M40: =L40/12 -> 157.97683 | N40: =Q40/J40 -> 74.8 | O40: =IF(Table1[[#This Row],[WL per Employee]]<=0,0,Table1[[#This Row],[Total Combined Expenses]]/Table1[[#This Row],[WL per Employee]]/Table1[[#This Row],[YE Unit Labor Headcount (FTE & SMP)]]) -> 1895.7219 | P40: =G40/J40 -> 98000 | Q40: ='Support Numbers'!C12 -> 187 | S40: =IF(Table1[[#This Row],['# WLD (Units or Users)]]=0,0,(G40+H40)/F40) -> 7090 | W40: =(G40+H40)/Q40 -> 1895.7219 | X40: Onboarding, ongoing, and offboarding support of seconded CH8 employees
A41: 2023 | B41: ATPD | C41: HR Support Services | D41: CH8 Support | E41: SAEV | F41: ='Support Numbers'!C4 -> 0 | G41: ='Support Numbers'!C64+('BUDGET-22-25 ATPD'!AA11*0.5) -> 245000 | H41: =('BUDGET-22-25 ATPD'!AA22-'BUDGET-22-25 ATPD'!AA13-'BUDGET-22-25 ATPD'!AA12)*0.5+'Support Numbers'!C80 -> 109500 | I41: =Table1[[#This Row],[Total Annual Labor Budget (by business unit)]]+Table1[[#This Row],[Total Annual Controllable Expenses (by business unit)]] -> 354500 | J41: 2.5 | K41: =Table1[[#This Row],['# WLD (Units or Users)]]*Table1[[#This Row],[Cost per WLD/yr]] -> 0 | L41: =(G41+H41)/Q41 -> 1895.7219 | M41: =L41/12 -> 157.97683 | N41: =Q41/J41 -> 74.8 | O41: =IF(Table1[[#This Row],[WL per Employee]]<=0,0,Table1[[#This Row],[Total Combined Expenses]]/Table1[[#This Row],[WL per Employee]]/Table1[[#This Row],[YE Unit Labor Headcount (FTE & SMP)]]) -> 1895.7219 | P41: =G41/J41 -> 98000 | Q41: ='Support Numbers'!C12 -> 187 | S41: =IF(Table1[[#This Row],['# WLD (Units or Users)]]=0,0,(G41+H41)/F41) -> 0 | W41: =(G41+H41)/Q41 -> 1895.7219 | X41: Onboarding, ongoing, and offboarding support of seconded CH8 employees
A42: 2023 | B42: ATPD | C42: HR Support Services | D42: CH8 Support | E42: SPII | F42: ='Support Numbers'!C8 -> 3 | G42: ='Support Numbers'!C64+('BUDGET-22-25 ATPD'!AA11*0.5) -> 245000 | H42: =('BUDGET-22-25 ATPD'!AA22-'BUDGET-22-25 ATPD'!AA13-'BUDGET-22-25 ATPD'!AA12)*0.5+'Support Numbers'!C80 -> 109500 | I42: =Table1[[#This Row],[Total Annual Labor Budget (by business unit)]]+Table1[[#This Row],[Total Annual Controllable Expenses (by business unit)]] -> 354500 | J42: 2.5 | K42: =Table1[[#This Row],['# WLD (Units or Users)]]*Table1[[#This Row],[Cost per WLD/yr]] -> 5687.1658 | L42: =(G42+H42)/Q42 -> 1895.7219 | M42: =L42/12 -> 157.97683 | N42: =Q42/J42 -> 74.8 | O42: =IF(Table1[[#This Row],[WL per Employee]]<=0,0,Table1[[#This Row],[Total Combined Expenses]]/Table1[[#This Row],[WL per Employee]]/Table1[[#This Row],[YE Unit Labor Headcount (FTE & SMP)]]) -> 1895.7219 | P42: =G42/J42 -> 98000 | Q42: ='Support Numbers'!C12 -> 187 | S42: =IF(Table1[[#This Row],['# WLD (Units or Users)]]=0,0,(G42+H42)/F42) -> 118166.67 | W42: =(G42+H42)/Q42 -> 1895.7219 | X42: Onboarding, ongoing, and offboarding support of seconded CH8 employees
A43: 2023 | B43: ATPD | C43: HR Support Services | D43: CH8 Support | E43: VGO | F43: ='Support Numbers'!C10 -> 0 | G43: ='Support Numbers'!C64+('BUDGET-22-25 ATPD'!AA11*0.5) -> 245000 | H43: =('BUDGET-22-25 ATPD'!AA22-'BUDGET-22-25 ATPD'!AA13-'BUDGET-22-25 ATPD'!AA12)*0.5+'Support Numbers'!C80 -> 109500 | I43: =Table1[[#This Row],[Total Annual Labor Budget (by business unit)]]+Table1[[#This Row],[Total Annual Controllable Expenses (by business unit)]] -> 354500 | J43: 2.5 | K43: =Table1[[#This Row],['# WLD (Units or Users)]]*Table1[[#This Row],[Cost per WLD/yr]] -> 0 | L43: =(G43+H43)/Q43 -> 1895.7219 | M43: =L43/12 -> 157.97683 | N43: =Q43/J43 -> 74.8 | O43: =IF(Table1[[#This Row],[WL per Employee]]<=0,0,Table1[[#This Row],[Total Combined Expenses]]/Table1[[#This Row],[WL per Employee]]/Table1[[#This Row],[YE Unit Labor Headcount (FTE & SMP)]]) -> 1895.7219 | P43: =G43/J43 -> 98000 | Q43: ='Support Numbers'!C12 -> 187 | S43: =IF(Table1[[#This Row],['# WLD (Units or Users)]]=0,0,(G43+H43)/F43) -> 0 | W43: =(G43+H43)/Q43 -> 1895.7219 | X43: Onboarding, ongoing, and offboarding support of seconded CH8 employees
A44: 2023 | B44: ATPD | C44: HR Support Services | D44: CH8 Support | E44: Motiva | F44: ='Support Numbers'!C7 -> 3 | G44: ='Support Numbers'!C64+('BUDGET-22-25 ATPD'!AA11*0.5) -> 245000 | H44: =('BUDGET-22-25 ATPD'!AA22-'BUDGET-22-25 ATPD'!AA13-'BUDGET-22-25 ATPD'!AA12)*0.5+'Support Numbers'!C80 -> 109500 | I44: =Table1[[#This Row],[Total Annual Labor Budget (by business unit)]]+Table1[[#This Row],[Total Annual Controllable Expenses (by business unit)]] -> 354500 | J44: 2.5 | K44: =Table1[[#This Row],['# WLD (Units or Users)]]*Table1[[#This Row],[Cost per WLD/yr]] -> 5687.1658 | L44: =(G44+H44)/Q44 -> 1895.7219 | M44: =L44/12 -> 157.97683 | N44: =Q44/J44 -> 74.8 | O44: =IF(Table1[[#This Row],[WL per Employee]]<=0,0,Table1[[#This Row],[Total Combined Expenses]]/Table1[[#This Row],[WL per Employee]]/Table1[[#This Row],[YE Unit Labor Headcount (FTE & SMP)]]) -> 1895.7219 | P44: =G44/J44 -> 98000 | Q44: ='Support Numbers'!C12 -> 187 | S44: =IF(Table1[[#This Row],['# WLD (Units or Users)]]=0,0,(G44+H44)/F44) -> 118166.67 | W44: =(G44+H44)/Q44 -> 1895.7219 | X44: Onboarding, ongoing, and offboarding support of seconded CH8 employees
A45: 2023 | B45: ATPD | C45: HR Support Services | D45: CH8 Support | E45: PMT | F45: ='Support Numbers'!C9 -> 80 | G45: ='Support Numbers'!C64+('BUDGET-22-25 ATPD'!AA11*0.5) -> 245000 | H45: =('BUDGET-22-25 ATPD'!AA22-'BUDGET-22-25 ATPD'!AA13-'BUDGET-22-25 ATPD'!AA12)*0.5+'Support Numbers'!C80 -> 109500 | I45: =Table1[[#This Row],[Total Annual Labor Budget (by business unit)]]+Table1[[#This Row],[Total Annual Controllable Expenses (by business unit)]] -> 354500 | J45: 2.5 | K45: =Table1[[#This Row],['# WLD (Units or Users)]]*Table1[[#This Row],[Cost per WLD/yr]] -> 151657.75 | L45: =(G45+H45)/Q45 -> 1895.7219 | M45: =L45/12 -> 157.97683 | N45: =Q45/J45 -> 74.8 | O45: =IF(Table1[[#This Row],[WL per Employee]]<=0,0,Table1[[#This Row],[Total Combined Expenses]]/Table1[[#This Row],[WL per Employee]]/Table1[[#This Row],[YE Unit Labor Headcount (FTE & SMP)]]) -> 1895.7219 | P45: =G45/J45 -> 98000 | Q45: ='Support Numbers'!C12 -> 187 | S45: =IF(Table1[[#This Row],['# WLD (Units or Users)]]=0,0,(G45+H45)/F45) -> 4431.25 | W45: =(G45+H45)/Q45 -> 1895.7219 | X45: Onboarding, ongoing, and offboarding support of seconded CH8 employees
A46: 2023 | B46: ATPD | C46: HR Support Services | D46: CH8 Support | E46: Internships | F46: ='Support Numbers'!C11 -> 50 | G46: ='Support Numbers'!C64+('BUDGET-22-25 ATPD'!AA11*0.5) -> 245000 | H46: =('BUDGET-22-25 ATPD'!AA22-'BUDGET-22-25 ATPD'!AA13-'BUDGET-22-25 ATPD'!AA12)*0.5+'Support Numbers'!C80 -> 109500 | I46: =Table1[[#This Row],[Total Annual Labor Budget (by business unit)]]+Table1[[#This Row],[Total Annual Controllable Expenses (by business unit)]] -> 354500 | J46: 2.5 | K46: =Table1[[#This Row],['# WLD (Units or Users)]]*Table1[[#This Row],[Cost per WLD/yr]] -> 94786.096 | L46: =(G46+H46)/Q46 -> 1895.7219 | M46: =L46/12 -> 157.97683 | N46: =Q46/J46 -> 74.8 | O46: =IF(Table1[[#This Row],[WL per Employee]]<=0,0,Table1[[#This Row],[Total Combined Expenses]]/Table1[[#This Row],[WL per Employee]]/Table1[[#This Row],[YE Unit Labor Headcount (FTE & SMP)]]) -> 1895.7219 | P46: =G46/J46 -> 98000 | Q46: ='Support Numbers'!C12 -> 187 | S46: =IF(Table1[[#This Row],['# WLD (Units or Users)]]=0,0,(G46+H46)/F46) -> 7090 | W46: =(G46+H46)/Q46 -> 1895.7219 | X46: Onboarding, ongoing, and offboarding support of seconded CH8 employees
A47: 2023 | B47: ATPD | C47: HR Support Services | D47: CH8 Support | E47: SRI | F47: ='Support Numbers'!C6 -> 0 | G47: ='Support Numbers'!C64+('BUDGET-22-25 ATPD'!AA11*0.5) -> 245000 | H47: =('BUDGET-22-25 ATPD'!AA22-'BUDGET-22-25 ATPD'!AA13-'BUDGET-22-25 ATPD'!AA12)*0.5+'Support Numbers'!C80 -> 109500 | I47: =Table1[[#This Row],[Total Annual Labor Budget (by business unit)]]+Table1[[#This Row],[Total Annual Controllable Expenses (by business unit)]] -> 354500 | J47: 2.5 | K47: =Table1[[#This Row],['# WLD (Units or Users)]]*Table1[[#This Row],[Cost per WLD/yr]] -> 0 | L47: =(G47+H47)/Q47 -> 1895.7219 | M47: =L47/12 -> 157.97683 | N47: =Q47/J47 -> 74.8 | O47: =IF(Table1[[#This Row],[WL per Employee]]<=0,0,Table1[[#This Row],[Total Combined Expenses]]/Table1[[#This Row],[WL per Employee]]/Table1[[#This Row],[YE Unit Labor Headcount (FTE & SMP)]]) -> 1895.7219 | P47: =G47/J47 -> 98000 | Q47: ='Support Numbers'!C12 -> 187 | S47: =IF(Table1[[#This Row],['# WLD (Units or Users)]]=0,0,(G47+H47)/F47) -> 0 | W47: =(G47+H47)/Q47 -> 1895.7219 | X47: Onboarding, ongoing, and offboarding support of seconded CH8 employees
A48: 2023 | B48: ATPD | C48: HR Support Services | D48: CH8 Support | E48: NEX | F48: ='Support Numbers'!C5 -> 1 | G48: ='Support Numbers'!C64+('BUDGET-22-25 ATPD'!AA11*0.5) -> 245000 | H48: =('BUDGET-22-25 ATPD'!AA22-'BUDGET-22-25 ATPD'!AA13-'BUDGET-22-25 ATPD'!AA12)*0.5+'Support Numbers'!C80 -> 109500 | I48: =Table1[[#This Row],[Total Annual Labor Budget (by business unit)]]+Table1[[#This Row],[Total Annual Controllable Expenses (by business unit)]] -> 354500 | J48: 2.5 | K48: =Table1[[#This Row],['# WLD (Units or Users)]]*Table1[[#This Row],[Cost per WLD/yr]] -> 1895.7219 | L48: =(G48+H48)/Q48 -> 1895.7219 | M48: =L48/12 -> 157.97683 | N48: =Q48/J48 -> 74.8 | O48: =IF(Table1[[#This Row],[WL per Employee]]<=0,0,Table1[[#This Row],[Total Combined Expenses]]/Table1[[#This Row],[WL per Employee]]/Table1[[#This Row],[YE Unit Labor Headcount (FTE & SMP)]]) -> 1895.7219 | P48: =G48/J48 -> 98000 | Q48: ='Support Numbers'!C12 -> 187 | S48: =IF(Table1[[#This Row],['# WLD (Units or Users)]]=0,0,(G48+H48)/F48) -> 354500 | W48: =(G48+H48)/Q48 -> 1895.7219 | X48: Onboarding, ongoing, and offboarding support of seconded CH8 employees
A49: 2023 | B49: ATPD | C49: HR Support Services | D49: Medical Referral | E49: Medical Referrals | F49: ='Support Numbers'!C19 -> 25 | G49: ='Support Numbers'!C65 -> 115000 | H49: =('BUDGET-22-25 ATPD'!AA22-'BUDGET-22-25 ATPD'!AA13-'BUDGET-22-25 ATPD'!AA12)*0.5 -> 34500 | I49: =Table1[[#This Row],[Total Annual Labor Budget (by business unit)]]+Table1[[#This Row],[Total Annual Controllable Expenses (by business unit)]] -> 149500 | J49: 1 | K49: =Table1[[#This Row],['# WLD (Units or Users)]]*Table1[[#This Row],[Cost per WLD/yr]] -> 149500 | L49: =(G49+H49)/Q49 -> 5980 | M49: =L49/12 -> 498.33333 | N49: =Q49/J49 -> 25 | O49: =IF(Table1[[#This Row],[WL per Employee]]<=0,0,Table1[[#This Row],[Total Combined Expenses]]/Table1[[#This Row],[WL per Employee]]/Table1[[#This Row],[YE Unit Labor Headcount (FTE & SMP)]]) -> 5980 | P49: =G49/J49 -> 115000 | Q49: ='Support Numbers'!C19 -> 25 | S49: =IF(Table1[[#This Row],['# WLD (Units or Users)]]=0,0,(G49+H49)/F49) -> 5980 | W49: =(G49+H49)/Q49 -> 5980 | X49: Coordination of medical referral patience and programs
A50: 2023 | B50: ATPD | C50: HR Support Services | D50: CH14 Fin Support | E50: All Students | F50: ='Support Numbers'!C18 -> 1270 | G50: ='Support Numbers'!C66+('BUDGET-22-25 ATPD'!AA11*0.5) -> 165000 | H50: =('BUDGET-22-25 ATPD'!AA22-'BUDGET-22-25 ATPD'!AA13-'BUDGET-22-25 ATPD'!AA12)*0.5 -> 34500 | I50: =Table1[[#This Row],[Total Annual Labor Budget (by business unit)]]+Table1[[#This Row],[Total Annual Controllable Expenses (by business unit)]] -> 199500 | J50: 2 | K50: =Table1[[#This Row],['# WLD (Units or Users)]]*Table1[[#This Row],[Cost per WLD/yr]] -> 199500 | L50: =(G50+H50)/Q50 -> 157.08661 | M50: =L50/12 -> 13.090551 | N50: =Q50/J50 -> 635 | O50: =IF(Table1[[#This Row],[WL per Employee]]<=0,0,Table1[[#This Row],[Total Combined Expenses]]/Table1[[#This Row],[WL per Employee]]/Table1[[#This Row],[YE Unit Labor Headcount (FTE & SMP)]]) -> 157.08661 | P50: =G50/J50 -> 82500 | Q50: =F50 -> 1270 | S50: =IF(Table1[[#This Row],['# WLD (Units or Users)]]=0,0,(G50+H50)/F50) -> 157.08661 | W50: =(G50+H50)/Q50 -> 157.08661 | X50: Help desk for all students inqueries
A51: 2023 | B51: ATPD | C51: Academic Prog | D51: CH14 Advisory | E51: Undergrad | F51: ='Support Numbers'!C15 -> 900 | G51: ='BUDGET-22-25 ATPD'!O8+'BUDGET-22-25 ATPD'!O12 -> 1212000 | H51: =('BUDGET-22-25 ATPD'!O9+'BUDGET-22-25 ATPD'!O22)-'BUDGET-22-25 ATPD'!O12-'BUDGET-22-25 ATPD'!O13+'Support Numbers'!C78 -> 526600 | I51: =Table1[[#This Row],[Total Annual Labor Budget (by business unit)]]+Table1[[#This Row],[Total Annual Controllable Expenses (by business unit)]] -> 1738600 | J51: ='BUDGET-22-25 ATPD'!O40+'BUDGET-22-25 ATPD'!O42 -> 10 | K51: =Table1[[#This Row],['# WLD (Units or Users)]]*Table1[[#This Row],[Cost per WLD/yr]] -> 1232078.7 | L51: =(G51+H51)/Q51 -> 1368.9764 | M51: =L51/12 -> 114.08136 | N51: =Q51/J51 -> 127 | O51: =IF(Table1[[#This Row],[WL per Employee]]<=0,0,Table1[[#This Row],[Total Combined Expenses]]/Table1[[#This Row],[WL per Employee]]/Table1[[#This Row],[YE Unit Labor Headcount (FTE & SMP)]]) -> 1368.9764 | P51: =G51/J51 -> 121200 | Q51: ='Support Numbers'!C18 -> 1270 | S51: =IF(Table1[[#This Row],['# WLD (Units or Users)]]=0,0,(G51+H51)/F51) -> 1931.7778 | W51: =(G51+H51)/Q51 -> 1368.9764 | X51: Academic advisory for SAO sponsored students in an Undergrad program
A52: 2023 | B52: ATPD | C52: Academic Prog | D52: CH14 Advisory | E52: Associates | F52: ='Support Numbers'!C16 -> 40 | G52: ='BUDGET-22-25 ATPD'!O8+'BUDGET-22-25 ATPD'!O12 -> 1212000 | H52: =(('BUDGET-22-25 ATPD'!O9+'BUDGET-22-25 ATPD'!O22)-'BUDGET-22-25 ATPD'!O12-'BUDGET-22-25 ATPD'!O13)+'Support Numbers'!C78 -> 526600 | I52: =Table1[[#This Row],[Total Annual Labor Budget (by business unit)]]+Table1[[#This Row],[Total Annual Controllable Expenses (by business unit)]] -> 1738600 | J52: ='BUDGET-22-25 ATPD'!O40+'BUDGET-22-25 ATPD'!O42 -> 10 | K52: =Table1[[#This Row],['# WLD (Units or Users)]]*Table1[[#This Row],[Cost per WLD/yr]] -> 54759.055 | L52: =(G52+H52)/Q52 -> 1368.9764 | M52: =L52/12 -> 114.08136 | N52: =Q52/J52 -> 127 | O52: =IF(Table1[[#This Row],[WL per Employee]]<=0,0,Table1[[#This Row],[Total Combined Expenses]]/Table1[[#This Row],[WL per Employee]]/Table1[[#This Row],[YE Unit Labor Headcount (FTE & SMP)]]) -> 1368.9764 | P52: =G52/J52 -> 121200 | Q52: ='Support Numbers'!C18 -> 1270 | S52: =IF(Table1[[#This Row],['# WLD (Units or Users)]]=0,0,(G52+H52)/F52) -> 43465 | W52: =(G52+H52)/Q52 -> 1368.9764 | X52: Academic advisory for SAO sponsored students in an Associates program
A53: 2023 | B53: ATPD | C53: Academic Prog | D53: CH14 Advisory | E53: Advanced | F53: ='Support Numbers'!C17 -> 330 | G53: ='BUDGET-22-25 ATPD'!O8+'BUDGET-22-25 ATPD'!O12 -> 1212000 | H53: =('BUDGET-22-25 ATPD'!O9+'BUDGET-22-25 ATPD'!O22)-'BUDGET-22-25 ATPD'!O12-'BUDGET-22-25 ATPD'!O13+'Support Numbers'!C78 -> 526600 | I53: =Table1[[#This Row],[Total Annual Labor Budget (by business unit)]]+Table1[[#This Row],[Total Annual Controllable Expenses (by business unit)]] -> 1738600 | J53: ='BUDGET-22-25 ATPD'!O40+'BUDGET-22-25 ATPD'!O42 -> 10 | K53: =Table1[[#This Row],['# WLD (Units or Users)]]*Table1[[#This Row],[Cost per WLD/yr]] -> 451762.2 | L53: =(G53+H53)/Q53 -> 1368.9764 | M53: =L53/12 -> 114.08136 | N53: =Q53/J53 -> 127 | O53: =IF(Table1[[#This Row],[WL per Employee]]<=0,0,Table1[[#This Row],[Total Combined Expenses]]/Table1[[#This Row],[WL per Employee]]/Table1[[#This Row],[YE Unit Labor Headcount (FTE & SMP)]]) -> 1368.9764 | P53: =G53/J53 -> 121200 | Q53: ='Support Numbers'!C18 -> 1270 | S53: =IF(Table1[[#This Row],['# WLD (Units or Users)]]=0,0,(G53+H53)/F53) -> 5268.4848 | W53: =(G53+H53)/Q53 -> 1368.9764 | X53: Academic advisory for SAO sponsored students in an Advanced degree program
A54: 2023 | B54: ATPD | C54: Tech Professional Unit | D54: Trainees Support | E54: CH14 | F54: ='Support Numbers'!C22 -> 10 | G54: ='BUDGET-22-25 ATPD'!U8+'BUDGET-22-25 ATPD'!U12 -> 672000 | H54: ='BUDGET-22-25 ATPD'!U9+'BUDGET-22-25 ATPD'!U22-'BUDGET-22-25 ATPD'!U12-'BUDGET-22-25 ATPD'!U13+'Support Numbers'!C79 -> 164300 | I54: =Table1[[#This Row],[Total Annual Labor Budget (by business unit)]]+Table1[[#This Row],[Total Annual Controllable Expenses (by business unit)]] -> 836300 | J54: ='BUDGET-22-25 ATPD'!U39 -> 5 | K54: =Table1[[#This Row],['# WLD (Units or Users)]]*Table1[[#This Row],[Cost per WLD/yr]] -> 278766.67 | L54: =(G54+H54)/Q54 -> 27876.667 | M54: =L54/12 -> 2323.0556 | N54: =Q54/J54 -> 6 | O54: =IF(Table1[[#This Row],[WL per Employee]]<=0,0,Table1[[#This Row],[Total Combined Expenses]]/Table1[[#This Row],[WL per Employee]]/Table1[[#This Row],[YE Unit Labor Headcount (FTE & SMP)]]) -> 27876.667 | P54: =G54/J54 -> 134400 | Q54: ='Support Numbers'!C24 -> 30 | S54: =IF(Table1[[#This Row],['# WLD (Units or Users)]]=0,0,(G54+H54)/F54) -> 83630 | W54: =(G54+H54)/Q54 -> 27876.667 | X54: Coordination and support for sponsored CH14 trainee programs
A55: 2023 | B55: ATPD | C55: Tech Professional Unit | D55: Trainees Support | E55: CH8 | F55: ='Support Numbers'!C23 -> 20 | G55: ='BUDGET-22-25 ATPD'!U8+'BUDGET-22-25 ATPD'!U12 -> 672000 | H55: ='BUDGET-22-25 ATPD'!U9+'BUDGET-22-25 ATPD'!U22-'BUDGET-22-25 ATPD'!U12-'BUDGET-22-25 ATPD'!U13+'Support Numbers'!C79 -> 164300 | I55: =Table1[[#This Row],[Total Annual Labor Budget (by business unit)]]+Table1[[#This Row],[Total Annual Controllable Expenses (by business unit)]] -> 836300 | J55: ='BUDGET-22-25 ATPD'!U39 -> 5 | K55: =Table1[[#This Row],['# WLD (Units or Users)]]*Table1[[#This Row],[Cost per WLD/yr]] -> 557533.33 | L55: =(G55+H55)/Q55 -> 27876.667 | M55: =L55/12 -> 2323.0556 | N55: =Q55/J55 -> 6 | O55: =IF(Table1[[#This Row],[WL per Employee]]<=0,0,Table1[[#This Row],[Total Combined Expenses]]/Table1[[#This Row],[WL per Employee]]/Table1[[#This Row],[YE Unit Labor Headcount (FTE & SMP)]]) -> 27876.667 | P55: =G55/J55 -> 134400 | Q55: ='Support Numbers'!C24 -> 30 | S55: =IF(Table1[[#This Row],['# WLD (Units or Users)]]=0,0,(G55+H55)/F55) -> 41815 | W55: =(G55+H55)/Q55 -> 27876.667 | X55: Coordination and support for sponsored CH8 trainee programs
A56: 2023 | B56: HRS | C56: All HRS | D56: HR Support Services | E56: ASC + RD | F56: ='Support Numbers'!C30 -> 501 | G56: =('BUDGET-22-25 HRS & CIG'!C8-'BUDGET-22-25 HRS & CIG'!C4) +'BUDGET-22-25 HRS & CIG'!I8+'BUDGET-22-25 HRS & CIG'!O8+'BUDGET-22-25 HRS & CIG'!U8 +'BUDGET-22-25 HRS & CIG'!C12 +'BUDGET-22-25 HRS & CIG'!I12+'BUDGET-22-25 HRS & CIG'!O12+'BUDGET-22-25 HRS & CIG'!U12 -> 2385800 | H56: =('BUDGET-22-25 HRS & CIG'!C22+'BUDGET-22-25 HRS & CIG'!I22+'BUDGET-22-25 HRS & CIG'!O22+'BUDGET-22-25 HRS & CIG'!U22)-'BUDGET-22-25 HRS & CIG'!C13-'BUDGET-22-25 HRS & CIG'!I13-'BUDGET-22-25 HRS & CIG'!O13-'BUDGET-22-25 HRS & CIG'!U13-'BUDGET-22-25 HRS & CIG'!C12-'BUDGET-22-25 HRS & CIG'!I12-'BUDGET-22-25 HRS & CIG'!O12-'BUDGET-22-25 HRS & CIG'!U12 -> 506500 | I56: =Table1[[#This Row],[Total Annual Labor Budget (by business unit)]]+Table1[[#This Row],[Total Annual Controllable Expenses (by business unit)]] -> 2892300 | J56: ='BUDGET-22-25 HRS & CIG'!C37+'BUDGET-22-25 HRS & CIG'!I37+'BUDGET-22-25 HRS & CIG'!O37+'BUDGET-22-25 HRS & CIG'!U37 -> 17 | K56: =Table1[[#This Row],['# WLD (Units or Users)]]*Table1[[#This Row],[Cost per WLD/yr]] -> 2601512.2 | L56: =(G56+H56)/Q56 -> 5192.6391 | M56: =L56/12 -> 432.71993 | N56: =Q56/J56 -> 32.764706 | O56: =IF(Table1[[#This Row],[WL per Employee]]<=0,0,Table1[[#This Row],[Total Combined Expenses]]/Table1[[#This Row],[WL per Employee]]/Table1[[#This Row],[YE Unit Labor Headcount (FTE & SMP)]]) -> 5192.6391 | P56: =G56/J56 -> 140341.18 | Q56: ='Support Numbers'!C36 -> 557 | S56: =IF(Table1[[#This Row],['# WLD (Units or Users)]]=0,0,(G56+H56)/F56) -> 5773.0539 | W56: =(G56+H56)/Q56 -> 5192.6391 | X56: Full life cycle HR support - hire to retire (onboarding, HRIS, personnel, training, offboarding) for ASC/RD employees, temps, independent contractors
A57: 2023 | B57: HRS | C57: All HRS | D57: HR Support Services | E57: AAC | F57: ='Support Numbers'!C27 -> 10 | G57: =('BUDGET-22-25 HRS & CIG'!C8-'BUDGET-22-25 HRS & CIG'!C4) +'BUDGET-22-25 HRS & CIG'!I8+'BUDGET-22-25 HRS & CIG'!O8+'BUDGET-22-25 HRS & CIG'!U8 +'BUDGET-22-25 HRS & CIG'!C12 +'BUDGET-22-25 HRS & CIG'!I12+'BUDGET-22-25 HRS & CIG'!O12+'BUDGET-22-25 HRS & CIG'!U12 -> 2385800 | H57: =('BUDGET-22-25 HRS & CIG'!C22+'BUDGET-22-25 HRS & CIG'!I22+'BUDGET-22-25 HRS & CIG'!O22+'BUDGET-22-25 HRS & CIG'!U22)-'BUDGET-22-25 HRS & CIG'!C13-'BUDGET-22-25 HRS & CIG'!I13-'BUDGET-22-25 HRS & CIG'!O13-'BUDGET-22-25 HRS & CIG'!U13-'BUDGET-22-25 HRS & CIG'!C12-'BUDGET-22-25 HRS & CIG'!I12-'BUDGET-22-25 HRS & CIG'!O12-'BUDGET-22-25 HRS & CIG'!U12 -> 506500 | I57: =Table1[[#This Row],[Total Annual Labor Budget (by business unit)]]+Table1[[#This Row],[Total Annual Controllable Expenses (by business unit)]] -> 2892300 | J57: ='BUDGET-22-25 HRS & CIG'!C37+'BUDGET-22-25 HRS & CIG'!I37+'BUDGET-22-25 HRS & CIG'!O37+'BUDGET-22-25 HRS & CIG'!U37 -> 17 | K57: =Table1[[#This Row],['# WLD (Units or Users)]]*Table1[[#This Row],[Cost per WLD/yr]] -> 51926.391 | L57: =(G57+H57)/Q57 -> 5192.6391 | M57: =L57/12 -> 432.71993 | N57: =Q57/J57 -> 32.764706 | O57: =IF(Table1[[#This Row],[WL per Employee]]<=0,0,Table1[[#This Row],[Total Combined Expenses]]/Table1[[#This Row],[WL per Employee]]/Table1[[#This Row],[YE Unit Labor Headcount (FTE & SMP)]]) -> 5192.6391 | P57: =G57/J57 -> 140341.18 | Q57: ='Support Numbers'!C36 -> 557 | S57: =IF(Table1[[#This Row],['# WLD (Units or Users)]]=0,0,(G57+H57)/F57) -> 289230 | W57: =(G57+H57)/Q57 -> 5192.6391 | X57: Full life cycle HR support - hire to retire (onboarding, HRIS, personnel, training, offboarding) for AAC employees, temps, independent contractors
A58: 2023 | B58: HRS | C58: All HRS | D58: HR Support Services | E58: ASBCO | F58: ='Support Numbers'!C29 -> 8 | G58: =('BUDGET-22-25 HRS & CIG'!C8-'BUDGET-22-25 HRS & CIG'!C4) +'BUDGET-22-25 HRS & CIG'!I8+'BUDGET-22-25 HRS & CIG'!O8+'BUDGET-22-25 HRS & CIG'!U8 +'BUDGET-22-25 HRS & CIG'!C12 +'BUDGET-22-25 HRS & CIG'!I12+'BUDGET-22-25 HRS & CIG'!O12+'BUDGET-22-25 HRS & CIG'!U12 -> 2385800 | H58: =('BUDGET-22-25 HRS & CIG'!C22+'BUDGET-22-25 HRS & CIG'!I22+'BUDGET-22-25 HRS & CIG'!O22+'BUDGET-22-25 HRS & CIG'!U22)-'BUDGET-22-25 HRS & CIG'!C13-'BUDGET-22-25 HRS & CIG'!I13-'BUDGET-22-25 HRS & CIG'!O13-'BUDGET-22-25 HRS & CIG'!U13-'BUDGET-22-25 HRS & CIG'!C12-'BUDGET-22-25 HRS & CIG'!I12-'BUDGET-22-25 HRS & CIG'!O12-'BUDGET-22-25 HRS & CIG'!U12 -> 506500 | I58: =Table1[[#This Row],[Total Annual Labor Budget (by business unit)]]+Table1[[#This Row],[Total Annual Controllable Expenses (by business unit)]] -> 2892300 | J58: ='BUDGET-22-25 HRS & CIG'!C37+'BUDGET-22-25 HRS & CIG'!I37+'BUDGET-22-25 HRS & CIG'!O37+'BUDGET-22-25 HRS & CIG'!U37 -> 17 | K58: =Table1[[#This Row],['# WLD (Units or Users)]]*Table1[[#This Row],[Cost per WLD/yr]] -> 41541.113 | L58: =(G58+H58)/Q58 -> 5192.6391 | M58: =L58/12 -> 432.71993 | N58: =Q58/J58 -> 32.764706 | O58: =IF(Table1[[#This Row],[WL per Employee]]<=0,0,Table1[[#This Row],[Total Combined Expenses]]/Table1[[#This Row],[WL per Employee]]/Table1[[#This Row],[YE Unit Labor Headcount (FTE & SMP)]]) -> 5192.6391 | P58: =G58/J58 -> 140341.18 | Q58: ='Support Numbers'!C36 -> 557 | S58: =IF(Table1[[#This Row],['# WLD (Units or Users)]]=0,0,(G58+H58)/F58) -> 361537.5 | W58: =(G58+H58)/Q58 -> 5192.6391 | X58: Full life cycle HR support - hire to retire (onboarding, HRIS, personnel, training, offboarding) for ASBCO employees, temps, independent contractors
A59: 2023 | B59: HRS | C59: All HRS | D59: HR Support Services | E59: ATA | F59: ='Support Numbers'!C31 -> 0 | G59: =('BUDGET-22-25 HRS & CIG'!C8-'BUDGET-22-25 HRS & CIG'!C4) +'BUDGET-22-25 HRS & CIG'!I8+'BUDGET-22-25 HRS & CIG'!O8+'BUDGET-22-25 HRS & CIG'!U8 +'BUDGET-22-25 HRS & CIG'!C12 +'BUDGET-22-25 HRS & CIG'!I12+'BUDGET-22-25 HRS & CIG'!O12+'BUDGET-22-25 HRS & CIG'!U12 -> 2385800 | H59: =('BUDGET-22-25 HRS & CIG'!C22+'BUDGET-22-25 HRS & CIG'!I22+'BUDGET-22-25 HRS & CIG'!O22+'BUDGET-22-25 HRS & CIG'!U22)-'BUDGET-22-25 HRS & CIG'!C13-'BUDGET-22-25 HRS & CIG'!I13-'BUDGET-22-25 HRS & CIG'!O13-'BUDGET-22-25 HRS & CIG'!U13-'BUDGET-22-25 HRS & CIG'!C12-'BUDGET-22-25 HRS & CIG'!I12-'BUDGET-22-25 HRS & CIG'!O12-'BUDGET-22-25 HRS & CIG'!U12 -> 506500 | I59: =Table1[[#This Row],[Total Annual Labor Budget (by business unit)]]+Table1[[#This Row],[Total Annual Controllable Expenses (by business unit)]] -> 2892300 | J59: ='BUDGET-22-25 HRS & CIG'!C37+'BUDGET-22-25 HRS & CIG'!I37+'BUDGET-22-25 HRS & CIG'!O37+'BUDGET-22-25 HRS & CIG'!U37 -> 17 | K59: =Table1[[#This Row],['# WLD (Units or Users)]]*Table1[[#This Row],[Cost per WLD/yr]] -> 0 | L59: =(G59+H59)/Q59 -> 5192.6391 | M59: =L59/12 -> 432.71993 | N59: =Q59/J59 -> 32.764706 | O59: =IF(Table1[[#This Row],[WL per Employee]]<=0,0,Table1[[#This Row],[Total Combined Expenses]]/Table1[[#This Row],[WL per Employee]]/Table1[[#This Row],[YE Unit Labor Headcount (FTE & SMP)]]) -> 5192.6391 | P59: =G59/J59 -> 140341.18 | Q59: ='Support Numbers'!C36 -> 557 | S59: =IF(Table1[[#This Row],['# WLD (Units or Users)]]=0,0,(G59+H59)/F59) -> 0 | W59: =(G59+H59)/Q59 -> 5192.6391 | X59: Full life cycle HR support - hire to retire (onboarding, HRIS, training, offboarding) for ATA employees, temps, independent contractors
A60: 2023 | B60: HRS | C60: All HRS | D60: HR Support Services | E60: AVMCC | F60: ='Support Numbers'!C32 -> 8 | G60: =('BUDGET-22-25 HRS & CIG'!C8-'BUDGET-22-25 HRS & CIG'!C4) +'BUDGET-22-25 HRS & CIG'!I8+'BUDGET-22-25 HRS & CIG'!O8+'BUDGET-22-25 HRS & CIG'!U8 +'BUDGET-22-25 HRS & CIG'!C12 +'BUDGET-22-25 HRS & CIG'!I12+'BUDGET-22-25 HRS & CIG'!O12+'BUDGET-22-25 HRS & CIG'!U12 -> 2385800 | H60: =('BUDGET-22-25 HRS & CIG'!C22+'BUDGET-22-25 HRS & CIG'!I22+'BUDGET-22-25 HRS & CIG'!O22+'BUDGET-22-25 HRS & CIG'!U22)-'BUDGET-22-25 HRS & CIG'!C13-'BUDGET-22-25 HRS & CIG'!I13-'BUDGET-22-25 HRS & CIG'!O13-'BUDGET-22-25 HRS & CIG'!U13-'BUDGET-22-25 HRS & CIG'!C12-'BUDGET-22-25 HRS & CIG'!I12-'BUDGET-22-25 HRS & CIG'!O12-'BUDGET-22-25 HRS & CIG'!U12 -> 506500 | I60: =Table1[[#This Row],[Total Annual Labor Budget (by business unit)]]+Table1[[#This Row],[Total Annual Controllable Expenses (by business unit)]] -> 2892300 | J60: ='BUDGET-22-25 HRS & CIG'!C37+'BUDGET-22-25 HRS & CIG'!I37+'BUDGET-22-25 HRS & CIG'!O37+'BUDGET-22-25 HRS & CIG'!U37 -> 17 | K60: =Table1[[#This Row],['# WLD (Units or Users)]]*Table1[[#This Row],[Cost per WLD/yr]] -> 41541.113 | L60: =(G60+H60)/Q60 -> 5192.6391 | M60: =L60/12 -> 432.71993 | N60: =Q60/J60 -> 32.764706 | O60: =IF(Table1[[#This Row],[WL per Employee]]<=0,0,Table1[[#This Row],[Total Combined Expenses]]/Table1[[#This Row],[WL per Employee]]/Table1[[#This Row],[YE Unit Labor Headcount (FTE & SMP)]]) -> 5192.6391 | P60: =G60/J60 -> 140341.18 | Q60: ='Support Numbers'!C36 -> 557 | S60: =IF(Table1[[#This Row],['# WLD (Units or Users)]]=0,0,(G60+H60)/F60) -> 361537.5 | W60: =(G60+H60)/Q60 -> 5192.6391 | X60: Full life cycle HR support - hire to retire (onboarding, HRIS, personnel, training, offboarding) for AVMCC employees, temps, independent contractors
A61: 2023 | B61: HRS | C61: All HRS | D61: HR Support Services | E61: SAEV | F61: ='Support Numbers'!C33 -> 11 | G61: =('BUDGET-22-25 HRS & CIG'!C8-'BUDGET-22-25 HRS & CIG'!C4) +'BUDGET-22-25 HRS & CIG'!I8+'BUDGET-22-25 HRS & CIG'!O8+'BUDGET-22-25 HRS & CIG'!U8 +'BUDGET-22-25 HRS & CIG'!C12 +'BUDGET-22-25 HRS & CIG'!I12+'BUDGET-22-25 HRS & CIG'!O12+'BUDGET-22-25 HRS & CIG'!U12 -> 2385800 | H61: =('BUDGET-22-25 HRS & CIG'!C22+'BUDGET-22-25 HRS & CIG'!I22+'BUDGET-22-25 HRS & CIG'!O22+'BUDGET-22-25 HRS & CIG'!U22)-'BUDGET-22-25 HRS & CIG'!C13-'BUDGET-22-25 HRS & CIG'!I13-'BUDGET-22-25 HRS & CIG'!O13-'BUDGET-22-25 HRS & CIG'!U13-'BUDGET-22-25 HRS & CIG'!C12-'BUDGET-22-25 HRS & CIG'!I12-'BUDGET-22-25 HRS & CIG'!O12-'BUDGET-22-25 HRS & CIG'!U12 -> 506500 | I61: =Table1[[#This Row],[Total Annual Labor Budget (by business unit)]]+Table1[[#This Row],[Total Annual Controllable Expenses (by business unit)]] -> 2892300 | J61: ='BUDGET-22-25 HRS & CIG'!C37+'BUDGET-22-25 HRS & CIG'!I37+'BUDGET-22-25 HRS & CIG'!O37+'BUDGET-22-25 HRS & CIG'!U37 -> 17 | K61: =Table1[[#This Row],['# WLD (Units or Users)]]*Table1[[#This Row],[Cost per WLD/yr]] -> 57119.031 | L61: =(G61+H61)/Q61 -> 5192.6391 | M61: =L61/12 -> 432.71993 | N61: =Q61/J61 -> 32.764706 | O61: =IF(Table1[[#This Row],[WL per Employee]]<=0,0,Table1[[#This Row],[Total Combined Expenses]]/Table1[[#This Row],[WL per Employee]]/Table1[[#This Row],[YE Unit Labor Headcount (FTE & SMP)]]) -> 5192.6391 | P61: =G61/J61 -> 140341.18 | Q61: ='Support Numbers'!C36 -> 557 | S61: =IF(Table1[[#This Row],['# WLD (Units or Users)]]=0,0,(G61+H61)/F61) -> 262936.36 | W61: =(G61+H61)/Q61 -> 5192.6391 | X61: Full life cycle HR support - hire to retire (onboarding, HRIS, personnel, training, offboarding) for SAEV employees, temps, independent contractors
A62: 2023 | B62: HRS | C62: All HRS | D62: HR Support Services | E62: SRI | F62: ='Support Numbers'!C34 -> 4 | G62: =('BUDGET-22-25 HRS & CIG'!C8-'BUDGET-22-25 HRS & CIG'!C4) +'BUDGET-22-25 HRS & CIG'!I8+'BUDGET-22-25 HRS & CIG'!O8+'BUDGET-22-25 HRS & CIG'!U8 +'BUDGET-22-25 HRS & CIG'!C12 +'BUDGET-22-25 HRS & CIG'!I12+'BUDGET-22-25 HRS & CIG'!O12+'BUDGET-22-25 HRS & CIG'!U12 -> 2385800 | H62: =('BUDGET-22-25 HRS & CIG'!C22+'BUDGET-22-25 HRS & CIG'!I22+'BUDGET-22-25 HRS & CIG'!O22+'BUDGET-22-25 HRS & CIG'!U22)-'BUDGET-22-25 HRS & CIG'!C13-'BUDGET-22-25 HRS & CIG'!I13-'BUDGET-22-25 HRS & CIG'!O13-'BUDGET-22-25 HRS & CIG'!U13-'BUDGET-22-25 HRS & CIG'!C12-'BUDGET-22-25 HRS & CIG'!I12-'BUDGET-22-25 HRS & CIG'!O12-'BUDGET-22-25 HRS & CIG'!U12 -> 506500 | I62: =Table1[[#This Row],[Total Annual Labor Budget (by business unit)]]+Table1[[#This Row],[Total Annual Controllable Expenses (by business unit)]] -> 2892300 | J62: ='BUDGET-22-25 HRS & CIG'!C37+'BUDGET-22-25 HRS & CIG'!I37+'BUDGET-22-25 HRS & CIG'!O37+'BUDGET-22-25 HRS & CIG'!U37 -> 17 | K62: =Table1[[#This Row],['# WLD (Units or Users)]]*Table1[[#This Row],[Cost per WLD/yr]] -> 20770.557 | L62: =(G62+H62)/Q62 -> 5192.6391 | M62: =L62/12 -> 432.71993 | N62: =Q62/J62 -> 32.764706 | O62: =IF(Table1[[#This Row],[WL per Employee]]<=0,0,Table1[[#This Row],[Total Combined Expenses]]/Table1[[#This Row],[WL per Employee]]/Table1[[#This Row],[YE Unit Labor Headcount (FTE & SMP)]]) -> 5192.6391 | P62: =G62/J62 -> 140341.18 | Q62: ='Support Numbers'!C36 -> 557 | S62: =IF(Table1[[#This Row],['# WLD (Units or Users)]]=0,0,(G62+H62)/F62) -> 723075 | W62: =(G62+H62)/Q62 -> 5192.6391 | X62: Full life cycle HR support - hire to retire (onboarding, HRIS, personnel, training, offboarding) for SRI employees, temps, independent contractors
A63: 2023 | B63: HRS | C63: All HRS | D63: HR Support Services | E63: SPII | F63: ='Support Numbers'!C35 -> 15 | G63: =('BUDGET-22-25 HRS & CIG'!C8-'BUDGET-22-25 HRS & CIG'!C4) +'BUDGET-22-25 HRS & CIG'!I8+'BUDGET-22-25 HRS & CIG'!O8+'BUDGET-22-25 HRS & CIG'!U8 +'BUDGET-22-25 HRS & CIG'!C12 +'BUDGET-22-25 HRS & CIG'!I12+'BUDGET-22-25 HRS & CIG'!O12+'BUDGET-22-25 HRS & CIG'!U12 -> 2385800 | H63: =('BUDGET-22-25 HRS & CIG'!C22+'BUDGET-22-25 HRS & CIG'!I22+'BUDGET-22-25 HRS & CIG'!O22+'BUDGET-22-25 HRS & CIG'!U22)-'BUDGET-22-25 HRS & CIG'!C13-'BUDGET-22-25 HRS & CIG'!I13-'BUDGET-22-25 HRS & CIG'!O13-'BUDGET-22-25 HRS & CIG'!U13-'BUDGET-22-25 HRS & CIG'!C12-'BUDGET-22-25 HRS & CIG'!I12-'BUDGET-22-25 HRS & CIG'!O12-'BUDGET-22-25 HRS & CIG'!U12 -> 506500 | I63: =Table1[[#This Row],[Total Annual Labor Budget (by business unit)]]+Table1[[#This Row],[Total Annual Controllable Expenses (by business unit)]] -> 2892300 | J63: ='BUDGET-22-25 HRS & CIG'!C37+'BUDGET-22-25 HRS & CIG'!I37+'BUDGET-22-25 HRS & CIG'!O37+'BUDGET-22-25 HRS & CIG'!U37 -> 17 | K63: =Table1[[#This Row],['# WLD (Units or Users)]]*Table1[[#This Row],[Cost per WLD/yr]] -> 77889.587 | L63: =(G63+H63)/Q63 -> 5192.6391 | M63: =L63/12 -> 432.71993 | N63: =Q63/J63 -> 32.764706 | O63: =IF(Table1[[#This Row],[WL per Employee]]<=0,0,Table1[[#This Row],[Total Combined Expenses]]/Table1[[#This Row],[WL per Employee]]/Table1[[#This Row],[YE Unit Labor Headcount (FTE & SMP)]]) -> 5192.6391 | P63: =G63/J63 -> 140341.18 | Q63: ='Support Numbers'!C36 -> 557 | S63: =IF(Table1[[#This Row],['# WLD (Units or Users)]]=0,0,(G63+H63)/F63) -> 192820 | W63: =(G63+H63)/Q63 -> 5192.6391 | X63: Full life cycle HR support - hire to retire (onboarding, HRIS, personnel, training, offboarding)
A64: 2023 | B64: SSD | C64: Expat Recruitment | D64: Bundled Recruitment | E64: SAO | F64: ='Support Numbers'!C50 -> 480 | G64: ='BUDGET-22-25 SSD'!C8+'BUDGET-22-25 SSD'!C12+'BUDGET-22-25 SSD'!I8+'BUDGET-22-25 SSD'!I12+'BUDGET-22-25 SSD'!O8+'BUDGET-22-25 SSD'!O12+'BUDGET-22-25 SSD'!U8+'BUDGET-22-25 SSD'!U12+'BUDGET-22-25 SSD'!AA8+'BUDGET-22-25 SSD'!AA12 -> 2797500 | H64: =('BUDGET-22-25 SSD'!C9+'BUDGET-22-25 SSD'!C22+'BUDGET-22-25 SSD'!I9+'BUDGET-22-25 SSD'!I22+'BUDGET-22-25 SSD'!O9+'BUDGET-22-25 SSD'!O22+'BUDGET-22-25 SSD'!U9+'BUDGET-22-25 SSD'!U22+'BUDGET-22-25 SSD'!AA9+'BUDGET-22-25 SSD'!AA22) -'BUDGET-22-25 SSD'!C12-'BUDGET-22-25 SSD'!C13-'BUDGET-22-25 SSD'!I12-'BUDGET-22-25 SSD'!I13-'BUDGET-22-25 SSD'!O12-'BUDGET-22-25 SSD'!O13-'BUDGET-22-25 SSD'!U12-'BUDGET-22-25 SSD'!U13-'BUDGET-22-25 SSD'!AA12-'BUDGET-22-25 SSD'!AA13 -> 2699520 | I64: =Table1[[#This Row],[Total Annual Labor Budget (by business unit)]]+Table1[[#This Row],[Total Annual Controllable Expenses (by business unit)]] -> 5497020 | J64: ='BUDGET-22-25 SSD'!C40+'BUDGET-22-25 SSD'!C42 +'BUDGET-22-25 SSD'!I40+'BUDGET-22-25 SSD'!I42 +'BUDGET-22-25 SSD'!O40+'BUDGET-22-25 SSD'!O42 +'BUDGET-22-25 SSD'!U40+'BUDGET-22-25 SSD'!U42 +'BUDGET-22-25 SSD'!AA40+'BUDGET-22-25 SSD'!AA42 -> 26 | K64: =Table1[[#This Row],['# WLD (Units or Users)]]*Table1[[#This Row],[Cost per WLD/yr]] -> 5497020 | L64: =(G64+H64)/Q64 -> 11452.125 | M64: =L64/12 -> 954.34375 | N64: =Q64/J64 -> 18.461538 | O64: =IF(Table1[[#This Row],[WL per Employee]]<=0,0,Table1[[#This Row],[Total Combined Expenses]]/Table1[[#This Row],[WL per Employee]]/Table1[[#This Row],[YE Unit Labor Headcount (FTE & SMP)]]) -> 11452.125 | P64: =G64/J64 -> 107596.15 | Q64: =F64 -> 480 | S64: =IF(Table1[[#This Row],['# WLD (Units or Users)]]=0,0,(G64+H64)/F64) -> 11452.125 | W64: =(G64+H64)/Q64 -> 11452.125 | X64: International recruitment services (sourcing, attracting, full life cycle candidate management, workshop coordination)
A65: 2023 | B65: SSD | C65: Domestic Recruitment | D65: FTE SMP Recruitment | E65: ASC + RD | F65: ='Support Numbers'!C53 -> 70 | G65: ='BUDGET-22-25 SSD'!AG8+'BUDGET-22-25 SSD'!AG12 -> 632500 | H65: =('BUDGET-22-25 SSD'!AG9+'BUDGET-22-25 SSD'!AG22)-'BUDGET-22-25 SSD'!AG12-'BUDGET-22-25 SSD'!AG13 -> 86880 | I65: =Table1[[#This Row],[Total Annual Labor Budget (by business unit)]]+Table1[[#This Row],[Total Annual Controllable Expenses (by business unit)]] -> 719380 | J65: ='BUDGET-22-25 SSD'!AG40+'BUDGET-22-25 SSD'!AG42 -> 5 | K65: =Table1[[#This Row],['# WLD (Units or Users)]]*Table1[[#This Row],[Cost per WLD/yr]] -> 312773.91 | L65: =(G65+H65)/Q65 -> 4468.1988 | M65: =L65/12 -> 372.3499 | N65: =Q65/J65 -> 32.2 | O65: =IF(Table1[[#This Row],[WL per Employee]]<=0,0,Table1[[#This Row],[Total Combined Expenses]]/Table1[[#This Row],[WL per Employee]]/Table1[[#This Row],[YE Unit Labor Headcount (FTE & SMP)]]) -> 4468.1988 | P65: =G65/J65 -> 126500 | Q65: ='Support Numbers'!C61 -> 161 | S65: =IF(Table1[[#This Row],['# WLD (Units or Users)]]=0,0,(G65+H65)/F65) -> 10276.857 | W65: =(G65+H65)/Q65 -> 4468.1988 | X65: Full life cycle recruitment - sourcing, attraction, proponent and candidate management
A66: 2023 | B66: SSD | C66: Domestic Recruitment | D66: SMP Recruitment | E66: PMT | F66: ='Support Numbers'!C54 -> 75 | G66: ='BUDGET-22-25 SSD'!AG8+'BUDGET-22-25 SSD'!AG12 -> 632500 | H66: =('BUDGET-22-25 SSD'!AG9+'BUDGET-22-25 SSD'!AG22)-'BUDGET-22-25 SSD'!AG12-'BUDGET-22-25 SSD'!AG13 -> 86880 | I66: =Table1[[#This Row],[Total Annual Labor Budget (by business unit)]]+Table1[[#This Row],[Total Annual Controllable Expenses (by business unit)]] -> 719380 | J66: ='BUDGET-22-25 SSD'!AG40+'BUDGET-22-25 SSD'!AG42 -> 5 | K66: =Table1[[#This Row],['# WLD (Units or Users)]]*Table1[[#This Row],[Cost per WLD/yr]] -> 335114.91 | L66: =(G66+H66)/Q66 -> 4468.1988 | M66: =L66/12 -> 372.3499 | N66: =Q66/J66 -> 32.2 | O66: =IF(Table1[[#This Row],[WL per Employee]]<=0,0,Table1[[#This Row],[Total Combined Expenses]]/Table1[[#This Row],[WL per Employee]]/Table1[[#This Row],[YE Unit Labor Headcount (FTE & SMP)]]) -> 4468.1988 | P66: =G66/J66 -> 126500 | Q66: ='Support Numbers'!C61 -> 161 | S66: =IF(Table1[[#This Row],['# WLD (Units or Users)]]=0,0,(G66+H66)/F66) -> 9591.7333 | W66: =(G66+H66)/Q66 -> 4468.1988 | X66: Managing recruitment for temporary PMT needs - sourcing, management of agency, candidates, and proponents
A67: 2023 | B67: SSD | C67: Domestic Recruitment | D67: FTE SMP Recruitment | E67: AVMCC | F67: ='Support Numbers'!C55 -> 3 | G67: ='BUDGET-22-25 SSD'!AG8+'BUDGET-22-25 SSD'!AG12 -> 632500 | H67: =('BUDGET-22-25 SSD'!AG9+'BUDGET-22-25 SSD'!AG22)-'BUDGET-22-25 SSD'!AG12-'BUDGET-22-25 SSD'!AG13 -> 86880 | I67: =Table1[[#This Row],[Total Annual Labor Budget (by business unit)]]+Table1[[#This Row],[Total Annual Controllable Expenses (by business unit)]] -> 719380 | J67: ='BUDGET-22-25 SSD'!AG40+'BUDGET-22-25 SSD'!AG42 -> 5 | K67: =Table1[[#This Row],['# WLD (Units or Users)]]*Table1[[#This Row],[Cost per WLD/yr]] -> 13404.596 | L67: =(G67+H67)/Q67 -> 4468.1988 | M67: =L67/12 -> 372.3499 | N67: =Q67/J67 -> 32.2 | O67: =IF(Table1[[#This Row],[WL per Employee]]<=0,0,Table1[[#This Row],[Total Combined Expenses]]/Table1[[#This Row],[WL per Employee]]/Table1[[#This Row],[YE Unit Labor Headcount (FTE & SMP)]]) -> 4468.1988 | P67: =G67/J67 -> 126500 | Q67: ='Support Numbers'!C61 -> 161 | S67: =IF(Table1[[#This Row],['# WLD (Units or Users)]]=0,0,(G67+H67)/F67) -> 239793.33 | W67: =(G67+H67)/Q67 -> 4468.1988 | X67: Full life cycle recruitment - sourcing, attraction, proponent and candidate management
A68: 2023 | B68: SSD | C68: Domestic Recruitment | D68: FTE SMP Recruitment | E68: SAEV | F68: ='Support Numbers'!C56 -> 3 | G68: ='BUDGET-22-25 SSD'!AG8+'BUDGET-22-25 SSD'!AG12 -> 632500 | H68: =('BUDGET-22-25 SSD'!AG9+'BUDGET-22-25 SSD'!AG22)-'BUDGET-22-25 SSD'!AG12-'BUDGET-22-25 SSD'!AG13 -> 86880 | I68: =Table1[[#This Row],[Total Annual Labor Budget (by business unit)]]+Table1[[#This Row],[Total Annual Controllable Expenses (by business unit)]] -> 719380 | J68: ='BUDGET-22-25 SSD'!AG40+'BUDGET-22-25 SSD'!AG42 -> 5 | K68: =Table1[[#This Row],['# WLD (Units or Users)]]*Table1[[#This Row],[Cost per WLD/yr]] -> 13404.596 | L68: =(G68+H68)/Q68 -> 4468.1988 | M68: =L68/12 -> 372.3499 | N68: =Q68/J68 -> 32.2 | O68: =IF(Table1[[#This Row],[WL per Employee]]<=0,0,Table1[[#This Row],[Total Combined Expenses]]/Table1[[#This Row],[WL per Employee]]/Table1[[#This Row],[YE Unit Labor Headcount (FTE & SMP)]]) -> 4468.1988 | P68: =G68/J68 -> 126500 | Q68: ='Support Numbers'!C61 -> 161 | S68: =IF(Table1[[#This Row],['# WLD (Units or Users)]]=0,0,(G68+H68)/F68) -> 239793.33 | W68: =(G68+H68)/Q68 -> 4468.1988 | X68: Full life cycle recruitment - sourcing, attraction, proponent and candidate management
A69: 2023 | B69: SSD | C69: Domestic Recruitment | D69: FTE SMP Recruitment | E69: SPII | F69: ='Support Numbers'!C57 -> 9 | G69: ='BUDGET-22-25 SSD'!AG8+'BUDGET-22-25 SSD'!AG12 -> 632500 | H69: =('BUDGET-22-25 SSD'!AG9+'BUDGET-22-25 SSD'!AG22)-'BUDGET-22-25 SSD'!AG12-'BUDGET-22-25 SSD'!AG13 -> 86880 | I69: =Table1[[#This Row],[Total Annual Labor Budget (by business unit)]]+Table1[[#This Row],[Total Annual Controllable Expenses (by business unit)]] -> 719380 | J69: ='BUDGET-22-25 SSD'!AG40+'BUDGET-22-25 SSD'!AG42 -> 5 | K69: =Table1[[#This Row],['# WLD (Units or Users)]]*Table1[[#This Row],[Cost per WLD/yr]] -> 40213.789 | L69: =(G69+H69)/Q69 -> 4468.1988 | M69: =L69/12 -> 372.3499 | N69: =Q69/J69 -> 32.2 | O69: =IF(Table1[[#This Row],[WL per Employee]]<=0,0,Table1[[#This Row],[Total Combined Expenses]]/Table1[[#This Row],[WL per Employee]]/Table1[[#This Row],[YE Unit Labor Headcount (FTE & SMP)]]) -> 4468.1988 | P69: =G69/J69 -> 126500 | Q69: ='Support Numbers'!C61 -> 161 | S69: =IF(Table1[[#This Row],['# WLD (Units or Users)]]=0,0,(G69+H69)/F69) -> 79931.111 | W69: =(G69+H69)/Q69 -> 4468.1988 | X69: Full life cycle recruitment - sourcing, attraction, proponent and candidate management
A70: 2023 | B70: SSD | C70: Domestic Recruitment | D70: FTE SMP Recruitment | E70: SRI | F70: ='Support Numbers'!C58 -> 1 | G70: ='BUDGET-22-25 SSD'!AG8+'BUDGET-22-25 SSD'!AG12 -> 632500 | H70: =('BUDGET-22-25 SSD'!AG9+'BUDGET-22-25 SSD'!AG22)-'BUDGET-22-25 SSD'!AG12-'BUDGET-22-25 SSD'!AG13 -> 86880 | I70: =Table1[[#This Row],[Total Annual Labor Budget (by business unit)]]+Table1[[#This Row],[Total Annual Controllable Expenses (by business unit)]] -> 719380 | J70: ='BUDGET-22-25 SSD'!AG40+'BUDGET-22-25 SSD'!AG42 -> 5 | K70: =Table1[[#This Row],['# WLD (Units or Users)]]*Table1[[#This Row],[Cost per WLD/yr]] -> 4468.1988 | L70: =(G70+H70)/Q70 -> 4468.1988 | M70: =L70/12 -> 372.3499 | N70: =Q70/J70 -> 32.2 | O70: =IF(Table1[[#This Row],[WL per Employee]]<=0,0,Table1[[#This Row],[Total Combined Expenses]]/Table1[[#This Row],[WL per Employee]]/Table1[[#This Row],[YE Unit Labor Headcount (FTE & SMP)]]) -> 4468.1988 | P70: =G70/J70 -> 126500 | Q70: ='Support Numbers'!C61 -> 161 | S70: =IF(Table1[[#This Row],['# WLD (Units or Users)]]=0,0,(G70+H70)/F70) -> 719380 | W70: =(G70+H70)/Q70 -> 4468.1988 | X70: Full life cycle recruitment - sourcing, attraction, proponent and candidate management
A71: 2023 | B71: SSD | C71: Domestic Recruitment | D71: FTE SMP Recruitment | E71: ASBCO | F71: ='Support Numbers'!C59 -> 0 | G71: ='BUDGET-22-25 SSD'!AG8+'BUDGET-22-25 SSD'!AG12 -> 632500 | H71: =('BUDGET-22-25 SSD'!AG9+'BUDGET-22-25 SSD'!AG22)-'BUDGET-22-25 SSD'!AG12-'BUDGET-22-25 SSD'!AG13 -> 86880 | I71: =Table1[[#This Row],[Total Annual Labor Budget (by business unit)]]+Table1[[#This Row],[Total Annual Controllable Expenses (by business unit)]] -> 719380 | J71: ='BUDGET-22-25 SSD'!AG40+'BUDGET-22-25 SSD'!AG42 -> 5 | K71: =Table1[[#This Row],['# WLD (Units or Users)]]*Table1[[#This Row],[Cost per WLD/yr]] -> 0 | L71: =(G71+H71)/Q71 -> 4468.1988 | M71: =L71/12 -> 372.3499 | N71: =Q71/J71 -> 32.2 | O71: =IF(Table1[[#This Row],[WL per Employee]]<=0,0,Table1[[#This Row],[Total Combined Expenses]]/Table1[[#This Row],[WL per Employee]]/Table1[[#This Row],[YE Unit Labor Headcount (FTE & SMP)]]) -> 4468.1988 | P71: =G71/J71 -> 126500 | Q71: ='Support Numbers'!C61 -> 161 | S71: =IF(Table1[[#This Row],['# WLD (Units or Users)]]=0,0,(G71+H71)/F71) -> 0 | W71: =(G71+H71)/Q71 -> 4468.1988 | X71: Full life cycle recruitment - sourcing, attraction, proponent and candidate management
A72: 2023 | B72: SSD | C72: Domestic Recruitment | D72: FTE SMP Recruitment | E72: ATA | F72: ='Support Numbers'!C60 -> 0 | G72: ='BUDGET-22-25 SSD'!AG8+'BUDGET-22-25 SSD'!AG12 -> 632500 | H72: =('BUDGET-22-25 SSD'!AG9+'BUDGET-22-25 SSD'!AG22)-'BUDGET-22-25 SSD'!AG12-'BUDGET-22-25 SSD'!AG13 -> 86880 | I72: =Table1[[#This Row],[Total Annual Labor Budget (by business unit)]]+Table1[[#This Row],[Total Annual Controllable Expenses (by business unit)]] -> 719380 | J72: ='BUDGET-22-25 SSD'!AG40+'BUDGET-22-25 SSD'!AG42 -> 5 | K72: =Table1[[#This Row],['# WLD (Units or Users)]]*Table1[[#This Row],[Cost per WLD/yr]] -> 0 | L72: =(G72+H72)/Q72 -> 4468.1988 | M72: =L72/12 -> 372.3499 | N72: =Q72/J72 -> 32.2 | O72: =IF(Table1[[#This Row],[WL per Employee]]<=0,0,Table1[[#This Row],[Total Combined Expenses]]/Table1[[#This Row],[WL per Employee]]/Table1[[#This Row],[YE Unit Labor Headcount (FTE & SMP)]]) -> 4468.1988 | P72: =G72/J72 -> 126500 | Q72: ='Support Numbers'!C61 -> 161 | S72: =IF(Table1[[#This Row],['# WLD (Units or Users)]]=0,0,(G72+H72)/F72) -> 0 | W72: =(G72+H72)/Q72 -> 4468.1988 | X72: Full life cycle recruitment - sourcing, attraction, proponent and candidate management
A73: 2023 | B73: CIG | C73: Background Investigations | D73: Expat Hiring | E73: SAO HR SSD | F73: ='Support Numbers'!C70 -> 400 | G73: ='BUDGET-22-25 HRS & CIG'!AG8+'BUDGET-22-25 HRS & CIG'!AG12 -> 392500 | H73: ='BUDGET-22-25 HRS & CIG'!AG9+'BUDGET-22-25 HRS & CIG'!AG22-'BUDGET-22-25 HRS & CIG'!AG12 -> 1909400 | I73: =Table1[[#This Row],[Total Annual Labor Budget (by business unit)]]+Table1[[#This Row],[Total Annual Controllable Expenses (by business unit)]] -> 2301900 | J73: ='BUDGET-22-25 HRS & CIG'!AG38+'BUDGET-22-25 HRS & CIG'!AG40 -> 4 | K73: =Table1[[#This Row],['# WLD (Units or Users)]]*Table1[[#This Row],[Cost per WLD/yr]] -> 613840 | L73: =(G73+H73)/Q73 -> 1534.6 | M73: =L73/12 -> 127.88333 | N73: =Q73/J73 -> 375 | O73: =IF(Table1[[#This Row],[WL per Employee]]<=0,0,Table1[[#This Row],[Total Combined Expenses]]/Table1[[#This Row],[WL per Employee]]/Table1[[#This Row],[YE Unit Labor Headcount (FTE & SMP)]]) -> 1534.6 | P73: =G73/J73 -> 98125 | Q73: ='Support Numbers'!C74 -> 1500 | S73: =IF(Table1[[#This Row],['# WLD (Units or Users)]]=0,0,(G73+H73)/F73) -> 5754.75 | W73: =(G73+H73)/Q73 -> 1534.6 | X73: Background checks initated for candidates consenting to checking at time of technically qualified and all candidates at offer accepted.
A74: 2023 | B74: CIG | C74: Background Investigations | D74: Domestic | E74: ASC+ATA | F74: ='Support Numbers'!C71 -> 150 | G74: ='BUDGET-22-25 HRS & CIG'!AG8+'BUDGET-22-25 HRS & CIG'!AG12 -> 392500 | H74: ='BUDGET-22-25 HRS & CIG'!AG9+'BUDGET-22-25 HRS & CIG'!AG22-'BUDGET-22-25 HRS & CIG'!AG12 -> 1909400 | I74: =Table1[[#This Row],[Total Annual Labor Budget (by business unit)]]+Table1[[#This Row],[Total Annual Controllable Expenses (by business unit)]] -> 2301900 | J74: ='BUDGET-22-25 HRS & CIG'!AG38+'BUDGET-22-25 HRS & CIG'!AG40 -> 4 | K74: =Table1[[#This Row],['# WLD (Units or Users)]]*Table1[[#This Row],[Cost per WLD/yr]] -> 230190 | L74: =(G74+H74)/Q74 -> 1534.6 | M74: =L74/12 -> 127.88333 | N74: =Q74/J74 -> 375 | O74: =IF(Table1[[#This Row],[WL per Employee]]<=0,0,Table1[[#This Row],[Total Combined Expenses]]/Table1[[#This Row],[WL per Employee]]/Table1[[#This Row],[YE Unit Labor Headcount (FTE & SMP)]]) -> 1534.6 | P74: =G74/J74 -> 98125 | Q74: ='Support Numbers'!C74 -> 1500 | S74: =IF(Table1[[#This Row],['# WLD (Units or Users)]]=0,0,(G74+H74)/F74) -> 15346 | W74: =(G74+H74)/Q74 -> 1534.6 | X74: Background checks for all domestic hiring efforts
A75: 2023 | B75: CIG | C75: Background Investigations | D75: SAO Corp Security | E75: SAO Corp Security | F75: ='Support Numbers'!C72 -> 900 | G75: ='BUDGET-22-25 HRS & CIG'!AG8+'BUDGET-22-25 HRS & CIG'!AG12 -> 392500 | H75: ='BUDGET-22-25 HRS & CIG'!AG9+'BUDGET-22-25 HRS & CIG'!AG22-'BUDGET-22-25 HRS & CIG'!AG12 -> 1909400 | I75: =Table1[[#This Row],[Total Annual Labor Budget (by business unit)]]+Table1[[#This Row],[Total Annual Controllable Expenses (by business unit)]] -> 2301900 | J75: ='BUDGET-22-25 HRS & CIG'!AG38+'BUDGET-22-25 HRS & CIG'!AG40 -> 4 | K75: =Table1[[#This Row],['# WLD (Units or Users)]]*Table1[[#This Row],[Cost per WLD/yr]] -> 1381140 | L75: =(G75+H75)/Q75 -> 1534.6 | M75: =L75/12 -> 127.88333 | N75: =Q75/J75 -> 375 | O75: =IF(Table1[[#This Row],[WL per Employee]]<=0,0,Table1[[#This Row],[Total Combined Expenses]]/Table1[[#This Row],[WL per Employee]]/Table1[[#This Row],[YE Unit Labor Headcount (FTE & SMP)]]) -> 1534.6 | P75: =G75/J75 -> 98125 | Q75: ='Support Numbers'!C74 -> 1500 | S75: =IF(Table1[[#This Row],['# WLD (Units or Users)]]=0,0,(G75+H75)/F75) -> 2557.6667 | W75: =(G75+H75)/Q75 -> 1534.6 | X75: Background checks initiated and completed for Saudi students who studied in the US/Canada and applied for jobs at Saudi Aramco upon returning home.
A76: 2023 | B76: CIG | C76: Background Investigations | D76: Special Inv. Requests | E76: Misc. | F76: ='Support Numbers'!C73 -> 50 | G76: ='BUDGET-22-25 HRS & CIG'!AG8+'BUDGET-22-25 HRS & CIG'!AG12 -> 392500 | H76: ='BUDGET-22-25 HRS & CIG'!AG9+'BUDGET-22-25 HRS & CIG'!AG22-'BUDGET-22-25 HRS & CIG'!AG12 -> 1909400 | I76: =Table1[[#This Row],[Total Annual Labor Budget (by business unit)]]+Table1[[#This Row],[Total Annual Controllable Expenses (by business unit)]] -> 2301900 | J76: ='BUDGET-22-25 HRS & CIG'!AG38+'BUDGET-22-25 HRS & CIG'!AG40 -> 4 | K76: =Table1[[#This Row],['# WLD (Units or Users)]]*Table1[[#This Row],[Cost per WLD/yr]] -> 76730 | L76: =(G76+H76)/Q76 -> 1534.6 | M76: =L76/12 -> 127.88333 | N76: =Q76/J76 -> 375 | O76: =IF(Table1[[#This Row],[WL per Employee]]<=0,0,Table1[[#This Row],[Total Combined Expenses]]/Table1[[#This Row],[WL per Employee]]/Table1[[#This Row],[YE Unit Labor Headcount (FTE & SMP)]]) -> 1534.6 | P76: =G76/J76 -> 98125 | Q76: ='Support Numbers'!C74 -> 1500 | S76: =IF(Table1[[#This Row],['# WLD (Units or Users)]]=0,0,(G76+H76)/F76) -> 46038 | W76: =(G76+H76)/Q76 -> 1534.6 | X76: Includes criminal history reports for consulates, help with relocating employees' families, and investigative consultation for stakeholders like SAEV and Audit.
A77: 2024 | B77: ATPD | C77: HR Support Services | D77: CH8 Support | E77: ASC + RD | F77: ='Support Numbers'!D2 -> 60 | G77: ='Support Numbers'!D64+('BUDGET-22-25 ATPD'!AB11*0.5) -> 300000 | H77: =(0.5*('BUDGET-22-25 ATPD'!AB22-'BUDGET-22-25 ATPD'!AB13-'BUDGET-22-25 ATPD'!AB12))+'Support Numbers'!D80 -> 110850 | I77: =Table1[[#This Row],[Total Annual Labor Budget (by business unit)]]+Table1[[#This Row],[Total Annual Controllable Expenses (by business unit)]] -> 410850 | J77: 3 | K77: =Table1[[#This Row],['# WLD (Units or Users)]]*Table1[[#This Row],[Cost per WLD/yr]] -> 147610.78 | L77: =(G77+H77)/Q77 -> 2460.1796 | M77: =L77/12 -> 205.01497 | N77: =Q77/J77 -> 55.666667 | O77: =IF(Table1[[#This Row],[WL per Employee]]<=0,0,Table1[[#This Row],[Total Combined Expenses]]/Table1[[#This Row],[WL per Employee]]/Table1[[#This Row],[YE Unit Labor Headcount (FTE & SMP)]]) -> 2460.1796 | P77: =G77/J77 -> 100000 | Q77: ='Support Numbers'!D12 -> 167 | S77: =IF(Table1[[#This Row],['# WLD (Units or Users)]]=0,0,(G77+H77)/F77) -> 6847.5 | W77: =(G77+H77)/Q77 -> 2460.1796 | X77: Onboarding, ongoing, and offboarding support of seconded CH8 employees
A78: 2024 | B78: ATPD | C78: HR Support Services | D78: CH8 Support | E78: SAEV | F78: ='Support Numbers'!D4 -> 1 | G78: ='Support Numbers'!D64+('BUDGET-22-25 ATPD'!AB11*0.5) -> 300000 | H78: =0.5*('BUDGET-22-25 ATPD'!AB22-'BUDGET-22-25 ATPD'!AB13-'BUDGET-22-25 ATPD'!AB12)+'Support Numbers'!D80 -> 110850 | I78: =Table1[[#This Row],[Total Annual Labor Budget (by business unit)]]+Table1[[#This Row],[Total Annual Controllable Expenses (by business unit)]] -> 410850 | J78: 3 | K78: =Table1[[#This Row],['# WLD (Units or Users)]]*Table1[[#This Row],[Cost per WLD/yr]] -> 2460.1796 | L78: =(G78+H78)/Q78 -> 2460.1796 | M78: =L78/12 -> 205.01497 | N78: =Q78/J78 -> 55.666667 | O78: =IF(Table1[[#This Row],[WL per Employee]]<=0,0,Table1[[#This Row],[Total Combined Expenses]]/Table1[[#This Row],[WL per Employee]]/Table1[[#This Row],[YE Unit Labor Headcount (FTE & SMP)]]) -> 2460.1796 | P78: =G78/J78 -> 100000 | Q78: ='Support Numbers'!D12 -> 167 | S78: =IF(Table1[[#This Row],['# WLD (Units or Users)]]=0,0,(G78+H78)/F78) -> 410850 | W78: =(G78+H78)/Q78 -> 2460.1796 | X78: Onboarding, ongoing, and offboarding support of seconded CH8 employees
A79: 2024 | B79: ATPD | C79: HR Support Services | D79: CH8 Support | E79: VGO | F79: ='Support Numbers'!D10 -> 2 | G79: ='Support Numbers'!D64+('BUDGET-22-25 ATPD'!AB11*0.5) -> 300000 | H79: =0.5*('BUDGET-22-25 ATPD'!AB22-'BUDGET-22-25 ATPD'!AB13-'BUDGET-22-25 ATPD'!AB12)+'Support Numbers'!D80 -> 110850 | I79: =Table1[[#This Row],[Total Annual Labor Budget (by business unit)]]+Table1[[#This Row],[Total Annual Controllable Expenses (by business unit)]] -> 410850 | J79: 3 | K79: =Table1[[#This Row],['# WLD (Units or Users)]]*Table1[[#This Row],[Cost per WLD/yr]] -> 4920.3593 | L79: =(G79+H79)/Q79 -> 2460.1796 | M79: =L79/12 -> 205.01497 | N79: =Q79/J79 -> 55.666667 | O79: =IF(Table1[[#This Row],[WL per Employee]]<=0,0,Table1[[#This Row],[Total Combined Expenses]]/Table1[[#This Row],[WL per Employee]]/Table1[[#This Row],[YE Unit Labor Headcount (FTE & SMP)]]) -> 2460.1796 | P79: =G79/J79 -> 100000 | Q79: ='Support Numbers'!D12 -> 167 | S79: =IF(Table1[[#This Row],['# WLD (Units or Users)]]=0,0,(G79+H79)/F79) -> 205425 | W79: =(G79+H79)/Q79 -> 2460.1796 | X79: Onboarding, ongoing, and offboarding support of seconded CH8 employees
A80: 2024 | B80: ATPD | C80: HR Support Services | D80: CH8 Support | E80: SRI | F80: ='Support Numbers'!D6 -> 0 | G80: ='Support Numbers'!D64+('BUDGET-22-25 ATPD'!AB11*0.5) -> 300000 | H80: =0.5*('BUDGET-22-25 ATPD'!AB22-'BUDGET-22-25 ATPD'!AB13-'BUDGET-22-25 ATPD'!AB12)+'Support Numbers'!D80 -> 110850 | I80: =Table1[[#This Row],[Total Annual Labor Budget (by business unit)]]+Table1[[#This Row],[Total Annual Controllable Expenses (by business unit)]] -> 410850 | J80: 3 | K80: =Table1[[#This Row],['# WLD (Units or Users)]]*Table1[[#This Row],[Cost per WLD/yr]] -> 0 | L80: =(G80+H80)/Q80 -> 2460.1796 | M80: =L80/12 -> 205.01497 | N80: =Q80/J80 -> 55.666667 | O80: =IF(Table1[[#This Row],[WL per Employee]]<=0,0,Table1[[#This Row],[Total Combined Expenses]]/Table1[[#This Row],[WL per Employee]]/Table1[[#This Row],[YE Unit Labor Headcount (FTE & SMP)]]) -> 2460.1796 | P80: =G80/J80 -> 100000 | Q80: ='Support Numbers'!D12 -> 167 | S80: =IF(Table1[[#This Row],['# WLD (Units or Users)]]=0,0,(G80+H80)/F80) -> 0 | W80: =(G80+H80)/Q80 -> 2460.1796 | X80: Onboarding, ongoing, and offboarding support of seconded CH8 employees
A81: 2024 | B81: ATPD | C81: HR Support Services | D81: CH8 Support | E81: SPII | F81: ='Support Numbers'!D8 -> 0 | G81: ='Support Numbers'!D64+('BUDGET-22-25 ATPD'!AB11*0.5) -> 300000 | H81: =0.5*('BUDGET-22-25 ATPD'!AB22-'BUDGET-22-25 ATPD'!AB13-'BUDGET-22-25 ATPD'!AB12)+'Support Numbers'!D80 -> 110850 | I81: =Table1[[#This Row],[Total Annual Labor Budget (by business unit)]]+Table1[[#This Row],[Total Annual Controllable Expenses (by business unit)]] -> 410850 | J81: 3 | K81: =Table1[[#This Row],['# WLD (Units or Users)]]*Table1[[#This Row],[Cost per WLD/yr]] -> 0 | L81: =(G81+H81)/Q81 -> 2460.1796 | M81: =L81/12 -> 205.01497 | N81: =Q81/J81 -> 55.666667 | O81: =IF(Table1[[#This Row],[WL per Employee]]<=0,0,Table1[[#This Row],[Total Combined Expenses]]/Table1[[#This Row],[WL per Employee]]/Table1[[#This Row],[YE Unit Labor Headcount (FTE & SMP)]]) -> 2460.1796 | P81: =G81/J81 -> 100000 | Q81: ='Support Numbers'!D12 -> 167 | S81: =IF(Table1[[#This Row],['# WLD (Units or Users)]]=0,0,(G81+H81)/F81) -> 0 | W81: =(G81+H81)/Q81 -> 2460.1796 | X81: Onboarding, ongoing, and offboarding support of seconded CH8 employees
A82: 2024 | B82: ATPD | C82: HR Support Services | D82: CH8 Support | E82: NEX | F82: ='Support Numbers'!D5 -> 0 | G82: ='Support Numbers'!D64+('BUDGET-22-25 ATPD'!AB11*0.5) -> 300000 | H82: =0.5*('BUDGET-22-25 ATPD'!AB22-'BUDGET-22-25 ATPD'!AB13-'BUDGET-22-25 ATPD'!AB12)+'Support Numbers'!D80 -> 110850 | I82: =Table1[[#This Row],[Total Annual Labor Budget (by business unit)]]+Table1[[#This Row],[Total Annual Controllable Expenses (by business unit)]] -> 410850 | J82: 3 | K82: =Table1[[#This Row],['# WLD (Units or Users)]]*Table1[[#This Row],[Cost per WLD/yr]] -> 0 | L82: =(G82+H82)/Q82 -> 2460.1796 | M82: =L82/12 -> 205.01497 | N82: =Q82/J82 -> 55.666667 | O82: =IF(Table1[[#This Row],[WL per Employee]]<=0,0,Table1[[#This Row],[Total Combined Expenses]]/Table1[[#This Row],[WL per Employee]]/Table1[[#This Row],[YE Unit Labor Headcount (FTE & SMP)]]) -> 2460.1796 | P82: =G82/J82 -> 100000 | Q82: ='Support Numbers'!D12 -> 167 | S82: =IF(Table1[[#This Row],['# WLD (Units or Users)]]=0,0,(G82+H82)/F82) -> 0 | W82: =(G82+H82)/Q82 -> 2460.1796 | X82: Onboarding, ongoing, and offboarding support of seconded CH8 employees
A83: 2024 | B83: ATPD | C83: HR Support Services | D83: CH8 Support | E83: Motiva | F83: ='Support Numbers'!D7 -> 4 | G83: ='Support Numbers'!D64+('BUDGET-22-25 ATPD'!AB11*0.5) -> 300000 | H83: =0.5*('BUDGET-22-25 ATPD'!AB22-'BUDGET-22-25 ATPD'!AB13-'BUDGET-22-25 ATPD'!AB12)+'Support Numbers'!D80 -> 110850 | I83: =Table1[[#This Row],[Total Annual Labor Budget (by business unit)]]+Table1[[#This Row],[Total Annual Controllable Expenses (by business unit)]] -> 410850 | J83: 3 | K83: =Table1[[#This Row],['# WLD (Units or Users)]]*Table1[[#This Row],[Cost per WLD/yr]] -> 9840.7186 | L83: =(G83+H83)/Q83 -> 2460.1796 | M83: =L83/12 -> 205.01497 | N83: =Q83/J83 -> 55.666667 | O83: =IF(Table1[[#This Row],[WL per Employee]]<=0,0,Table1[[#This Row],[Total Combined Expenses]]/Table1[[#This Row],[WL per Employee]]/Table1[[#This Row],[YE Unit Labor Headcount (FTE & SMP)]]) -> 2460.1796 | P83: =G83/J83 -> 100000 | Q83: ='Support Numbers'!D12 -> 167 | S83: =IF(Table1[[#This Row],['# WLD (Units or Users)]]=0,0,(G83+H83)/F83) -> 102712.5 | W83: =(G83+H83)/Q83 -> 2460.1796 | X83: Onboarding, ongoing, and offboarding support of seconded CH8 employees
A84: 2024 | B84: ATPD | C84: HR Support Services | D84: CH8 Support | E84: PMT | F84: ='Support Numbers'!D9 -> 60 | G84: ='Support Numbers'!D64+('BUDGET-22-25 ATPD'!AB11*0.5) -> 300000 | H84: =0.5*('BUDGET-22-25 ATPD'!AB22-'BUDGET-22-25 ATPD'!AB13-'BUDGET-22-25 ATPD'!AB12)+'Support Numbers'!D80 -> 110850 | I84: =Table1[[#This Row],[Total Annual Labor Budget (by business unit)]]+Table1[[#This Row],[Total Annual Controllable Expenses (by business unit)]] -> 410850 | J84: 3 | K84: =Table1[[#This Row],['# WLD (Units or Users)]]*Table1[[#This Row],[Cost per WLD/yr]] -> 147610.78 | L84: =(G84+H84)/Q84 -> 2460.1796 | M84: =L84/12 -> 205.01497 | N84: =Q84/J84 -> 55.666667 | O84: =IF(Table1[[#This Row],[WL per Employee]]<=0,0,Table1[[#This Row],[Total Combined Expenses]]/Table1[[#This Row],[WL per Employee]]/Table1[[#This Row],[YE Unit Labor Headcount (FTE & SMP)]]) -> 2460.1796 | P84: =G84/J84 -> 100000 | Q84: ='Support Numbers'!D12 -> 167 | S84: =IF(Table1[[#This Row],['# WLD (Units or Users)]]=0,0,(G84+H84)/F84) -> 6847.5 | W84: =(G84+H84)/Q84 -> 2460.1796 | X84: Onboarding, ongoing, and offboarding support of seconded CH8 employees
A85: 2024 | B85: ATPD | C85: HR Support Services | D85: CH8 Support | E85: Internships | F85: ='Support Numbers'!D11 -> 40 | G85: ='Support Numbers'!D64+('BUDGET-22-25 ATPD'!AB11*0.5) -> 300000 | H85: =0.5*('BUDGET-22-25 ATPD'!AB22-'BUDGET-22-25 ATPD'!AB13-'BUDGET-22-25 ATPD'!AB12)+'Support Numbers'!D80 -> 110850 | I85: =Table1[[#This Row],[Total Annual Labor Budget (by business unit)]]+Table1[[#This Row],[Total Annual Controllable Expenses (by business unit)]] -> 410850 | J85: 3 | K85: =Table1[[#This Row],['# WLD (Units or Users)]]*Table1[[#This Row],[Cost per WLD/yr]] -> 98407.186 | L85: =(G85+H85)/Q85 -> 2460.1796 | M85: =L85/12 -> 205.01497 | N85: =Q85/J85 -> 55.666667 | O85: =IF(Table1[[#This Row],[WL per Employee]]<=0,0,Table1[[#This Row],[Total Combined Expenses]]/Table1[[#This Row],[WL per Employee]]/Table1[[#This Row],[YE Unit Labor Headcount (FTE & SMP)]]) -> 2460.1796 | P85: =G85/J85 -> 100000 | Q85: ='Support Numbers'!D12 -> 167 | S85: =IF(Table1[[#This Row],['# WLD (Units or Users)]]=0,0,(G85+H85)/F85) -> 10271.25 | W85: =(G85+H85)/Q85 -> 2460.1796 | X85: Onboarding, ongoing, and offboarding support of seconded CH8 employees
A86: 2024 | B86: ATPD | C86: HR Support Services | D86: Medical Referral | E86: Medical Referrals | F86: ='Support Numbers'!D19 -> 50 | G86: ='Support Numbers'!D65 -> 117000 | H86: =0.5*('BUDGET-22-25 ATPD'!AB22-'BUDGET-22-25 ATPD'!AB13-'BUDGET-22-25 ATPD'!AB12) -> 35850 | I86: =Table1[[#This Row],[Total Annual Labor Budget (by business unit)]]+Table1[[#This Row],[Total Annual Controllable Expenses (by business unit)]] -> 152850 | J86: 1 | K86: =Table1[[#This Row],['# WLD (Units or Users)]]*Table1[[#This Row],[Cost per WLD/yr]] -> 152850 | L86: =(G86+H86)/Q86 -> 3057 | M86: =L86/12 -> 254.75 | N86: =Q86/J86 -> 50 | O86: =IF(Table1[[#This Row],[WL per Employee]]<=0,0,Table1[[#This Row],[Total Combined Expenses]]/Table1[[#This Row],[WL per Employee]]/Table1[[#This Row],[YE Unit Labor Headcount (FTE & SMP)]]) -> 3057 | P86: =G86/J86 -> 117000 | Q86: ='Support Numbers'!D19 -> 50 | S86: =IF(Table1[[#This Row],['# WLD (Units or Users)]]=0,0,(G86+H86)/F86) -> 3057 | W86: =(G86+H86)/Q86 -> 3057 | X86: Coordination of medical referral patience and programs
A87: 2024 | B87: ATPD | C87: HR Support Services | D87: CH14 Fin Support | E87: All Students | F87: ='Support Numbers'!D18 -> 1350 | G87: ='Support Numbers'!D66+('BUDGET-22-25 ATPD'!AB11*0.5) -> 215000 | H87: =0.5*('BUDGET-22-25 ATPD'!AB22-'BUDGET-22-25 ATPD'!AB13-'BUDGET-22-25 ATPD'!AB12) -> 35850 | I87: =Table1[[#This Row],[Total Annual Labor Budget (by business unit)]]+Table1[[#This Row],[Total Annual Controllable Expenses (by business unit)]] -> 250850 | J87: 2 | K87: =Table1[[#This Row],['# WLD (Units or Users)]]*Table1[[#This Row],[Cost per WLD/yr]] -> 250850 | L87: =(G87+H87)/Q87 -> 185.81481 | M87: =L87/12 -> 15.484568 | N87: =Q87/J87 -> 675 | O87: =IF(Table1[[#This Row],[WL per Employee]]<=0,0,Table1[[#This Row],[Total Combined Expenses]]/Table1[[#This Row],[WL per Employee]]/Table1[[#This Row],[YE Unit Labor Headcount (FTE & SMP)]]) -> 185.81481 | P87: =G87/J87 -> 107500 | Q87: =F87 -> 1350 | S87: =IF(Table1[[#This Row],['# WLD (Units or Users)]]=0,0,(G87+H87)/F87) -> 185.81481 | W87: =(G87+H87)/Q87 -> 185.81481 | X87: Help desk for all students inqueries
A88: 2024 | B88: ATPD | C88: Academic Prog | D88: CH14 Advisory | E88: Undergrad | F88: ='Support Numbers'!D15 -> 950 | G88: ='BUDGET-22-25 ATPD'!P8+'BUDGET-22-25 ATPD'!P12 -> 1290000 | H88: =('BUDGET-22-25 ATPD'!P9+'BUDGET-22-25 ATPD'!P22)-'BUDGET-22-25 ATPD'!P13-'BUDGET-22-25 ATPD'!P12+'Support Numbers'!D78 -> 566000 | I88: =Table1[[#This Row],[Total Annual Labor Budget (by business unit)]]+Table1[[#This Row],[Total Annual Controllable Expenses (by business unit)]] -> 1856000 | J88: ='BUDGET-22-25 ATPD'!P40+'BUDGET-22-25 ATPD'!P42 -> 11 | K88: =Table1[[#This Row],['# WLD (Units or Users)]]*Table1[[#This Row],[Cost per WLD/yr]] -> 1306074.1 | L88: =(G88+H88)/Q88 -> 1374.8148 | M88: =L88/12 -> 114.5679 | N88: =Q88/J88 -> 122.72727 | O88: =IF(Table1[[#This Row],[WL per Employee]]<=0,0,Table1[[#This Row],[Total Combined Expenses]]/Table1[[#This Row],[WL per Employee]]/Table1[[#This Row],[YE Unit Labor Headcount (FTE & SMP)]]) -> 1374.8148 | P88: =G88/J88 -> 117272.73 | Q88: ='Support Numbers'!D18 -> 1350 | S88: =IF(Table1[[#This Row],['# WLD (Units or Users)]]=0,0,(G88+H88)/F88) -> 1953.6842 | W88: =(G88+H88)/Q88 -> 1374.8148 | X88: Academic advisory for SAO sponsored students in an Undergrad program
A89: 2024 | B89: ATPD | C89: Academic Prog | D89: CH14 Advisory | E89: Associates | F89: ='Support Numbers'!D16 -> 50 | G89: ='BUDGET-22-25 ATPD'!P8+'BUDGET-22-25 ATPD'!P12 -> 1290000 | H89: =('BUDGET-22-25 ATPD'!P9+'BUDGET-22-25 ATPD'!P22)-'BUDGET-22-25 ATPD'!P13-'BUDGET-22-25 ATPD'!P12+'Support Numbers'!D78 -> 566000 | I89: =Table1[[#This Row],[Total Annual Labor Budget (by business unit)]]+Table1[[#This Row],[Total Annual Controllable Expenses (by business unit)]] -> 1856000 | J89: ='BUDGET-22-25 ATPD'!P40+'BUDGET-22-25 ATPD'!P42 -> 11 | K89: =Table1[[#This Row],['# WLD (Units or Users)]]*Table1[[#This Row],[Cost per WLD/yr]] -> 68740.741 | L89: =(G89+H89)/Q89 -> 1374.8148 | M89: =L89/12 -> 114.5679 | N89: =Q89/J89 -> 122.72727 | O89: =IF(Table1[[#This Row],[WL per Employee]]<=0,0,Table1[[#This Row],[Total Combined Expenses]]/Table1[[#This Row],[WL per Employee]]/Table1[[#This Row],[YE Unit Labor Headcount (FTE & SMP)]]) -> 1374.8148 | P89: =G89/J89 -> 117272.73 | Q89: ='Support Numbers'!D18 -> 1350 | S89: =IF(Table1[[#This Row],['# WLD (Units or Users)]]=0,0,(G89+H89)/F89) -> 37120 | W89: =(G89+H89)/Q89 -> 1374.8148 | X89: Academic advisory for SAO sponsored students in an Associates program
A90: 2024 | B90: ATPD | C90: Academic Prog | D90: CH14 Advisory | E90: Advanced | F90: ='Support Numbers'!D17 -> 350 | G90: ='BUDGET-22-25 ATPD'!P8+'BUDGET-22-25 ATPD'!P12 -> 1290000 | H90: =('BUDGET-22-25 ATPD'!P9+'BUDGET-22-25 ATPD'!P22)-'BUDGET-22-25 ATPD'!P13-'BUDGET-22-25 ATPD'!P12+'Support Numbers'!D78 -> 566000 | I90: =Table1[[#This Row],[Total Annual Labor Budget (by business unit)]]+Table1[[#This Row],[Total Annual Controllable Expenses (by business unit)]] -> 1856000 | J90: ='BUDGET-22-25 ATPD'!P40+'BUDGET-22-25 ATPD'!P42 -> 11 | K90: =Table1[[#This Row],['# WLD (Units or Users)]]*Table1[[#This Row],[Cost per WLD/yr]] -> 481185.19 | L90: =(G90+H90)/Q90 -> 1374.8148 | M90: =L90/12 -> 114.5679 | N90: =Q90/J90 -> 122.72727 | O90: =IF(Table1[[#This Row],[WL per Employee]]<=0,0,Table1[[#This Row],[Total Combined Expenses]]/Table1[[#This Row],[WL per Employee]]/Table1[[#This Row],[YE Unit Labor Headcount (FTE & SMP)]]) -> 1374.8148 | P90: =G90/J90 -> 117272.73 | Q90: ='Support Numbers'!D18 -> 1350 | S90: =IF(Table1[[#This Row],['# WLD (Units or Users)]]=0,0,(G90+H90)/F90) -> 5302.8571 | W90: =(G90+H90)/Q90 -> 1374.8148 | X90: Academic advisory for SAO sponsored students in an Advanced degree program
A91: 2024 | B91: ATPD | C91: Tech Professional Unit | D91: Trainees Support | E91: CH14 | F91: ='Support Numbers'!D22 -> 20 | G91: ='BUDGET-22-25 ATPD'!V8+'BUDGET-22-25 ATPD'!V12 -> 668000 | H91: ='BUDGET-22-25 ATPD'!V9+'BUDGET-22-25 ATPD'!V22-'BUDGET-22-25 ATPD'!V12-'BUDGET-22-25 ATPD'!V13+'Support Numbers'!D79 -> 187900 | I91: =Table1[[#This Row],[Total Annual Labor Budget (by business unit)]]+Table1[[#This Row],[Total Annual Controllable Expenses (by business unit)]] -> 855900 | J91: ='BUDGET-22-25 ATPD'!V39 -> 5 | K91: =Table1[[#This Row],['# WLD (Units or Users)]]*Table1[[#This Row],[Cost per WLD/yr]] -> 427950 | L91: =(G91+H91)/Q91 -> 21397.5 | M91: =L91/12 -> 1783.125 | N91: =Q91/J91 -> 8 | O91: =IF(Table1[[#This Row],[WL per Employee]]<=0,0,Table1[[#This Row],[Total Combined Expenses]]/Table1[[#This Row],[WL per Employee]]/Table1[[#This Row],[YE Unit Labor Headcount (FTE & SMP)]]) -> 21397.5 | P91: =G91/J91 -> 133600 | Q91: ='Support Numbers'!D24 -> 40 | S91: =IF(Table1[[#This Row],['# WLD (Units or Users)]]=0,0,(G91+H91)/F91) -> 42795 | W91: =(G91+H91)/Q91 -> 21397.5 | X91: Coordination and support for sponsored CH14 trainee programs
A92: 2024 | B92: ATPD | C92: Tech Professional Unit | D92: Trainees Support | E92: CH8 | F92: ='Support Numbers'!D23 -> 20 | G92: ='BUDGET-22-25 ATPD'!V8+'BUDGET-22-25 ATPD'!V12 -> 668000 | H92: ='BUDGET-22-25 ATPD'!V9+'BUDGET-22-25 ATPD'!V22-'BUDGET-22-25 ATPD'!V12-'BUDGET-22-25 ATPD'!V13+'Support Numbers'!D79 -> 187900 | I92: =Table1[[#This Row],[Total Annual Labor Budget (by business unit)]]+Table1[[#This Row],[Total Annual Controllable Expenses (by business unit)]] -> 855900 | J92: ='BUDGET-22-25 ATPD'!V39 -> 5 | K92: =Table1[[#This Row],['# WLD (Units or Users)]]*Table1[[#This Row],[Cost per WLD/yr]] -> 427950 | L92: =(G92+H92)/Q92 -> 21397.5 | M92: =L92/12 -> 1783.125 | N92: =Q92/J92 -> 8 | O92: =IF(Table1[[#This Row],[WL per Employee]]<=0,0,Table1[[#This Row],[Total Combined Expenses]]/Table1[[#This Row],[WL per Employee]]/Table1[[#This Row],[YE Unit Labor Headcount (FTE & SMP)]]) -> 21397.5 | P92: =G92/J92 -> 133600 | Q92: ='Support Numbers'!D24 -> 40 | S92: =IF(Table1[[#This Row],['# WLD (Units or Users)]]=0,0,(G92+H92)/F92) -> 42795 | W92: =(G92+H92)/Q92 -> 21397.5 | X92: Coordination and support for sponsored CH8 trainee programs
A93: 2024 | B93: CIG | C93: Background Investigations | D93: Expat Hiring | E93: SAO HR SSD | F93: ='Support Numbers'!D70 -> 250 | G93: ='BUDGET-22-25 HRS & CIG'!AH8+'BUDGET-22-25 HRS & CIG'!AH12 -> 410000 | H93: ='BUDGET-22-25 HRS & CIG'!AH9+'BUDGET-22-25 HRS & CIG'!AH22-'BUDGET-22-25 HRS & CIG'!AH12 -> 1807000 | I93: =Table1[[#This Row],[Total Annual Labor Budget (by business unit)]]+Table1[[#This Row],[Total Annual Controllable Expenses (by business unit)]] -> 2217000 | J93: ='BUDGET-22-25 HRS & CIG'!AH38+'BUDGET-22-25 HRS & CIG'!AH40 -> 4 | K93: =Table1[[#This Row],['# WLD (Units or Users)]]*Table1[[#This Row],[Cost per WLD/yr]] -> 595967.74 | L93: =(G93+H93)/Q93 -> 2383.871 | M93: =L93/12 -> 198.65591 | N93: =Q93/J93 -> 232.5 | O93: =IF(Table1[[#This Row],[WL per Employee]]<=0,0,Table1[[#This Row],[Total Combined Expenses]]/Table1[[#This Row],[WL per Employee]]/Table1[[#This Row],[YE Unit Labor Headcount (FTE & SMP)]]) -> 2383.871 | P93: =G93/J93 -> 102500 | Q93: ='Support Numbers'!D74 -> 930 | S93: =IF(Table1[[#This Row],['# WLD (Units or Users)]]=0,0,(G93+H93)/F93) -> 8868 | W93: =(G93+H93)/Q93 -> 2383.871 | X93: Background checks initated for candidates consenting to checking at time of technically qualified and all candidates at offer accepted.
A94: 2024 | B94: CIG | C94: Background Investigations | D94: Domestic | E94: ASC+ATA | F94: ='Support Numbers'!D71 -> 170 | G94: ='BUDGET-22-25 HRS & CIG'!AH8+'BUDGET-22-25 HRS & CIG'!AH12 -> 410000 | H94: ='BUDGET-22-25 HRS & CIG'!AH9+'BUDGET-22-25 HRS & CIG'!AH22-'BUDGET-22-25 HRS & CIG'!AH12 -> 1807000 | I94: =Table1[[#This Row],[Total Annual Labor Budget (by business unit)]]+Table1[[#This Row],[Total Annual Controllable Expenses (by business unit)]] -> 2217000 | J94: ='BUDGET-22-25 HRS & CIG'!AH38+'BUDGET-22-25 HRS & CIG'!AH40 -> 4 | K94: =Table1[[#This Row],['# WLD (Units or Users)]]*Table1[[#This Row],[Cost per WLD/yr]] -> 405258.06 | L94: =(G94+H94)/Q94 -> 2383.871 | M94: =L94/12 -> 198.65591 | N94: =Q94/J94 -> 232.5 | O94: =IF(Table1[[#This Row],[WL per Employee]]<=0,0,Table1[[#This Row],[Total Combined Expenses]]/Table1[[#This Row],[WL per Employee]]/Table1[[#This Row],[YE Unit Labor Headcount (FTE & SMP)]]) -> 2383.871 | P94: =G94/J94 -> 102500 | Q94: ='Support Numbers'!D74 -> 930 | S94: =IF(Table1[[#This Row],['# WLD (Units or Users)]]=0,0,(G94+H94)/F94) -> 13041.176 | W94: =(G94+H94)/Q94 -> 2383.871 | X94: Background checks for all domestic hiring efforts
A95: 2024 | B95: CIG | C95: Background Investigations | D95: SAO Corp Security | E95: SAO Corp Security | F95: ='Support Numbers'!D72 -> 500 | G95: ='BUDGET-22-25 HRS & CIG'!AH8+'BUDGET-22-25 HRS & CIG'!AH12 -> 410000 | H95: ='BUDGET-22-25 HRS & CIG'!AH9+'BUDGET-22-25 HRS & CIG'!AH22-'BUDGET-22-25 HRS & CIG'!AH12 -> 1807000 | I95: =Table1[[#This Row],[Total Annual Labor Budget (by business unit)]]+Table1[[#This Row],[Total Annual Controllable Expenses (by business unit)]] -> 2217000 | J95: ='BUDGET-22-25 HRS & CIG'!AH38+'BUDGET-22-25 HRS & CIG'!AH40 -> 4 | K95: =Table1[[#This Row],['# WLD (Units or Users)]]*Table1[[#This Row],[Cost per WLD/yr]] -> 1191935.5 | L95: =(G95+H95)/Q95 -> 2383.871 | M95: =L95/12 -> 198.65591 | N95: =Q95/J95 -> 232.5 | O95: =IF(Table1[[#This Row],[WL per Employee]]<=0,0,Table1[[#This Row],[Total Combined Expenses]]/Table1[[#This Row],[WL per Employee]]/Table1[[#This Row],[YE Unit Labor Headcount (FTE & SMP)]]) -> 2383.871 | P95: =G95/J95 -> 102500 | Q95: ='Support Numbers'!D74 -> 930 | S95: =IF(Table1[[#This Row],['# WLD (Units or Users)]]=0,0,(G95+H95)/F95) -> 4434 | W95: =(G95+H95)/Q95 -> 2383.871 | X95: Background checks initiated and completed for Saudi students who studied in the US/Canada and applied for jobs at Saudi Aramco upon returning home.
A96: 2024 | B96: CIG | C96: Background Investigations | D96: Special Inv. Requests | E96: Misc. | F96: ='Support Numbers'!D73 -> 10 | G96: ='BUDGET-22-25 HRS & CIG'!AH8+'BUDGET-22-25 HRS & CIG'!AH12 -> 410000 | H96: ='BUDGET-22-25 HRS & CIG'!AH9+'BUDGET-22-25 HRS & CIG'!AH22-'BUDGET-22-25 HRS & CIG'!AH12 -> 1807000 | I96: =Table1[[#This Row],[Total Annual Labor Budget (by business unit)]]+Table1[[#This Row],[Total Annual Controllable Expenses (by business unit)]] -> 2217000 | J96: ='BUDGET-22-25 HRS & CIG'!AH38+'BUDGET-22-25 HRS & CIG'!AH40 -> 4 | K96: =Table1[[#This Row],['# WLD (Units or Users)]]*Table1[[#This Row],[Cost per WLD/yr]] -> 23838.71 | L96: =(G96+H96)/Q96 -> 2383.871 | M96: =L96/12 -> 198.65591 | N96: =Q96/J96 -> 232.5 | O96: =IF(Table1[[#This Row],[WL per Employee]]<=0,0,Table1[[#This Row],[Total Combined Expenses]]/Table1[[#This Row],[WL per Employee]]/Table1[[#This Row],[YE Unit Labor Headcount (FTE & SMP)]]) -> 2383.871 | P96: =G96/J96 -> 102500 | Q96: ='Support Numbers'!D74 -> 930 | S96: =IF(Table1[[#This Row],['# WLD (Units or Users)]]=0,0,(G96+H96)/F96) -> 221700 | W96: =(G96+H96)/Q96 -> 2383.871 | X96: Includes criminal history reports for consulates, help with relocating employees' families, and investigative consultation for stakeholders like SAEV and Audit.
A97: 2024 | B97: HRS | C97: All HRS | D97: HR Support Services | E97: ASC + RD | F97: ='Support Numbers'!D30 -> 507 | G97: =('BUDGET-22-25 HRS & CIG'!D8-'BUDGET-22-25 HRS & CIG'!D4) +'BUDGET-22-25 HRS & CIG'!J8+'BUDGET-22-25 HRS & CIG'!P8+'BUDGET-22-25 HRS & CIG'!V8 +'BUDGET-22-25 HRS & CIG'!D12 +'BUDGET-22-25 HRS & CIG'!J12+'BUDGET-22-25 HRS & CIG'!P12+'BUDGET-22-25 HRS & CIG'!V12 -> 2473500 | H97: ='BUDGET-22-25 HRS & CIG'!D9+'BUDGET-22-25 HRS & CIG'!J9+'BUDGET-22-25 HRS & CIG'!V9+'BUDGET-22-25 HRS & CIG'!P9 +('BUDGET-22-25 HRS & CIG'!D22-'BUDGET-22-25 HRS & CIG'!D12-'BUDGET-22-25 HRS & CIG'!D13) +('BUDGET-22-25 HRS & CIG'!J22-'BUDGET-22-25 HRS & CIG'!J13-'BUDGET-22-25 HRS & CIG'!J12) +('BUDGET-22-25 HRS & CIG'!P22-'BUDGET-22-25 HRS & CIG'!P13-'BUDGET-22-25 HRS & CIG'!P12) +('BUDGET-22-25 HRS & CIG'!V22-'BUDGET-22-25 HRS & CIG'!V13-'BUDGET-22-25 HRS & CIG'!V12) -> 710775 | I97: =Table1[[#This Row],[Total Annual Labor Budget (by business unit)]]+Table1[[#This Row],[Total Annual Controllable Expenses (by business unit)]] -> 3184275 | J97: ='BUDGET-22-25 HRS & CIG'!D37+'BUDGET-22-25 HRS & CIG'!J37+'BUDGET-22-25 HRS & CIG'!P37+'BUDGET-22-25 HRS & CIG'!V37 -> 19 | K97: =Table1[[#This Row],['# WLD (Units or Users)]]*Table1[[#This Row],[Cost per WLD/yr]] -> 2306324.9 | L97: =(G97+H97)/Q97 -> 4548.9643 | M97: =L97/12 -> 379.08036 | N97: =Q97/J97 -> 36.842105 | O97: =IF(Table1[[#This Row],[WL per Employee]]<=0,0,Table1[[#This Row],[Total Combined Expenses]]/Table1[[#This Row],[WL per Employee]]/Table1[[#This Row],[YE Unit Labor Headcount (FTE & SMP)]]) -> 4548.9643 | P97: =G97/J97 -> 130184.21 | Q97: ='Support Numbers'!D36 -> 700 | S97: =IF(Table1[[#This Row],['# WLD (Units or Users)]]=0,0,(G97+H97)/F97) -> 6280.6213 | W97: =(G97+H97)/Q97 -> 4548.9643 | X97: Full life cycle HR support - hire to retire (onboarding, HRIS, personnel, training, offboarding) for ASC/RD employees, temps, independent contractors
A98: 2024 | B98: HRS | C98: All HRS | D98: HR Support Services | E98: AAC | F98: ='Support Numbers'!D27 -> 6 | G98: =('BUDGET-22-25 HRS & CIG'!D8-'BUDGET-22-25 HRS & CIG'!D4) +'BUDGET-22-25 HRS & CIG'!J8+'BUDGET-22-25 HRS & CIG'!P8+'BUDGET-22-25 HRS & CIG'!V8 +'BUDGET-22-25 HRS & CIG'!D12 +'BUDGET-22-25 HRS & CIG'!J12+'BUDGET-22-25 HRS & CIG'!P12+'BUDGET-22-25 HRS & CIG'!V12 -> 2473500 | H98: ='BUDGET-22-25 HRS & CIG'!D9+'BUDGET-22-25 HRS & CIG'!J9+'BUDGET-22-25 HRS & CIG'!V9+'BUDGET-22-25 HRS & CIG'!P9 +('BUDGET-22-25 HRS & CIG'!D22-'BUDGET-22-25 HRS & CIG'!D12-'BUDGET-22-25 HRS & CIG'!D13) +('BUDGET-22-25 HRS & CIG'!J22-'BUDGET-22-25 HRS & CIG'!J13-'BUDGET-22-25 HRS & CIG'!J12) +('BUDGET-22-25 HRS & CIG'!P22-'BUDGET-22-25 HRS & CIG'!P13-'BUDGET-22-25 HRS & CIG'!P12) +('BUDGET-22-25 HRS & CIG'!V22-'BUDGET-22-25 HRS & CIG'!V13-'BUDGET-22-25 HRS & CIG'!V12) -> 710775 | I98: =Table1[[#This Row],[Total Annual Labor Budget (by business unit)]]+Table1[[#This Row],[Total Annual Controllable Expenses (by business unit)]] -> 3184275 | J98: ='BUDGET-22-25 HRS & CIG'!D37+'BUDGET-22-25 HRS & CIG'!J37+'BUDGET-22-25 HRS & CIG'!P37+'BUDGET-22-25 HRS & CIG'!V37 -> 19 | K98: =Table1[[#This Row],['# WLD (Units or Users)]]*Table1[[#This Row],[Cost per WLD/yr]] -> 27293.786 | L98: =(G98+H98)/Q98 -> 4548.9643 | M98: =L98/12 -> 379.08036 | N98: =Q98/J98 -> 36.842105 | O98: =IF(Table1[[#This Row],[WL per Employee]]<=0,0,Table1[[#This Row],[Total Combined Expenses]]/Table1[[#This Row],[WL per Employee]]/Table1[[#This Row],[YE Unit Labor Headcount (FTE & SMP)]]) -> 4548.9643 | P98: =G98/J98 -> 130184.21 | Q98: ='Support Numbers'!D36 -> 700 | S98: =IF(Table1[[#This Row],['# WLD (Units or Users)]]=0,0,(G98+H98)/F98) -> 530712.5 | W98: =(G98+H98)/Q98 -> 4548.9643 | X98: Full life cycle HR support - hire to retire (onboarding, HRIS, personnel, training, offboarding) for AAC employees, temps, independent contractors
A99: 2024 | B99: HRS | C99: All HRS | D99: HR Support Services | E99: ASBCO | F99: ='Support Numbers'!D29 -> 8 | G99: =('BUDGET-22-25 HRS & CIG'!D8-'BUDGET-22-25 HRS & CIG'!D4) +'BUDGET-22-25 HRS & CIG'!J8+'BUDGET-22-25 HRS & CIG'!P8+'BUDGET-22-25 HRS & CIG'!V8 +'BUDGET-22-25 HRS & CIG'!D12 +'BUDGET-22-25 HRS & CIG'!J12+'BUDGET-22-25 HRS & CIG'!P12+'BUDGET-22-25 HRS & CIG'!V12 -> 2473500 | H99: ='BUDGET-22-25 HRS & CIG'!D9+'BUDGET-22-25 HRS & CIG'!J9+'BUDGET-22-25 HRS & CIG'!V9+'BUDGET-22-25 HRS & CIG'!P9 +('BUDGET-22-25 HRS & CIG'!D22-'BUDGET-22-25 HRS & CIG'!D12-'BUDGET-22-25 HRS & CIG'!D13) +('BUDGET-22-25 HRS & CIG'!J22-'BUDGET-22-25 HRS & CIG'!J13-'BUDGET-22-25 HRS & CIG'!J12) +('BUDGET-22-25 HRS & CIG'!P22-'BUDGET-22-25 HRS & CIG'!P13-'BUDGET-22-25 HRS & CIG'!P12) +('BUDGET-22-25 HRS & CIG'!V22-'BUDGET-22-25 HRS & CIG'!V13-'BUDGET-22-25 HRS & CIG'!V12) -> 710775 | I99: =Table1[[#This Row],[Total Annual Labor Budget (by business unit)]]+Table1[[#This Row],[Total Annual Controllable Expenses (by business unit)]] -> 3184275 | J99: ='BUDGET-22-25 HRS & CIG'!D37+'BUDGET-22-25 HRS & CIG'!J37+'BUDGET-22-25 HRS & CIG'!P37+'BUDGET-22-25 HRS & CIG'!V37 -> 19 | K99: =Table1[[#This Row],['# WLD (Units or Users)]]*Table1[[#This Row],[Cost per WLD/yr]] -> 36391.714 | L99: =(G99+H99)/Q99 -> 4548.9643 | M99: =L99/12 -> 379.08036 | N99: =Q99/J99 -> 36.842105 | O99: =IF(Table1[[#This Row],[WL per Employee]]<=0,0,Table1[[#This Row],[Total Combined Expenses]]/Table1[[#This Row],[WL per Employee]]/Table1[[#This Row],[YE Unit Labor Headcount (FTE & SMP)]]) -> 4548.9643 | P99: =G99/J99 -> 130184.21 | Q99: ='Support Numbers'!D36 -> 700 | S99: =IF(Table1[[#This Row],['# WLD (Units or Users)]]=0,0,(G99+H99)/F99) -> 398034.38 | W99: =(G99+H99)/Q99 -> 4548.9643 | X99: Full life cycle HR support - hire to retire (onboarding, HRIS, personnel, training, offboarding) for ASBCO employees, temps, independent contractors
A100: 2024 | B100: HRS | C100: All HRS | D100: HR Support Services | E100: ATA | F100: ='Support Numbers'!D31 -> 150 | G100: =('BUDGET-22-25 HRS & CIG'!D8-'BUDGET-22-25 HRS & CIG'!D4) +'BUDGET-22-25 HRS & CIG'!J8+'BUDGET-22-25 HRS & CIG'!P8+'BUDGET-22-25 HRS & CIG'!V8 +'BUDGET-22-25 HRS & CIG'!D12 +'BUDGET-22-25 HRS & CIG'!J12+'BUDGET-22-25 HRS & CIG'!P12+'BUDGET-22-25 HRS & CIG'!V12 -> 2473500 | H100: ='BUDGET-22-25 HRS & CIG'!D9+'BUDGET-22-25 HRS & CIG'!J9+'BUDGET-22-25 HRS & CIG'!V9+'BUDGET-22-25 HRS & CIG'!P9 +('BUDGET-22-25 HRS & CIG'!D22-'BUDGET-22-25 HRS & CIG'!D12-'BUDGET-22-25 HRS & CIG'!D13) +('BUDGET-22-25 HRS & CIG'!J22-'BUDGET-22-25 HRS & CIG'!J13-'BUDGET-22-25 HRS & CIG'!J12) +('BUDGET-22-25 HRS & CIG'!P22-'BUDGET-22-25 HRS & CIG'!P13-'BUDGET-22-25 HRS & CIG'!P12) +('BUDGET-22-25 HRS & CIG'!V22-'BUDGET-22-25 HRS & CIG'!V13-'BUDGET-22-25 HRS & CIG'!V12) -> 710775 | I100: =Table1[[#This Row],[Total Annual Labor Budget (by business unit)]]+Table1[[#This Row],[Total Annual Controllable Expenses (by business unit)]] -> 3184275 | J100: ='BUDGET-22-25 HRS & CIG'!D37+'BUDGET-22-25 HRS & CIG'!J37+'BUDGET-22-25 HRS & CIG'!P37+'BUDGET-22-25 HRS & CIG'!V37 -> 19 | K100: =Table1[[#This Row],['# WLD (Units or Users)]]*Table1[[#This Row],[Cost per WLD/yr]] -> 682344.64 | L100: =(G100+H100)/Q100 -> 4548.9643 | M100: =L100/12 -> 379.08036 | N100: =Q100/J100 -> 36.842105 | O100: =IF(Table1[[#This Row],[WL per Employee]]<=0,0,Table1[[#This Row],[Total Combined Expenses]]/Table1[[#This Row],[WL per Employee]]/Table1[[#This Row],[YE Unit Labor Headcount (FTE & SMP)]]) -> 4548.9643 | P100: =G100/J100 -> 130184.21 | Q100: ='Support Numbers'!D36 -> 700 | S100: =IF(Table1[[#This Row],['# WLD (Units or Users)]]=0,0,(G100+H100)/F100) -> 21228.5 | W100: =(G100+H100)/Q100 -> 4548.9643 | X100: Full life cycle HR support - hire to retire (onboarding, HRIS, training, offboarding) for ATA employees, temps, independent contractors
...

Sheet Support Numbers
A1: ATPD - Chapter 8 Employees | B1: YE Active 2022 | C1: YE Active 2023 | D1: YE Active 2024 | E1: YE Active 2025 | F1: 2026
A2: ASC & RD | B2: 40 | C2: 50 | D2: 60 | E2: 70
A3: ATA | B3: 0 | C3: 0 | D3: 0 | E3: 1
A4: SAEV | B4: 0 | C4: 0 | D4: 1 | E4: 0
A5: NEx | B5: 1 | C5: 1 | D5: 0 | E5: 0
A6: SRI | B6: 2 | C6: 0 | D6: 0 | E6: 0
A7: Motiva | B7: 2 | C7: 3 | D7: 4 | E7: 5
A8: SPI | B8: 3 | C8: 3 | D8: 0 | E8: 0
A9: PMT | B9: 30 | C9: 80 | D9: 60 | E9: 90
A10: VGO | B10: 0 | C10: 0 | D10: 2 | E10: 2
A11: Other Company Internship | B11: 80 | C11: 50 | D11: 40 | E11: 70
A12: Total Chapter 8 | B12: =SUM(B2:B11) -> 158 | C12: =SUM(C2:C11) -> 187 | D12: =SUM(D2:D11) -> 167 | E12: 179
A14: ATPD - CH14 Support | B14: Year End 2022 | C14: Year End 2023 | D14: Year End 2024 | E14: Year End 2025 | F14: 2026
A15: # of CH14 Students (CDPNE) | B15: 800 | C15: 900 | D15: 950 | E15: 1000
A16: # of CH14 Students (ASDP) | B16: 30 | C16: 40 | D16: 50 | E16: 60
A17: # of CH14 Students (ADVDEG) | B17: 250 | C17: 330 | D17: 350 | E17: 280
A18: Total # of CH14 | B18: =SUM(B15:B17) -> 1080 | C18: =SUM(C15:C17) -> 1270 | D18: =SUM(D15:D17) -> 1350 | E18: =SUM(E15:E17) -> 1340
A19: # of Medical Referrals | B19: 50 | C19: 25 | D19: 50 | E19: 50
A21: ATPD - Trainees | B21: 2022 | C21: 2023 | D21: 2024 | E21: 2025 | F21: 2026
A22: CH14 | B22: 25 | C22: 10 | D22: 20 | E22: 40
A23: Ch8 | B23: 25 | C23: 20 | D23: 20 | E23: 15
A24: Total | B24: =SUM(B22:B23) -> 50 | C24: =SUM(C22:C23) -> 30 | D24: =SUM(D22:D23) -> 40 | E24: =SUM(E22:E23) -> 55
A26: HRS Support (US$ Emp & Temp) | B26: Year-End 2022 | C26: Year-End 2023 | D26: Year-End 2024 | E26: Year-End 2025 | F26: 2026
A27: AAC-Aramco Associated Company | B27: 10 | C27: 10 | D27: 6 | E27: 5
A28: APM - Aramco Performance Materials | B28: 11 | C28: 0 | D28: 0 | E28: 0
A29: ASBC-Aramco Shared Benefit Company | B29: 6 | C29: 8 | D29: 8 | E29: 8
A30: ASC-Aramco Services Company | B30: 500 | C30: 501 | D30: 507 | E30: 515
A31: ATA-Aramco Trading Americas | B31: 0 | C31: 0 | D31: 150 | E31: 150
A32: AVMC-Aramco Vent. Mgt Consultant Co | B32: 5 | C32: 8 | D32: 12 | E32: 12
A33: SAEV-Saudi Aramco Energy Ventures | B33: 10 | C33: 11 | D33: 13 | E33: 9
A34: SRI-Saudi Refining Inc. | B34: 4 | C34: 4 | D34: 4 | E34: 3
A35: SPII | B35: 12 | C35: 15 | D35: 0 | E35: 0
A36: Grand Total | B36: =SUM(B27:B35) -> 558 | C36: =SUM(C27:C35) -> 557 | D36: =SUM(D27:D35) -> 700 | E36: 660 | F36: 660
A38: HRS Support (2025) | B38: US$ Employee | C38: Saudi Ch8 Employee | D38: Temp Personnel | E38: Contractor | F38: Grand Total
A39: AAC-Aramco Associated Company | F39: 5
A40: ASBC-Aramco Shared Benefit Company | F40: 12
A41: ASC-Aramco Services Company | F41: 664
A42: ATA-Aramco Trading Americas | F42: 269
A43: AVMC-Aramco Vent. Mgt Consultant Co | F43: 12
A44: SAEV-Saudi Aramco Energy Ventures | F44: 9
A45: SRI-Saudi Refining Inc. | F45: 8
A46: Grand Total | F46: 979
A49: SSD Requisitions Opened | B49: 2022 | C49: 2023 | D49: 2024 | E49: 2025 | F49: 2026
A50: # of Expat Requisitions Open for Sourcing | B50: 500 | C50: 480 | D50: 600 | E50: 400
A51: # of Expat Hiring Targets
A52: Total # of Expat Requisitions | B52: =B50 -> 500 | C52: =C50 -> 480 | D52: =D50 -> 600 | E52: =E50 -> 400
A53: # of Domestic Requisitions - ASC Core + R&D | B53: 60 | C53: 70 | D53: 80 | E53: 90
A54: # of Domestic Requisitions – SMP PMT | B54: 40 | C54: 75 | D54: 100 | E54: 30
A55: # of Domestic Requisitions – AMVCC | B55: 0 | C55: 3 | D55: 5 | E55: 1
A56: # of Domestic Requisitions – SAEV | B56: 3 | C56: 3 | D56: 6 | E56: 2
A57: # of Domestic Requisitions – SPII | B57: 0 | C57: 9 | D57: 0 | E57: 0
A58: # of Domestic Requisitions – SRI | B58: 0 | C58: 1 | D58: 0 | E58: 0
A59: # of Domestic Requisitions – ASBCO | B59: 1 | C59: 0 | D59: 1 | E59: 0
A60: # of Domestic Requisitions – ATA | B60: 0 | C60: 0 | D60: 50 | E60: 40
A61: Total # of Requisitions | B61: =SUM(B53:B60) -> 104 | C61: =SUM(C53:C60) -> 161 | D61: =SUM(D53:D60) -> 242 | E61: =SUM(E53:E60) -> 163 | F61: =SUM(F53:F60) -> 0
A63: Ch8 Support Salaries + OT + Temp | B63: 2022 | C63: 2023 | D63: 2024 | E63: 2025 | F63: 2026
A64: 21804440 (Ch8 Support) | B64: 150000 | C64: 200000 | D64: 210000 | E64: 270000
A65: 21804440 (Medical Referral) | B65: 110000 | C65: 115000 | D65: 117000 | E65: 118000
A66: 21804440 (Call Center Support) | B66: 110000 | C66: 120000 | D66: 125000 | E66: 100000
A67: Total | B67: =SUM(B64:B66) -> 370000 | C67: =SUM(C64:C66) -> 435000 | D67: =SUM(D64:D66) -> 452000 | E67: =SUM(E64:E66) -> 488000
A69: CIG Group/Category | B69: # of 2022 | C69: # of 2023 | D69: # of 2024 | E69: # of 2025 | F69: # of 2026
A70: Expat Hiring | B70: 300 | C70: 400 | D70: 250 | E70: 100
A71: Domestic Hiring | B71: 150 | C71: 150 | D71: 170 | E71: 100
A72: SAO – Corporate Security | B72: 1000 | C72: 900 | D72: 500 | E72: 300
A73: Special Investigative Requests | B73: 150 | C73: 50 | D73: 10 | E73: 20
A74: Total | B74: =SUM(B70:B73) -> 1600 | C74: =SUM(C70:C73) -> 1500 | D74: =SUM(D70:D73) -> 930 | E74: 408
A76: ATPD Software Usage | B76: 2022 | C76: 2023 | D76: 2024 | E76: 2025 | F76: 2026
A77: 300000
A78: Academic Programs - The Key 50% | B78: =A77*0.5 -> 150000 | C78: =A77*0.5 -> 150000 | D78: =A77*0.5 -> 150000 | E78: =A77*0.5 -> 150000
A79: TPU - The Key 25% | B79: =A77*0.25 -> 75000 | C79: =A77*0.25 -> 75000 | D79: =A77*0.25 -> 75000 | E79: =A77*0.25 -> 75000
A80: Support Group - CH8 Thamaniya 25% | B80: =A77*0.25 -> 75000 | C80: =A77*0.25 -> 75000 | D80: =A77*0.25 -> 75000 | E80: =A77*0.25 -> 75000

Sheet BUDGET-22-25 SSD
A1: GL Description | B1: 2022 Recruiting Actual | C1: 2023 Recruiting Actual | D1: 2024 Recruiting Actual | E1: 2025 Recruiting Plan | F1: 2025 Recruiting Actual | G1: Column1 | H1: 2022 Sourcing Actual | I1: 2023 Sourcing Actual | J1: 2024 Sourcing Actual | K1: 2025 Sourcing Plan | L1: 2025 Sourcing Actual | M1: Column2 | N1: 2022 Recruiting-Corporate Services Actual | O1: 2023 Recruiting-Corporate Services Actual | P1: 2024 Recruiting-Corporate Services Actual | Q1: 2025 Recruiting-Corporate Services Plan | R1: 2025 Recruiting-Corporate Services Actual | S1: 3 | T1: 2022 Relocation Actual | U1: 2023 Relocation Actual | V1: 2024 Relocation Actual | W1: 2025 Relocation Plan | X1: 2025 Relocation Actual | Y1: Column4 | Z1: 2022 Admin Actual | AA1: 2023 Admin Actual | AB1: 2024 Admin Actual | AC1: 2025 Admin Plan | AD1: 2025 Admin Actual | AE1: Column3 | AF1: 2022 Domestic Recruiting Actual | AG1: 2023 Domestic Recruiting Actual | AH1: 2024 Domestic Recruiting Actual | AI1: 2025 Domestic Recruiting Plan | AJ1: 2025 Domestic Recruiting Actual
A2: Labor - US Company Regular | B2: 760000 | C2: 570000 | D2: 285000 | F2: 285000 | H2: 380000 | I2: 380000 | J2: 190000 | L2: 285000 | N2: 0 | O2: 190000 | P2: 285000 | R2: 190000 | S2: 0 | T2: 475000 | U2: 475000 | V2: 380000 | X2: 380000 | Z2: 0 | AA2: 0 | AB2: 95000 | AD2: 0 | AF2: 190000 | AG2: 285000 | AH2: 475000 | AJ2: 475000
A3: Labor - Regular Accrual | B3: 15200 | C3: 11400 | D3: 5700 | F3: 5700 | H3: 7600 | I3: 7600 | J3: 3800 | L3: 5700 | N3: 0 | O3: 3800 | P3: 5700 | R3: 3800 | S3: 0 | T3: 9500 | U3: 9500 | V3: 7600 | X3: 7600 | Z3: 0 | AA3: 0 | AB3: 1900 | AD3: 0 | AF3: 3800 | AG3: 5700 | AH3: 9500 | AJ3: 9500
A4: Labor - Incentive Plan | B4: 0 | C4: 0 | D4: 0 | F4: 0 | H4: 0 | I4: 0 | J4: 0 | L4: 0 | N4: 0 | O4: 0 | P4: 0 | R4: 0 | T4: 0 | U4: 0 | V4: 0 | X4: 0 | Z4: 0 | AA4: 0 | AB4: 0 | AD4: 0 | AF4: 0 | AG4: 0 | AH4: 0 | AJ4: 0
A5: Labor - Special Employees | B5: 120000 | C5: 180000 | D5: 240000 | E5: 0 | F5: 120000 | H5: 60000 | I5: 60000 | J5: 60000 | K5: 0 | L5: 60000 | N5: 0 | O5: 0 | P5: 120000 | Q5: 0 | R5: 60000 | S5: 0 | T5: 120000 | U5: 120000 | V5: 60000 | W5: 0 | X5: 180000 | Z5: 60000 | AA5: 60000 | AB5: 60000 | AC5: 0 | AD5: 60000 | AF5: 120000 | AG5: 180000 | AH5: 120000 | AI5: 0 | AJ5: 60000
A6: Loaned Employees Cost | B6: 0 | C6: 0 | D6: 0 | F6: 0 | H6: 0 | I6: 0 | J6: 0 | L6: 0 | N6: 0 | O6: 0 | P6: 0 | R6: 0 | S6: 0 | T6: 0 | U6: 0 | V6: 0 | X6: 0 | Z6: 0 | AA6: 0 | AB6: 0 | AD6: 0 | AF6: 0 | AG6: 0 | AH6: 0 | AJ6: 0
A7: Salary overtime expenses | B7: 4800 | C7: 3600 | D7: 1800 | E7: 0 | F7: 1800 | H7: 2400 | I7: 2400 | J7: 1200 | K7: 0 | L7: 1800 | N7: 0 | O7: 1200 | P7: 1800 | Q7: 0 | R7: 1200 | S7: 0 | T7: 3000 | U7: 3000 | V7: 2400 | W7: 0 | X7: 2400 | Z7: 0 | AA7: 0 | AB7: 600 | AC7: 0 | AD7: 0 | AF7: 1200 | AG7: 1800 | AH7: 3000 | AI7: 0 | AJ7: 3000
A8: Total Labor | B8: =SUM(B2:B7) -> 900000 | C8: =SUM(C2:C7) -> 765000 | D8: =SUM(D2:D7) -> 532500 | F8: =SUM(F2:F7) -> 412500 | H8: =SUM(H2:H7) -> 450000 | I8: =SUM(I2:I7) -> 450000 | J8: =SUM(J2:J7) -> 255000 | L8: =SUM(L2:L7) -> 352500 | N8: =SUM(N2:N7) -> 0 | O8: =SUM(O2:O7) -> 195000 | P8: =SUM(P2:P7) -> 412500 | R8: =SUM(R2:R7) -> 255000 | S8: =SUM(S2:S7) -> 0 | T8: =SUM(T2:T7) -> 607500 | U8: =SUM(U2:U7) -> 607500 | V8: =SUM(V2:V7) -> 450000 | X8: =SUM(X2:X7) -> 570000 | Z8: =SUM(Z2:Z7) -> 60000 | AA8: =SUM(AA2:AA7) -> 60000 | AB8: =SUM(AB2:AB7) -> 157500 | AD8: =SUM(AD2:AD7) -> 60000 | AF8: =SUM(AF2:AF7) -> 315000 | AG8: =SUM(AG2:AG7) -> 472500 | AH8: =SUM(AH2:AH7) -> 607500 | AJ8: =SUM(AJ2:AJ7) -> 547500
A9: Total Materials | B9: 1000 | C9: 700 | D9: 800 | F9: 1200 | H9: 900 | I9: 900 | J9: 600 | L9: 500 | N9: 0 | O9: 250 | P9: 500 | R9: 600 | T9: 300 | U9: 200 | V9: 300 | X9: 500 | Z9: 5000 | AA9: 4000 | AB9: 3000 | AD9: 2500 | AF9: 200 | AG9: 150 | AH9: 250 | AJ9: 300
A10: Consultants Compensation | B10: 0 | C10: 0 | D10: 0 | F10: 0 | H10: 0 | I10: 0 | J10: 0 | L10: 0 | N10: 0 | O10: 0 | P10: 0 | R10: 0 | S10: 0 | T10: 0 | U10: 0 | V10: 0 | X10: 0 | Z10: 0 | AA10: 0 | AB10: 0 | AD10: 0 | AF10: 0 | AG10: 0 | AH10: 0 | AJ10: 0
A11: Temporary Labor | B11: 80000 | C11: 80000 | D11: 320000 | F11: 240000 | H11: 80000 | I11: 160000 | J11: 240000 | L11: 160000 | O11: 240000 | P11: 240000 | R11: 160000 | S11: 0 | T11: 80000 | U11: 240000 | V11: 160000 | X11: 240000 | Z11: 80000 | AA11: 0 | AB11: 0 | AD11: 0 | AF11: 80000 | AG11: 160000 | AH11: 80000 | AJ11: 160000
A12: Invoiced Labor | B12: =SUM(B10:B11) -> 80000 | C12: =SUM(C10:C11) -> 80000 | D12: =SUM(D10:D11) -> 320000 | F12: =SUM(F10:F11) -> 240000 | H12: =SUM(H10:H11) -> 80000 | I12: =SUM(I10:I11) -> 160000 | J12: =SUM(J10:J11) -> 240000 | L12: =SUM(L10:L11) -> 160000 | N12: =SUM(N10:N11) -> 0 | O12: =SUM(O10:O11) -> 240000 | P12: =SUM(P10:P11) -> 240000 | R12: =SUM(R10:R11) -> 160000 | S12: =SUM(S10:S11) -> 0 | T12: =SUM(T10:T11) -> 80000 | U12: =SUM(U10:U11) -> 240000 | V12: =SUM(V10:V11) -> 160000 | X12: =SUM(X10:X11) -> 240000 | Z12: =SUM(Z10:Z11) -> 80000 | AA12: =SUM(AA10:AA11) -> 0 | AB12: =SUM(AB10:AB11) -> 0 | AD12: =SUM(AD10:AD11) -> 0 | AF12: =SUM(AF10:AF11) -> 80000 | AG12: =SUM(AG10:AG11) -> 160000 | AH12: =SUM(AH10:AH11) -> 80000 | AJ12: =SUM(AJ10:AJ11) -> 160000
A13: Corporate Obligations | B13: 2000 | C13: 1500 | D13: 750 | F13: 750 | H13: 1000 | I13: 1000 | J13: 500 | L13: 750 | N13: 0 | O13: 500 | P13: 750 | R13: 500 | S13: 0 | T13: 1250 | U13: 1250 | V13: 1000 | X13: 1000 | Z13: 0 | AA13: 0 | AB13: 250 | AD13: 0 | AF13: 500 | AG13: 750 | AH13: 1250 | AJ13: 1250
A14: Recruiting | B14: 800000 | C14: 1200000 | D14: 900000 | F14: 600000 | H14: 1500000 | I14: 1100000 | J14: 1000000 | L14: 1300000 | N14: 0 | O14: 30000 | P14: 30000 | R14: 30000 | T14: 50000 | U14: 60000 | V14: 70000 | X14: 10000 | Z14: 1500 | AA14: 3000 | AB14: 1000 | AD14: 500 | AF14: 50000 | AG14: 70000 | AH14: 40000 | AJ14: 50000
A15: Public Affairs Activities | B15: 10000 | C15: 0 | D15: 0 | F15: 0 | H15: 10000 | I15: 0 | J15: 0 | L15: 0 | N15: 0 | O15: 0 | P15: 0 | R15: 0 | T15: 0 | U15: 0 | V15: 0 | X15: 0 | Z15: 0 | AA15: 0 | AB15: 0 | AD15: 0 | AF15: 0 | AG15: 0 | AH15: 0 | AJ15: 0
A16: Environmental Services | B16: 0 | C16: 0 | D16: 0 | F16: 0 | H16: 0 | I16: 0 | J16: 0 | L16: 0 | N16: 0 | O16: 0 | P16: 0 | R16: 0 | T16: 0 | U16: 0 | V16: 0 | X16: 0 | Z16: 0 | AA16: 0 | AB16: 0 | AD16: 0 | AF16: 0 | AG16: 0 | AH16: 0 | AJ16: 0
A17: Computer & Communications | B17: 10000 | C17: 8000 | D17: 7000 | F17: 6000 | H17: 5000 | I17: 6000 | J17: 5000 | L17: 5000 | N17: 0 | O17: 5000 | P17: 6000 | R17: 4000 | S17: 0 | T17: 6000 | U17: 8000 | V17: 6000 | X17: 7000 | Z17: 1000 | AA17: 0 | AB17: 2000 | AD17: 0 | AF17: 3000 | AG17: 5000 | AH17: 6000 | AJ17: 7000
A18: Facility Operations & Maintenance | B18: 120 | C18: 480 | D18: 600 | F18: 720 | H18: 120 | I18: 480 | J18: 600 | L18: 720 | N18: 0 | O18: 480 | P18: 600 | R18: 720 | T18: 120 | U18: 480 | V18: 600 | X18: 720 | Z18: 0 | AA18: 0 | AB18: 0 | AD18: 0 | AF18: 120 | AG18: 480 | AH18: 600 | AJ18: 720
A19: Leases | B19: 0 | C19: 0 | D19: 0 | F19: 0 | H19: 0 | I19: 0 | J19: 0 | L19: 0 | N19: 0 | O19: 0 | P19: 0 | R19: 0 | T19: 0 | U19: 0 | V19: 0 | X19: 0 | Z19: 0 | AA19: 0 | AB19: 0 | AD19: 0 | AF19: 0 | AG19: 0 | AH19: 0 | AJ19: 0
A20: Business Support | B20: 150000 | C20: 140000 | D20: 130000 | F20: 120000 | H20: 20000 | I20: 30000 | J20: 40000 | L20: 50000 | N20: 0 | O20: 25000 | P20: 40000 | R20: 50000 | T20: 10000 | U20: 9000 | V20: 8000 | X20: 7000 | Z20: 50000 | AA20: 50000 | AB20: 50000 | AC20: 50000 | AD20: 50000 | AF20: 7000 | AG20: 8000 | AH20: 9000 | AJ20: 10000
A21: Employee Support | B21: 6500 | C21: 5200 | D21: 4550 | E21: 0 | F21: 3900 | H21: 3250 | I21: 3900 | J21: 3250 | K21: 0 | L21: 3250 | N21: 0 | O21: 3250 | P21: 3900 | Q21: 0 | R21: 2600 | S21: 0 | T21: 3900 | U21: 5200 | V21: 3900 | W21: 0 | X21: 4550 | Z21: 650 | AA21: 0 | AB21: 1300 | AC21: 0 | AD21: 0 | AF21: 1950 | AG21: 3250 | AH21: 3900 | AI21: 0 | AJ21: 4550
A22: Total Invoices | B22: =SUM(B10:B11,B13:B21) -> 1058620 | C22: =SUM(C10:C11,C13:C21) -> 1435180 | D22: =SUM(D10:D11,D13:D21) -> 1362900 | F22: =SUM(F10:F11,F13:F21) -> 971370 | H22: =SUM(H10:H11,H13:H21) -> 1619370 | I22: =SUM(I10:I11,I13:I21) -> 1301380 | J22: =SUM(J10:J11,J13:J21) -> 1289350 | L22: =SUM(L10:L11,L13:L21) -> 1519720 | N22: =SUM(N10:N11,N13:N21) -> 0 | O22: =SUM(O10:O11,O13:O21) -> 304230 | P22: =SUM(P10:P11,P13:P21) -> 321250 | R22: =SUM(R10:R11,R13:R21) -> 247820 | S22: =SUM(S10:S11,S13:S21) -> 0 | T22: =SUM(T10:T11,T13:T21) -> 151270 | U22: =SUM(U10:U11,U13:U21) -> 323930 | V22: =SUM(V10:V11,V13:V21) -> 249500 | X22: =SUM(X10:X11,X13:X21) -> 270270 | Z22: =SUM(Z10:Z11,Z13:Z21) -> 133150 | AA22: =SUM(AA10:AA11,AA13:AA21) -> 53000 | AB22: =SUM(AB10:AB11,AB13:AB21) -> 54550 | AD22: =SUM(AD10:AD11,AD13:AD21) -> 50500 | AF22: =SUM(AF10:AF11,AF13:AF21) -> 142570 | AG22: =SUM(AG10:AG11,AG13:AG21) -> 247480 | AH22: =SUM(AH10:AH11,AH13:AH21) -> 140750 | AJ22: =SUM(AJ10:AJ11,AJ13:AJ21) -> 233520
A23: Total Net Direct Expenses | B23: =SUM(B22,B8:B9) -> 1959620 | C23: =SUM(C22,C8:C9) -> 2200880 | D23: =SUM(D22,D8:D9) -> 1896200 | F23: =SUM(F22,F8:F9) -> 1385070 | H23: =SUM(H22,H8:H9) -> 2070270 | I23: =SUM(I22,I8:I9) -> 1752280 | J23: =SUM(J22,J8:J9) -> 1544950 | L23: =SUM(L22,L8:L9) -> 1872720 | N23: =SUM(N22,N8:N9) -> 0 | O23: =SUM(O22,O8:O9) -> 499480 | P23: =SUM(P22,P8:P9) -> 734250 | R23: =SUM(R22,R8:R9) -> 503420 | S23: =SUM(S22,S8:S9) -> 0 | T23: =SUM(T22,T8:T9) -> 759070 | U23: =SUM(U22,U8:U9) -> 931630 | V23: =SUM(V22,V8:V9) -> 699800 | X23: =SUM(X22,X8:X9) -> 840770 | Z23: =SUM(Z22,Z8:Z9) -> 198150 | AA23: =SUM(AA22,AA8:AA9) -> 117000 | AB23: =SUM(AB22,AB8:AB9) -> 215050 | AD23: =SUM(AD22,AD8:AD9) -> 113000 | AF23: =SUM(AF22,AF8:AF9) -> 457770 | AG23: =SUM(AG22,AG8:AG9) -> 720130 | AH23: =SUM(AH22,AH8:AH9) -> 748500 | AJ23: =SUM(AJ22,AJ8:AJ9) -> 781320
A24: Total Allocations | B24: =SUM(B25:B36) -> 0 | C24: =SUM(C25:C36) -> 0 | D24: =SUM(D25:D36) -> 0 | F24: =SUM(F25:F36) -> 0 | H24: =SUM(H25:H36) -> 0 | I24: =SUM(I25:I36) -> 0 | J24: =SUM(J25:J36) -> 0 | L24: =SUM(L25:L36) -> 0 | N24: =SUM(N25:N36) -> 0 | O24: =SUM(O25:O36) -> 0 | P24: =SUM(P25:P36) -> 0 | R24: =SUM(R25:R36) -> 0 | S24: =SUM(S25:S36) -> 0 | T24: =SUM(T25:T36) -> 0 | U24: =SUM(U25:U36) -> 0 | V24: =SUM(V25:V36) -> 0 | X24: =SUM(X25:X36) -> 0 | Z24: =SUM(Z25:Z36) -> 0 | AA24: =SUM(AA25:AA36) -> 0 | AB24: =SUM(AB25:AB36) -> 0 | AD24: =SUM(AD25:AD36) -> 0 | AF24: =SUM(AF25:AF36) -> 0 | AG24: =SUM(AG25:AG36) -> 0 | AH24: =SUM(AH25:AH36) -> 0 | AJ24: =SUM(AJ25:AJ36) -> 0
A25: ASC/ATA Reallocation | B25: 0 | C25: 0 | D25: 0 | E25: 0 | F25: 0 | H25: 0 | I25: 0 | J25: 0 | K25: 0 | L25: 0 | N25: 0 | O25: 0 | P25: 0 | Q25: 0 | R25: 0 | S25: 0 | T25: 0 | U25: 0 | V25: 0 | W25: 0 | X25: 0 | Z25: 0 | AA25: 0 | AB25: 0 | AC25: 0 | AD25: 0 | AF25: 0 | AG25: 0 | AH25: 0 | AI25: 0 | AJ25: 0
A26: ATA Monthly Billing | B26: 0 | C26: 0 | D26: 0 | E26: 0 | F26: 0 | H26: 0 | I26: 0 | J26: 0 | K26: 0 | L26: 0 | N26: 0 | O26: 0 | P26: 0 | Q26: 0 | R26: 0 | S26: 0 | T26: 0 | U26: 0 | V26: 0 | W26: 0 | X26: 0 | Z26: 0 | AA26: 0 | AB26: 0 | AC26: 0 | AD26: 0 | AF26: 0 | AG26: 0 | AH26: 0 | AI26: 0 | AJ26: 0
A27: Accrued Vacation | B27: 0 | C27: 0 | D27: 0 | E27: 0 | F27: 0 | H27: 0 | I27: 0 | J27: 0 | K27: 0 | L27: 0 | N27: 0 | O27: 0 | P27: 0 | Q27: 0 | R27: 0 | S27: 0 | T27: 0 | U27: 0 | V27: 0 | W27: 0 | X27: 0 | Z27: 0 | AA27: 0 | AB27: 0 | AC27: 0 | AD27: 0 | AF27: 0 | AG27: 0 | AH27: 0 | AI27: 0 | AJ27: 0
A28: Depreciation - Ordinary | B28: 0 | C28: 0 | D28: 0 | E28: 0 | F28: 0 | H28: 0 | I28: 0 | J28: 0 | K28: 0 | L28: 0 | N28: 0 | O28: 0 | P28: 0 | Q28: 0 | R28: 0 | S28: 0 | T28: 0 | U28: 0 | V28: 0 | W28: 0 | X28: 0 | Z28: 0 | AA28: 0 | AB28: 0 | AC28: 0 | AD28: 0 | AF28: 0 | AG28: 0 | AH28: 0 | AI28: 0 | AJ28: 0
A29: LD Telephone Distr | B29: 0 | C29: 0 | D29: 0 | E29: 0 | F29: 0 | H29: 0 | I29: 0 | J29: 0 | K29: 0 | L29: 0 | N29: 0 | O29: 0 | P29: 0 | Q29: 0 | R29: 0 | S29: 0 | T29: 0 | U29: 0 | V29: 0 | W29: 0 | X29: 0 | Z29: 0 | AA29: 0 | AB29: 0 | AC29: 0 | AD29: 0 | AF29: 0 | AG29: 0 | AH29: 0 | AI29: 0 | AJ29: 0
A30: Miscellaneous Allocations | B30: 0 | C30: 0 | D30: 0 | E30: 0 | F30: 0 | H30: 0 | I30: 0 | J30: 0 | K30: 0 | L30: 0 | N30: 0 | O30: 0 | P30: 0 | Q30: 0 | R30: 0 | S30: 0 | T30: 0 | U30: 0 | V30: 0 | W30: 0 | X30: 0 | Z30: 0 | AA30: 0 | AB30: 0 | AC30: 0 | AD30: 0 | AF30: 0 | AG30: 0 | AH30: 0 | AI30: 0 | AJ30: 0
A31: ASC/SRI Reallocations | B31: 0 | C31: 0 | D31: 0 | E31: 0 | F31: 0 | H31: 0 | I31: 0 | J31: 0 | K31: 0 | L31: 0 | N31: 0 | O31: 0 | P31: 0 | Q31: 0 | R31: 0 | S31: 0 | T31: 0 | U31: 0 | V31: 0 | W31: 0 | X31: 0 | Z31: 0 | AA31: 0 | AB31: 0 | AC31: 0 | AD31: 0 | AF31: 0 | AG31: 0 | AH31: 0 | AI31: 0 | AJ31: 0
A32: ASC/R&D Allocations | B32: 0 | C32: 0 | D32: 0 | E32: 0 | F32: 0 | H32: 0 | I32: 0 | J32: 0 | K32: 0 | L32: 0 | N32: 0 | O32: 0 | P32: 0 | Q32: 0 | R32: 0 | S32: 0 | T32: 0 | U32: 0 | V32: 0 | W32: 0 | X32: 0 | Z32: 0 | AA32: 0 | AB32: 0 | AC32: 0 | AD32: 0 | AF32: 0 | AG32: 0 | AH32: 0 | AI32: 0 | AJ32: 0
A33: ASC/AAC Reallocations | B33: 0 | C33: 0 | D33: 0 | E33: 0 | F33: 0 | H33: 0 | I33: 0 | J33: 0 | K33: 0 | L33: 0 | N33: 0 | O33: 0 | P33: 0 | Q33: 0 | R33: 0 | S33: 0 | T33: 0 | U33: 0 | V33: 0 | W33: 0 | X33: 0 | Z33: 0 | AA33: 0 | AB33: 0 | AC33: 0 | AD33: 0 | AF33: 0 | AG33: 0 | AH33: 0 | AI33: 0 | AJ33: 0
A34: ASC/SAEV Reallocations | B34: 0 | C34: 0 | D34: 0 | E34: 0 | F34: 0 | H34: 0 | I34: 0 | J34: 0 | K34: 0 | L34: 0 | N34: 0 | O34: 0 | P34: 0 | Q34: 0 | R34: 0 | S34: 0 | T34: 0 | U34: 0 | V34: 0 | W34: 0 | X34: 0 | Z34: 0 | AA34: 0 | AB34: 0 | AC34: 0 | AD34: 0 | AF34: 0 | AG34: 0 | AH34: 0 | AI34: 0 | AJ34: 0
A35: ASC/ASBCO Reallocation | B35: 0 | C35: 0 | D35: 0 | E35: 0 | F35: 0 | H35: 0 | I35: 0 | J35: 0 | K35: 0 | L35: 0 | N35: 0 | O35: 0 | P35: 0 | Q35: 0 | R35: 0 | S35: 0 | T35: 0 | U35: 0 | V35: 0 | W35: 0 | X35: 0 | Z35: 0 | AA35: 0 | AB35: 0 | AC35: 0 | AD35: 0 | AF35: 0 | AG35: 0 | AH35: 0 | AI35: 0 | AJ35: 0
A36: ASC/AVMCC Reallocation | B36: 0 | C36: 0 | D36: 0 | E36: 0 | F36: 0 | H36: 0 | I36: 0 | J36: 0 | K36: 0 | L36: 0 | N36: 0 | O36: 0 | P36: 0 | Q36: 0 | R36: 0 | S36: 0 | T36: 0 | U36: 0 | V36: 0 | W36: 0 | X36: 0 | Z36: 0 | AA36: 0 | AB36: 0 | AC36: 0 | AD36: 0 | AF36: 0 | AG36: 0 | AH36: 0 | AI36: 0 | AJ36: 0
A37: Total Controllable Expenses | B37: =SUM(B23:B24) -> 1959620 | C37: =SUM(C23:C24) -> 2200880 | D37: =SUM(D23:D24) -> 1896200 | F37: =SUM(F23:F24) -> 1385070 | H37: =SUM(H23:H24) -> 2070270 | I37: =SUM(I23:I24) -> 1752280 | J37: =SUM(J23:J24) -> 1544950 | L37: =SUM(L23:L24) -> 1872720 | N37: =SUM(N23:N24) -> 0 | O37: =SUM(O23:O24) -> 499480 | P37: =SUM(P23:P24) -> 734250 | R37: =SUM(R23:R24) -> 503420 | S37: =SUM(S23:S24) -> 0 | T37: =SUM(T23:T24) -> 759070 | U37: =SUM(U23:U24) -> 931630 | V37: =SUM(V23:V24) -> 699800 | X37: =SUM(X23:X24) -> 840770 | Z37: =SUM(Z23:Z24) -> 198150 | AA37: =SUM(AA23:AA24) -> 117000 | AB37: =SUM(AB23:AB24) -> 215050 | AD37: =SUM(AD23:AD24) -> 113000 | AF37: =SUM(AF23:AF24) -> 457770 | AG37: =SUM(AG23:AG24) -> 720130 | AH37: =SUM(AH23:AH24) -> 748500 | AJ37: =SUM(AJ23:AJ24) -> 781320
A39: Total Headcount | B39: =SUM(B40:B42) -> 10 | C39: =SUM(C40:C42) -> 8 | D39: =SUM(D40:D42) -> 7 | F39: =SUM(F40:F42) -> 6 | H39: =SUM(H40:H42) -> 5 | I39: =SUM(I40:I42) -> 6 | J39: =SUM(J40:J42) -> 5 | L39: =SUM(L40:L42) -> 5 | N39: =SUM(N40:N42) -> 0 | O39: =SUM(O40:O42) -> 5 | P39: =SUM(P40:P42) -> 6 | R39: =SUM(R40:R42) -> 4 | S39: =SUM(S40:S42) -> 0 | T39: =SUM(T40:T42) -> 6 | U39: =SUM(U40:U42) -> 8 | V39: =SUM(V40:V42) -> 6 | X39: =SUM(X40:X42) -> 7 | Z39: =SUM(Z40:Z42) -> 1 | AA39: =SUM(AA40:AA42) -> 0 | AB39: =SUM(AB40:AB42) -> 2 | AD39: =SUM(AD40:AD42) -> 0 | AF39: =SUM(AF40:AF42) -> 3 | AG39: =SUM(AG40:AG42) -> 5 | AH39: =SUM(AH40:AH42) -> 6 | AJ39: =SUM(AJ40:AJ42) -> 7
A40: Regular+Excl. Regular | B40: 8 | C40: 6 | D40: 3 | F40: 3 | H40: 4 | I40: 4 | J40: 2 | L40: 3 | N40: 0 | O40: 2 | P40: 3 | R40: 2 | T40: 5 | U40: 5 | V40: 4 | X40: 4 | Z40: 0 | AA40: 0 | AB40: 1 | AD40: 0 | AF40: 2 | AG40: 3 | AH40: 5 | AJ40: 5
A41: Saudi Riyal Chapter 8 | B41: 1 | C41: 1 | D41: 0 | F41: 0 | H41: 0 | I41: 0 | J41: 0 | L41: 0 | N41: 0 | O41: 0 | P41: 0 | R41: 0 | T41: 0 | U41: 0 | V41: 0 | X41: 0 | Z41: 0 | AA41: 0 | AB41: 1 | AD41: 0 | AF41: 0 | AG41: 0 | AH41: 0 | AJ41: 0
A42: Supplemental | B42: 1 | C42: 1 | D42: 4 | F42: 3 | H42: 1 | I42: 2 | J42: 3 | L42: 2 | N42: 0 | O42: 3 | P42: 3 | R42: 2 | T42: 1 | U42: 3 | V42: 2 | X42: 3 | Z42: 1 | AA42: 0 | AB42: 0 | AD42: 0 | AF42: 1 | AG42: 2 | AH42: 1 | AJ42: 2
A43: Special Employee | B43: 2 | C43: 3 | D43: 4 | F43: 2 | H43: 1 | I43: 1 | J43: 1 | L43: 1 | N43: 0 | O43: 0 | P43: 2 | R43: 1 | T43: 2 | U43: 2 | V43: 1 | X43: 3 | Z43: 1 | AA43: 1 | AB43: 1 | AD43: 1 | AF43: 2 | AG43: 3 | AH43: 2 | AJ43: 1

Sheet BUDGET-22-25 HRS & CIG
A1: GL Description | B1: 2022 Human Resources Services Actual | C1: 2023 Human Resources Services Actual | D1: 2024 Human Resources Services Actual | E1: 2025 Human Resources Services Plan | F1: 2025 Human Resources Services Actual | G1: Column1 | H1: 2022 Training and Development Actual | I1: 2023 Training and Development Actual | J1: 2024 Training and Development Actual | K1: 2025 Training and Development Plan | L1: 2025 Training and Development Actual | M1: Column2 | N1: 2022 Compensation & Organization Actual | O1: 2023 Compensation & Organization Actual | P1: 2024 Compensation & Organization Actual | Q1: 2025 Compensation & Organization Plan | R1: 2025 Compensation & Organization Actual | S1: Column3 | T1: 2022 Personnel Administration Actual | U1: 2023 Personnel Administration Actual | V1: 2024 Personnel Administration Actual | W1: 2025 Personnel Administration Plan | X1: 2025 Personnel Administration Actual | Y1: Column4 | Z1: 2022 Human Resources Adm/Planning Actual | AA1: 2023 Human Resources Adm/Planning Actual | AB1: 2024 Human Resources Adm/Planning Actual | AC1: 2025 Human Resources Adm/Planning Plan | AD1: 2025 Human Resources Adm/Planning Actual | AE1: Column5 | AF1: 2022 Central Investigations Actual | AG1: 2023 Central Investigations Actual | AH1: 2024 Central Investigations Actual | AI1: 2025 Central Investigations Plan | AJ1: 2025 Central Investigations Actual
A2: Labor - US Company Regular | B2: 100000 | C2: 100000 | D2: 100000 | F2: 100000 | H2: 500000 | I2: 500000 | J2: 600000 | L2: 700000 | N2: 600000 | O2: 600000 | P2: 600000 | R2: 600000 | T2: 400000 | U2: 400000 | V2: 400000 | X2: 400000 | AB2: 300000 | AD2: 400000 | AF2: 400000 | AG2: 300000 | AH2: 400000 | AJ2: 300000
A3: Labor - Regular Accrual | B3: 2000 | C3: 2000 | D3: 2000 | E3: 0 | F3: 2000 | H3: 10000 | I3: 10000 | J3: 12000 | K3: 0 | L3: 14000 | N3: 12000 | O3: 12000 | P3: 12000 | Q3: 0 | R3: 12000 | T3: 8000 | U3: 8000 | V3: 8000 | W3: 0 | X3: 8000 | AB3: 6000 | AC3: 0 | AD3: 8000 | AF3: 8000 | AG3: 6000 | AH3: 8000 | AI3: 0 | AJ3: 6000
A4: Labor - Incentive Plan | B4: 8000000 | C4: 7000000 | D4: 9000000 | F4: 11000000 | H4: 0 | I4: 0 | J4: 0 | L4: 0 | N4: 0 | O4: 0 | P4: 0 | R4: 0 | T4: 0 | U4: 0 | V4: 0 | X4: 0 | AB4: 0 | AD4: 0 | AF4: 0 | AG4: 0 | AH4: 0 | AJ4: 0
A5: Labor - Special Employees | B5: 60000 | C5: 120000 | D5: 180000 | E5: 0 | F5: 120000 | H5: 120000 | I5: 120000 | J5: 60000 | K5: 0 | L5: 60000 | N5: 120000 | O5: 60000 | P5: 60000 | Q5: 0 | R5: 60000 | T5: 60000 | U5: 60000 | V5: 60000 | W5: 0 | X5: 60000 | AB5: 0 | AC5: 0 | AD5: 60000 | AF5: 0 | AG5: 0 | AH5: 0 | AI5: 0 | AJ5: 0
A6: Loaned Employees Cost | B6: 0 | C6: 0 | D6: 0 | F6: 0 | H6: 0 | I6: 0 | J6: 0 | L6: 0 | N6: 0 | O6: 0 | P6: 0 | R6: 0 | T6: 0 | U6: 0 | V6: 0 | X6: 0 | AB6: 0 | AD6: 0 | AF6: 0 | AG6: 0 | AH6: 0 | AJ6: 0
A7: Salary overtime expenses | B7: 500 | C7: 500 | D7: 500 | E7: 0 | F7: 500 | H7: 2500 | I7: 2500 | J7: 3000 | K7: 0 | L7: 3500 | N7: 3000 | O7: 3000 | P7: 3000 | Q7: 0 | R7: 3000 | T7: 2000 | U7: 2000 | V7: 2000 | W7: 0 | X7: 2000 | AB7: 1500 | AC7: 0 | AD7: 2000 | AF7: 2000 | AG7: 1500 | AH7: 2000 | AI7: 0 | AJ7: 1500
A8: Total Labor | B8: =SUM(B2:B7) -> 8162500 | C8: =SUM(C2:C7) -> 7222500 | D8: =SUM(D2:D7) -> 9282500 | E8: =SUM(E2:E7) -> 0 | F8: =SUM(F2:F7) -> 11222500 | H8: =SUM(H2:H7) -> 632500 | I8: =SUM(I2:I7) -> 632500 | J8: =SUM(J2:J7) -> 675000 | K8: =SUM(K2:K7) -> 0 | L8: =SUM(L2:L7) -> 777500 | N8: =SUM(N2:N7) -> 735000 | O8: =SUM(O2:O7) -> 675000 | P8: =SUM(P2:P7) -> 675000 | Q8: =SUM(Q2:Q7) -> 0 | R8: =SUM(R2:R7) -> 675000 | T8: =SUM(T2:T7) -> 470000 | U8: =SUM(U2:U7) -> 470000 | V8: =SUM(V2:V7) -> 470000 | W8: =SUM(W2:W7) -> 0 | X8: =SUM(X2:X7) -> 470000 | AB8: =SUM(AB2:AB7) -> 307500 | AC8: =SUM(AC2:AC7) -> 0 | AD8: =SUM(AD2:AD7) -> 470000 | AF8: =SUM(AF2:AF7) -> 410000 | AG8: =SUM(AG2:AG7) -> 307500 | AH8: =SUM(AH2:AH7) -> 410000 | AI8: =SUM(AI2:AI7) -> 0 | AJ8: =SUM(AJ2:AJ7) -> 307500
A9: Total Materials | B9: 3900 | C9: 4000 | D9: 7000 | F9: 3000 | H9: 1500 | I9: 1000 | J9: 250 | L9: 100 | N9: 25 | O9: 0 | P9: 0 | R9: 0 | T9: 0 | U9: 500 | V9: 200 | X9: 0 | AB9: 12000 | AD9: 7000 | AF9: 500 | AG9: 5000 | AH9: 1500 | AJ9: 2500
A10: Consultants Compensation | B10: 400000 | C10: 300000 | D10: 200000 | E10: 0 | F10: 250000 | H10: 0 | I10: 0 | J10: 0 | K10: 0 | L10: 0 | N10: 300 | O10: 400 | P10: 500 | Q10: 0 | R10: 200 | T10: 300 | U10: 400 | V10: 500 | W10: 0 | X10: 200 | AB10: 500 | AC10: 0 | AD10: 200
A11: Temporary Labor | B11: 0 | C11: 0 | D11: 0 | F11: 0 | H11: 0 | I11: 85000 | J11: 85000 | L11: 0 | N11: 0 | O11: 0 | P11: 85000 | R11: 0 | T11: 0 | U11: 0 | V11: 0 | X11: 0 | AB11: 0 | AD11: 0 | AF11: 0 | AG11: 85000 | AH11: 0 | AJ11: 0
A12: Invoiced Labor | B12: =SUM(B10:B11) -> 400000 | C12: =SUM(C10:C11) -> 300000 | D12: =SUM(D10:D11) -> 200000 | E12: =SUM(E10:E11) -> 0 | F12: =SUM(F10:F11) -> 250000 | H12: =SUM(H10:H11) -> 0 | I12: =SUM(I10:I11) -> 85000 | J12: =SUM(J10:J11) -> 85000 | K12: =SUM(K10:K11) -> 0 | L12: =SUM(L10:L11) -> 0 | N12: =SUM(N10:N11) -> 300 | O12: =SUM(O10:O11) -> 400 | P12: =SUM(P10:P11) -> 85500 | Q12: =SUM(Q10:Q11) -> 0 | R12: =SUM(R10:R11) -> 200 | T12: =SUM(T10:T11) -> 300 | U12: =SUM(U10:U11) -> 400 | V12: =SUM(V10:V11) -> 500 | W12: =SUM(W10:W11) -> 0 | X12: =SUM(X10:X11) -> 200 | AB12: =SUM(AB10:AB11) -> 500 | AC12: =SUM(AC10:AC11) -> 0 | AD12: =SUM(AD10:AD11) -> 200 | AF12: =SUM(AF10:AF11) -> 0 | AG12: =SUM(AG10:AG11) -> 85000 | AH12: =SUM(AH10:AH11) -> 0 | AI12: =SUM(AI10:AI11) -> 0 | AJ12: =SUM(AJ10:AJ11) -> 0
A13: Corporate Obligations | B13: 40000000 | C13: 30000000 | D13: 20000000 | F13: 25000000 | H13: 500 | I13: 600 | J13: 700 | K13: 0 | L13: 700 | N13: 600 | O13: 600 | P13: 700 | Q13: 0 | R13: 600 | T13: 400 | U13: 400 | V13: 400 | W13: 0 | X13: 400 | Z13: 0 | AA13: 0 | AB13: 500 | AC13: 0 | AD13: 600 | AF13: 400 | AG13: 400 | AH13: 500 | AI13: 0 | AJ13: 400
A14: Recruiting | B14: 0 | C14: 0 | D14: 0 | E14: 0 | F14: 0 | H14: 0 | I14: 0 | J14: 0 | K14: 0 | L14: 0 | N14: 0 | O14: 0 | P14: 0 | Q14: 0 | R14: 0 | T14: 0 | U14: 0 | V14: 0 | W14: 0 | X14: 0 | AB14: 0 | AC14: 0 | AD14: 0 | AF14: 2000000 | AG14: 1900000 | AH14: 1800000 | AJ14: 1700000
A15: Public Affairs Activities | B15: 0 | C15: 0 | D15: 0 | F15: 0 | H15: 0 | I15: 0 | J15: 0 | L15: 0 | N15: 0 | O15: 0 | P15: 0 | R15: 0 | T15: 0 | U15: 0 | V15: 0 | X15: 0 | AB15: 40000 | AD15: 60000 | AF15: 0 | AG15: 0 | AH15: 0 | AJ15: 0
A16: Environmental Services | B16: 0 | C16: 0 | D16: 0 | F16: 0 | H16: 0 | I16: 0 | J16: 0 | L16: 0 | N16: 0 | O16: 0 | P16: 0 | R16: 0 | T16: 0 | U16: 0 | V16: 0 | X16: 0 | AB16: 0 | AD16: 0 | AF16: 0 | AG16: 0 | AH16: 0 | AJ16: 0
A17: Computer & Communications | B17: 1000 | C17: 1000 | D17: 1000 | E17: 0 | F17: 1000 | H17: 5000 | I17: 6000 | J17: 7000 | K17: 0 | L17: 7000 | N17: 6000 | O17: 6000 | P17: 7000 | Q17: 0 | R17: 6000 | T17: 4000 | U17: 4000 | V17: 4000 | W17: 0 | X17: 4000 | AB17: 5000 | AC17: 0 | AD17: 6000 | AF17: 4000 | AG17: 4000 | AH17: 5000 | AI17: 0 | AJ17: 4000
A18: Facility Operations & Maintenance | B18: 0 | C18: 0 | D18: 0 | F18: 0 | H18: 0 | I18: 0 | J18: 75 | L18: 0 | N18: 0 | O18: 0 | P18: 0 | R18: 0 | T18: 0 | U18: 0 | V18: 0 | X18: 0 | AB18: 0 | AD18: 0 | AF18: 0 | AG18: 0 | AH18: 0 | AJ18: 0
A19: Leases | B19: 0 | C19: 0 | D19: 0 | F19: 0 | H19: 0 | I19: 0 | J19: 0 | L19: 0 | N19: 0 | O19: 0 | P19: 0 | R19: 0 | T19: 0 | U19: 0 | V19: 0 | X19: 0 | AB19: 0 | AD19: 0 | AF19: 0 | AG19: 0 | AH19: 0 | AJ19: 0
A20: Business Support | B20: 100000 | C20: 90000 | D20: 110000 | F20: 60000 | H20: 10000 | I20: 12000 | J20: 14000 | K20: 0 | L20: 14000 | N20: 12000 | O20: 12000 | P20: 14000 | Q20: 0 | R20: 12000 | T20: 8000 | U20: 8000 | V20: 8000 | W20: 0 | X20: 8000 | AB20: 10000 | AC20: 0 | AD20: 12000 | AF20: 0 | AG20: 0 | AH20: 0 | AJ20: 0
A21: Employee Support | B21: 80000 | C21: -40000 | D21: 30000 | F21: -15000 | H21: 300000 | I21: 400000 | J21: 500000 | K21: 300000 | L21: 200000 | N21: 4500 | O21: 4500 | P21: 5250 | Q21: 0 | R21: 4500 | T21: 3000 | U21: 3000 | V21: 3000 | W21: 0 | X21: 3000 | AB21: 3750 | AC21: 0 | AD21: 4500 | AF21: 0 | AG21: 0 | AH21: 0 | AJ21: 0
A22: Total Invoices | B22: =SUM(B10:B11,B13:B21) -> 40581000 | C22: =SUM(C10:C11,C13:C21) -> 30351000 | D22: =SUM(D10:D11,D13:D21) -> 20341000 | E22: =SUM(E10:E11,E13:E21) -> 0 | F22: =SUM(F10:F11,F13:F21) -> 25296000 | H22: =SUM(H10:H11,H13:H21) -> 315500 | I22: =SUM(I10:I11,I13:I21) -> 503600 | J22: =SUM(J10:J11,J13:J21) -> 606775 | K22: =SUM(K10:K11,K13:K21) -> 300000 | L22: =SUM(L10:L11,L13:L21) -> 221700 | N22: =SUM(N10:N11,N13:N21) -> 23400 | O22: =SUM(O10:O11,O13:O21) -> 23500 | P22: =SUM(P10:P11,P13:P21) -> 112450 | Q22: =SUM(Q10:Q11,Q13:Q21) -> 0 | R22: =SUM(R10:R11,R13:R21) -> 23300 | T22: =SUM(T10:T11,T13:T21) -> 15700 | U22: =SUM(U10:U11,U13:U21) -> 15800 | V22: =SUM(V10:V11,V13:V21) -> 15900 | W22: =SUM(W10:W11,W13:W21) -> 0 | X22: =SUM(X10:X11,X13:X21) -> 15600 | AB22: =SUM(AB10:AB11,AB13:AB21) -> 59750 | AC22: =SUM(AC10:AC11,AC13:AC21) -> 0 | AD22: =SUM(AD10:AD11,AD13:AD21) -> 83300 | AF22: =SUM(AF10:AF11,AF13:AF21) -> 2004400 | AG22: =SUM(AG10:AG11,AG13:AG21) -> 1989400 | AH22: =SUM(AH10:AH11,AH13:AH21) -> 1805500 | AI22: =SUM(AI10:AI11,AI13:AI21) -> 0 | AJ22: =SUM(AJ10:AJ11,AJ13:AJ21) -> 1704400
A23: Total Net Direct Expenses | B23: =SUM(B22,B8:B9) -> 48747400 | C23: =SUM(C22,C8:C9) -> 37577500 | D23: =SUM(D22,D8:D9) -> 29630500 | E23: =SUM(E22,E8:E9) -> 0 | F23: =SUM(F22,F8:F9) -> 36521500 | H23: =SUM(H22,H8:H9) -> 949500 | I23: =SUM(I22,I8:I9) -> 1137100 | J23: =SUM(J22,J8:J9) -> 1282025 | K23: =SUM(K22,K8:K9) -> 300000 | L23: =SUM(L22,L8:L9) -> 999300 | N23: =SUM(N22,N8:N9) -> 758425 | O23: =SUM(O22,O8:O9) -> 698500 | P23: =SUM(P22,P8:P9) -> 787450 | Q23: =SUM(Q22,Q8:Q9) -> 0 | R23: =SUM(R22,R8:R9) -> 698300 | T23: =SUM(T22,T8:T9) -> 485700 | U23: =SUM(U22,U8:U9) -> 486300 | V23: =SUM(V22,V8:V9) -> 486100 | W23: =SUM(W22,W8:W9) -> 0 | X23: =SUM(X22,X8:X9) -> 485600 | AB23: =SUM(AB22,AB8:AB9) -> 379250 | AC23: =SUM(AC22,AC8:AC9) -> 0 | AD23: =SUM(AD22,AD8:AD9) -> 560300 | AF23: =SUM(AF22,AF8:AF9) -> 2414900 | AG23: =SUM(AG22,AG8:AG9) -> 2301900 | AH23: =SUM(AH22,AH8:AH9) -> 2217000 | AI23: =SUM(AI22,AI8:AI9) -> 0 | AJ23: =SUM(AJ22,AJ8:AJ9) -> 2014400
A24: Total Allocations | B24: =SUM(B25:B34) -> 0 | C24: =SUM(C25:C34) -> 0 | D24: =SUM(D25:D34) -> 0 | F24: =SUM(F25:F34) -> 0 | H24: =SUM(H25:H34) -> 0 | I24: =SUM(I25:I34) -> 0 | J24: =SUM(J25:J34) -> 0 | L24: =SUM(L25:L34) -> 0 | N24: =SUM(N25:N34) -> 0 | O24: =SUM(O25:O34) -> 0 | P24: =SUM(P25:P34) -> 0 | R24: =SUM(R25:R34) -> 0 | T24: =SUM(T25:T34) -> 0 | U24: =SUM(U25:U34) -> 0 | V24: =SUM(V25:V34) -> 0 | X24: =SUM(X25:X34) -> 0 | AB24: =SUM(AB25:AB34) -> 0 | AD24: =SUM(AD25:AD34) -> 0 | AF24: =SUM(AF25:AF34) -> 0 | AG24: =SUM(AG25:AG34) -> 0 | AH24: =SUM(AH25:AH34) -> 0 | AJ24: =SUM(AJ25:AJ34) -> 0
A25: Accrued Vacation | B25: 0 | C25: 0 | D25: 0 | F25: 0 | H25: 0 | I25: 0 | J25: 0 | L25: 0 | N25: 0 | O25: 0 | P25: 0 | R25: 0 | T25: 0 | U25: 0 | V25: 0 | X25: 0 | AB25: 0 | AD25: 0 | AF25: 0 | AG25: 0 | AH25: 0 | AJ25: 0
A26: Depreciation - Ordinary | B26: 0 | C26: 0 | D26: 0 | F26: 0 | H26: 0 | I26: 0 | J26: 0 | L26: 0 | N26: 0 | O26: 0 | P26: 0 | R26: 0 | T26: 0 | U26: 0 | V26: 0 | X26: 0 | AB26: 0 | AD26: 0 | AF26: 0 | AG26: 0 | AH26: 0 | AJ26: 0
A27: LD Telephone Distr | B27: 0 | C27: 0 | D27: 0 | F27: 0 | H27: 0 | I27: 0 | J27: 0 | L27: 0 | N27: 0 | O27: 0 | P27: 0 | R27: 0 | T27: 0 | U27: 0 | V27: 0 | X27: 0 | AB27: 0 | AD27: 0 | AF27: 0 | AG27: 0 | AH27: 0 | AJ27: 0
A28: Miscellaneous Allocations | B28: 0 | C28: 0 | D28: 0 | F28: 0 | H28: 0 | I28: 0 | J28: 0 | L28: 0 | N28: 0 | O28: 0 | P28: 0 | R28: 0 | T28: 0 | U28: 0 | V28: 0 | X28: 0 | AB28: 0 | AD28: 0 | AF28: 0 | AG28: 0 | AH28: 0 | AJ28: 0
A29: ASC/SRI Reallocations | B29: 0 | C29: 0 | D29: 0 | F29: 0 | H29: 0 | I29: 0 | J29: 0 | L29: 0 | N29: 0 | O29: 0 | P29: 0 | R29: 0 | T29: 0 | U29: 0 | V29: 0 | X29: 0 | AB29: 0 | AD29: 0 | AF29: 0 | AG29: 0 | AH29: 0 | AJ29: 0
A30: ASC/R&D Allocations | B30: 0 | C30: 0 | D30: 0 | F30: 0 | H30: 0 | I30: 0 | J30: 0 | L30: 0 | N30: 0 | O30: 0 | P30: 0 | R30: 0 | T30: 0 | U30: 0 | V30: 0 | X30: 0 | AB30: 0 | AD30: 0 | AF30: 0 | AG30: 0 | AH30: 0 | AJ30: 0
A31: ASC/AAC Reallocations | B31: 0 | C31: 0 | D31: 0 | F31: 0 | H31: 0 | I31: 0 | J31: 0 | L31: 0 | N31: 0 | O31: 0 | P31: 0 | R31: 0 | T31: 0 | U31: 0 | V31: 0 | X31: 0 | AB31: 0 | AD31: 0 | AF31: 0 | AG31: 0 | AH31: 0 | AJ31: 0
A32: ASC/SAEV Reallocations | B32: 0 | C32: 0 | D32: 0 | F32: 0 | H32: 0 | I32: 0 | J32: 0 | L32: 0 | N32: 0 | O32: 0 | P32: 0 | R32: 0 | T32: 0 | U32: 0 | V32: 0 | X32: 0 | AB32: 0 | AD32: 0 | AF32: 0 | AG32: 0 | AH32: 0 | AJ32: 0
A33: ASC/ASBCO Reallocation | B33: 0 | C33: 0 | D33: 0 | F33: 0 | H33: 0 | I33: 0 | J33: 0 | L33: 0 | N33: 0 | O33: 0 | P33: 0 | R33: 0 | T33: 0 | U33: 0 | V33: 0 | X33: 0 | AB33: 0 | AD33: 0 | AF33: 0 | AG33: 0 | AH33: 0 | AJ33: 0
A34: ASC/AVMCC Reallocation | B34: 0 | C34: 0 | D34: 0 | F34: 0 | H34: 0 | I34: 0 | J34: 0 | L34: 0 | N34: 0 | O34: 0 | P34: 0 | R34: 0 | T34: 0 | U34: 0 | V34: 0 | X34: 0 | AB34: 0 | AD34: 0 | AF34: 0 | AG34: 0 | AH34: 0 | AJ34: 0
A35: Total Controllable Expenses | B35: =SUM(B23:B24) -> 48747400 | C35: =SUM(C23:C24) -> 37577500 | D35: =SUM(D23:D24) -> 29630500 | E35: =SUM(E23:E24) -> 0 | F35: =SUM(F23:F24) -> 36521500 | H35: =SUM(H23:H24) -> 949500 | I35: =SUM(I23:I24) -> 1137100 | J35: =SUM(J23:J24) -> 1282025 | K35: =SUM(K23:K24) -> 300000 | L35: =SUM(L23:L24) -> 999300 | N35: =SUM(N23:N24) -> 758425 | O35: =SUM(O23:O24) -> 698500 | P35: =SUM(P23:P24) -> 787450 | Q35: =SUM(Q23:Q24) -> 0 | R35: =SUM(R23:R24) -> 698300 | T35: =SUM(T23:T24) -> 485700 | U35: =SUM(U23:U24) -> 486300 | V35: =SUM(V23:V24) -> 486100 | W35: =SUM(W23:W24) -> 0 | X35: =SUM(X23:X24) -> 485600 | AB35: =SUM(AB23:AB24) -> 379250 | AC35: =SUM(AC23:AC24) -> 0 | AD35: =SUM(AD23:AD24) -> 560300 | AF35: =SUM(AF23:AF24) -> 2414900 | AG35: =SUM(AG23:AG24) -> 2301900 | AH35: =SUM(AH23:AH24) -> 2217000 | AI35: =SUM(AI23:AI24) -> 0 | AJ35: =SUM(AJ23:AJ24) -> 2014400
A37: Total Headcount | B37: =SUM(B38:B40) -> 1 | C37: =SUM(C38:C40) -> 1 | D37: =SUM(D38:D40) -> 1 | E37: =SUM(E38:E40) -> 0 | F37: =SUM(F38:F40) -> 1 | H37: =SUM(H38:H40) -> 5 | I37: =SUM(I38:I40) -> 6 | J37: =SUM(J38:J40) -> 7 | K37: =SUM(K38:K40) -> 0 | L37: =SUM(L38:L40) -> 7 | N37: =SUM(N38:N40) -> 6 | O37: =SUM(O38:O40) -> 6 | P37: =SUM(P38:P40) -> 7 | Q37: =SUM(Q38:Q40) -> 0 | R37: =SUM(R38:R40) -> 6 | T37: =SUM(T38:T40) -> 4 | U37: =SUM(U38:U40) -> 4 | V37: =SUM(V38:V40) -> 4 | W37: =SUM(W38:W40) -> 0 | X37: =SUM(X38:X40) -> 4 | AB37: =SUM(AB38:AB40) -> 5 | AC37: =SUM(AC38:AC40) -> 0 | AD37: =SUM(AD38:AD40) -> 6 | AF37: =SUM(AF38:AF40) -> 4 | AG37: =SUM(AG38:AG40) -> 4 | AH37: =SUM(AH38:AH40) -> 5 | AI37: =SUM(AI38:AI40) -> 0 | AJ37: =SUM(AJ38:AJ40) -> 4
A38: Regular+Excl. Regular | B38: 1 | C38: 1 | D38: 1 | F38: 1 | H38: 5 | I38: 5 | J38: 6 | L38: 7 | N38: 6 | O38: 6 | P38: 6 | R38: 6 | T38: 4 | U38: 4 | V38: 4 | X38: 4 | AB38: 3 | AD38: 4 | AF38: 4 | AG38: 3 | AH38: 4 | AJ38: 3
A39: Saudi Riyal Chapter 8 | B39: 0 | C39: 0 | D39: 0 | F39: 0 | H39: 0 | I39: 0 | J39: 0 | L39: 0 | N39: 0 | O39: 0 | P39: 0 | R39: 0 | T39: 0 | U39: 0 | V39: 0 | X39: 0 | AB39: 2 | AD39: 2 | AF39: 0 | AG39: 0 | AH39: 1 | AJ39: 1
A40: Supplemental | B40: 0 | C40: 0 | D40: 0 | F40: 0 | H40: 0 | I40: 1 | J40: 1 | L40: 0 | N40: 0 | O40: 0 | P40: 1 | R40: 0 | T40: 0 | U40: 0 | V40: 0 | X40: 0 | AB40: 0 | AD40: 0 | AF40: 0 | AG40: 1 | AH40: 0
A41: Special Employee | B41: 1 | C41: 2 | D41: 3 | F41: 2 | H41: 2 | I41: 2 | J41: 1 | L41: 1 | N41: 2 | O41: 1 | P41: 1 | R41: 1 | T41: 1 | U41: 1 | V41: 1 | X41: 1 | AB41: 0 | AD41: 1 | AF41: 0 | AG41: 0 | AH41: 0 | AJ41: 0
A48: Allocation Affiliate = HRS section (Total

Sheet BUDGET-22-25 ATPD
A1: GL Description | B1: Academic & Technical Programs 2022 Actual | C1: Academic & Technical Programs 2023 Actual | D1: Academic & Technical Programs 2024 Actual | E1: Academic & Technical Programs 2025 Plan | F1: Academic & Technical Programs 2025 Plan2 | G1: Column1 | H1: Student Placement, Events & Systems 2022 Actual | I1: Student Placement, Events & Systems 2023 Actual | J1: Student Placement, Events & Systems 2024 Actual | K1: Student Placement, Events & Systems 2025 Plan | L1: Student Placement, Events & Systems 2025 Actual | M1: Column2 | N1: Academic Programs 2022 Actual | O1: Academic Programs 2023 Actual | P1: Academic Programs 2024 Actual | Q1: Academic Programs 2025 Plan | R1: Academic Programs 2025 Actual | S1: Column3 | T1: Technical/Professional 2022 Actual | U1: Technical/Professional 2023 Actual | V1: Technical/Professional 2024 Actual | W1: Technical/Professional 2025 Plan | X1: Technical/Professional 2025 Actual | Y1: Column4 | Z1: Employee & Student Support 2022 Actual | AA1: Employee & Student Support 2023 Actual | AB1: Employee & Student Support 2024 Actual | AC1: Employee & Student Support 2025 Plan | AD1: Employee & Student Support 2025 Actual
A2: Labor - US Company Regular | B2: 1900000 | C2: 2000000 | D2: 2200000 | E2: 0 | F2: 2200000 | H2: 0 | I2: 0 | J2: 200000 | K2: 0 | L2: 200000 | N2: 800000 | O2: 900000 | P2: 1000000 | Q2: 0 | R2: 1000000 | T2: 300000 | U2: 300000 | V2: 400000 | W2: 0 | X2: 300000 | Z2: 600000 | AA2: 600000 | AB2: 600000 | AC2: 0 | AD2: 400000
A3: Labor - Regular Accrual | B3: 38000 | C3: -40000 | D3: 44000 | E3: 0 | F3: -44000 | H3: 0 | I3: 0 | J3: -4000 | K3: 0 | L3: 4000 | N3: -16000 | O3: 18000 | P3: -20000 | Q3: 0 | R3: 20000 | T3: 6000 | U3: -6000 | V3: 8000 | W3: 0 | X3: -6000 | Z3: 12000 | AA3: -12000 | AB3: 12000 | AC3: 0 | AD3: -8000
A4: Labor - Incentive Plan | B4: 0 | C4: 0 | D4: 0 | F4: 0 | H4: 0 | I4: 0 | J4: 0 | L4: 0 | N4: 0 | O4: 0 | P4: 0 | T4: 0 | U4: 0 | V4: 0 | X4: 0 | Z4: 0 | AA4: 0 | AB4: 0 | AD4: 0
A5: Labor - Special Employees | B5: 130000 | C5: 130000 | D5: 65000 | E5: 0 | F5: 65000 | H5: 0 | I5: 0 | J5: 0 | K5: 0 | L5: 0 | N5: 130000 | O5: 195000 | P5: 130000 | Q5: 0 | R5: 195000 | T5: 130000 | U5: 195000 | V5: 130000 | W5: 0 | X5: 130000 | Z5: 65000 | AA5: 65000 | AB5: 65000 | AC5: 0 | AD5: 65000
A6: Loaned Employees Cost | B6: 0 | C6: 0 | D6: 0 | F6: 0 | H6: 0 | I6: 0 | J6: 0 | L6: 0 | N6: 0 | O6: 0 | P6: 0 | R6: 0 | T6: 0 | U6: 0 | V6: 0 | X6: 0 | Z6: 0 | AA6: 0 | AB6: 0 | AD6: 0
A7: Salary overtime expenses | B7: 19000 | C7: 20000 | D7: 22000 | E7: 0 | F7: 22000 | H7: 0 | I7: 0 | J7: 2000 | K7: 0 | L7: 2000 | N7: 8000 | O7: 9000 | P7: 10000 | Q7: 0 | R7: 10000 | T7: 3000 | U7: 3000 | V7: 4000 | W7: 0 | X7: 3000 | Z7: 6000 | AA7: 6000 | AB7: 6000 | AC7: 0 | AD7: 4000
A8: Total Labor | B8: =SUM(B2:B7) -> 2087000 | C8: =SUM(C2:C7) -> 2110000 | D8: =SUM(D2:D7) -> 2331000 | E8: =SUM(E2:E7) -> 0 | F8: =SUM(F2:F7) -> 2243000 | H8: =SUM(H2:H7) -> 0 | I8: =SUM(I2:I7) -> 0 | J8: =SUM(J2:J7) -> 198000 | K8: =SUM(K2:K7) -> 0 | L8: =SUM(L2:L7) -> 206000 | N8: =SUM(N2:N7) -> 922000 | O8: =SUM(O2:O7) -> 1122000 | P8: =SUM(P2:P7) -> 1120000 | Q8: =SUM(Q2:Q7) -> 0 | R8: =SUM(R2:R7) -> 1225000 | T8: =SUM(T2:T7) -> 439000 | U8: =SUM(U2:U7) -> 492000 | V8: =SUM(V2:V7) -> 542000 | W8: =SUM(W2:W7) -> 0 | X8: =SUM(X2:X7) -> 427000 | Z8: =SUM(Z2:Z7) -> 683000 | AA8: =SUM(AA2:AA7) -> 659000 | AB8: =SUM(AB2:AB7) -> 683000 | AC8: =SUM(AC2:AC7) -> 0 | AD8: =SUM(AD2:AD7) -> 461000
A9: Total Materials | B9: 60000 | C9: 100000 | D9: 40000 | F9: 20000 | H9: 0 | I9: 0 | J9: 500 | L9: 1500 | N9: 5000 | O9: 200 | P9: 2500 | R9: 1000 | T9: 500 | U9: 5000 | V9: 3000 | X9: 200 | Z9: 1000 | AA9: 2000 | AB9: 1000 | AD9: 1500
A10: Consultants Compensation | B10: 0 | C10: 0 | D10: 100000 | F10: 100000 | H10: 0 | I10: 0 | J10: 0 | L10: 0 | N10: 0 | O10: 0 | P10: 80000 | R10: 100000 | T10: 0 | U10: 0 | V10: 36000 | X10: 0 | Z10: 0 | AA10: 0 | AB10: 0 | AD10: 0
A11: Temporary Labor | B11: 90000 | C11: 360000 | D11: 540000 | E11: 0 | F11: 540000 | H11: 0 | I11: 0 | J11: 180000 | K11: 0 | L11: 180000 | N11: 90000 | O11: 90000 | P11: 90000 | Q11: 0 | R11: 90000 | T11: 0 | U11: 180000 | V11: 90000 | W11: 0 | X11: 90000 | Z11: 0 | AA11: 90000 | AB11: 180000 | AC11: 0 | AD11: 90000
A12: Invoiced Labor | B12: =SUM(B10:B11) -> 90000 | C12: =SUM(C10:C11) -> 360000 | D12: =SUM(D10:D11) -> 640000 | E12: =SUM(E10:E11) -> 0 | F12: =SUM(F10:F11) -> 640000 | H12: =SUM(H10:H11) -> 0 | I12: =SUM(I10:I11) -> 0 | J12: =SUM(J10:J11) -> 180000 | K12: =SUM(K10:K11) -> 0 | L12: =SUM(L10:L11) -> 180000 | N12: =SUM(N10:N11) -> 90000 | O12: =SUM(O10:O11) -> 90000 | P12: =SUM(P10:P11) -> 170000 | Q12: =SUM(Q10:Q11) -> 0 | R12: =SUM(R10:R11) -> 190000 | T12: =SUM(T10:T11) -> 0 | U12: =SUM(U10:U11) -> 180000 | V12: =SUM(V10:V11) -> 126000 | W12: =SUM(W10:W11) -> 0 | X12: =SUM(X10:X11) -> 90000 | Z12: =SUM(Z10:Z11) -> 0 | AA12: =SUM(AA10:AA11) -> 90000 | AB12: =SUM(AB10:AB11) -> 180000 | AC12: =SUM(AC10:AC11) -> 0 | AD12: =SUM(AD10:AD11) -> 90000
A13: Corporate Obligations | B13: 285000 | C13: 300000 | D13: 330000 | E13: 0 | F13: 330000 | H13: 0 | I13: 0 | J13: 40000 | K13: 0 | L13: 40000 | N13: 160000 | O13: 180000 | P13: 200000 | Q13: 0 | R13: 200000 | T13: 60000 | U13: 60000 | V13: 80000 | W13: 0 | X13: 60000 | Z13: 120000 | AA13: 120000 | AB13: 120000 | AC13: 0 | AD13: 80000
A14: Recruiting | B14: 3000 | C14: 4000 | D14: 1500 | F14: 2500 | H14: 0 | I14: 0 | J14: 0 | K14: 0 | L14: 0 | N14: 0 | O14: 0 | P14: 0 | Q14: 0 | R14: 0 | T14: 0 | U14: 0 | V14: 0 | W14: 0 | X14: 0 | Z14: 1000 | AA14: 1200 | AB14: 1100 | AD14: 1100
A15: Public Affairs Activities | B15: 3000 | C15: 1000 | D15: 11000 | F15: 900 | H15: 0 | I15: 0 | J15: 0 | L15: 0 | N15: 2000 | O15: 0 | P15: 0 | R15: 0 | T15: 0 | U15: 0 | V15: 0 | X15: 0 | Z15: 0 | AA15: 0 | AB15: 0 | AD15: 0
A16: Environmental Services | B16: 0 | C16: 0 | D16: 0 | F16: 0 | H16: 0 | I16: 0 | J16: 0 | L16: 0 | N16: 0 | O16: 0 | P16: 0 | R16: 0 | T16: 0 | U16: 0 | V16: 0 | X16: 0 | Z16: 0 | AA16: 0 | AB16: 0 | AD16: 0
A17: Computer & Communications | B17: 500000 | C17: 600000 | D17: 660000 | E17: 0 | F17: 660000 | H17: 0 | I17: 0 | J17: 4000 | K17: 0 | L17: 4000 | N17: 6000 | O17: 7000 | P17: 7000 | Q17: 0 | R17: 7000 | T17: 4500 | U17: 7500 | V17: 7500 | W17: 0 | X17: 6000 | Z17: 14000 | AA17: 16000 | AB17: 18000 | AC17: 0 | AD17: 14000
A18: Facility Operations & Maintenance | B18: 100000 | C18: 90000 | D18: 130000 | F18: 90000 | H18: 0 | I18: 0 | J18: 0 | L18: 0 | N18: 3000 | O18: 4000 | P18: 500 | R18: 0 | T18: 0 | U18: 0 | V18: 0 | X18: 0 | Z18: 200 | AA18: 200 | AB18: 1000 | AD18: 200
A19: Leases | B19: 0 | C19: 0 | D19: 0 | F19: 0 | H19: 0 | I19: 0 | J19: 0 | L19: 0 | N19: 0 | O19: 0 | P19: 0 | R19: 0 | T19: 0 | U19: 0 | V19: 0 | X19: 0 | Z19: 0 | AA19: 0 | AB19: 0 | AD19: 0
A20: Business Support | B20: 1000000 | C20: 1200000 | D20: 1320000 | E20: 0 | F20: 1320000 | H20: 0 | I20: 0 | J20: 300000 | K20: 0 | L20: 300000 | N20: 320000 | O20: 360000 | P20: 400000 | Q20: 0 | R20: 400000 | T20: 75000 | U20: 75000 | V20: 100000 | W20: 0 | X20: 75000 | Z20: 48000 | AA20: 48000 | AB20: 48000 | AC20: 0 | AD20: 32000
A21: Employee Support | B21: 25000 | C21: 30000 | D21: 33000 | E21: 0 | F21: 33000 | H21: 0 | I21: 0 | J21: 12000 | K21: 0 | L21: 12000 | N21: 4800 | O21: 5400 | P21: 6000 | Q21: 0 | R21: 6000 | T21: 1800 | U21: 1800 | V21: 2400 | W21: 0 | X21: 1800 | Z21: 3600 | AA21: 3600 | AB21: 3600 | AC21: 0 | AD21: 2400
A22: Total Invoices | B22: =SUM(B10:B11,B13:B21) -> 2006000 | C22: =SUM(C10:C11,C13:C21) -> 2585000 | D22: =SUM(D10:D11,D13:D21) -> 3125500 | E22: =SUM(E10:E11,E13:E21) -> 0 | F22: =SUM(F10:F11,F13:F21) -> 3076400 | H22: =SUM(H10:H11,H13:H21) -> 0 | I22: =SUM(I10:I11,I13:I21) -> 0 | J22: =SUM(J10:J11,J13:J21) -> 536000 | K22: =SUM(K10:K11,K13:K21) -> 0 | L22: =SUM(L10:L11,L13:L21) -> 536000 | N22: =SUM(N10:N11,N13:N21) -> 585800 | O22: =SUM(O10:O11,O13:O21) -> 646400 | P22: =SUM(P10:P11,P13:P21) -> 783500 | Q22: =SUM(Q10:Q11,Q13:Q21) -> 0 | R22: =SUM(R10:R11,R13:R21) -> 803000 | T22: =SUM(T10:T11,T13:T21) -> 141300 | U22: =SUM(U10:U11,U13:U21) -> 324300 | V22: =SUM(V10:V11,V13:V21) -> 315900 | W22: =SUM(W10:W11,W13:W21) -> 0 | X22: =SUM(X10:X11,X13:X21) -> 232800 | Z22: =SUM(Z10:Z11,Z13:Z21) -> 186800 | AA22: =SUM(AA10:AA11,AA13:AA21) -> 279000 | AB22: =SUM(AB10:AB11,AB13:AB21) -> 371700 | AC22: =SUM(AC10:AC11,AC13:AC21) -> 0 | AD22: =SUM(AD10:AD11,AD13:AD21) -> 219700
A23: Total Net Direct Expenses | B23: =SUM(B8:B9,B22) -> 4153000 | C23: =SUM(C8:C9,C22) -> 4795000 | D23: =SUM(D8:D9,D22) -> 5496500 | E23: =SUM(E8:E9,E22) -> 0 | F23: =SUM(F8:F9,F22) -> 5339400 | H23: =SUM(H8:H9,H22) -> 0 | I23: =SUM(I8:I9,I22) -> 0 | J23: =SUM(J8:J9,J22) -> 734500 | K23: =SUM(K8:K9,K22) -> 0 | L23: =SUM(L8:L9,L22) -> 743500 | N23: =SUM(N8:N9,N22) -> 1512800 | O23: =SUM(O8:O9,O22) -> 1768600 | P23: =SUM(P8:P9,P22) -> 1906000 | Q23: =SUM(Q8:Q9,Q22) -> 0 | R23: =SUM(R8:R9,R22) -> 2029000 | T23: =SUM(T8:T9,T22) -> 580800 | U23: =SUM(U8:U9,U22) -> 821300 | V23: =SUM(V8:V9,V22) -> 860900 | W23: =SUM(W8:W9,W22) -> 0 | X23: =SUM(X8:X9,X22) -> 660000 | Z23: =SUM(Z8:Z9,Z22) -> 870800 | AA23: =SUM(AA8:AA9,AA22) -> 940000 | AB23: =SUM(AB8:AB9,AB22) -> 1055700 | AC23: =SUM(AC8:AC9,AC22) -> 0 | AD23: =SUM(AD8:AD9,AD22) -> 682200
A24: Total Allocations | B24: =SUM(B25:B36) -> 0 | C24: =SUM(C25:C36) -> 0 | D24: =SUM(D25:D36) -> 0 | F24: =SUM(F25:F36) -> 0 | H24: =SUM(H25:H36) -> 0 | I24: =SUM(I25:I36) -> 0 | J24: =SUM(J25:J36) -> 0 | L24: =SUM(L25:L36) -> 0 | N24: =SUM(N25:N36) -> 0 | O24: =SUM(O25:O36) -> 0 | P24: =SUM(P25:P36) -> 0 | R24: =SUM(R25:R36) -> 0 | T24: =SUM(T25:T36) -> 0 | U24: =SUM(U25:U36) -> 0 | V24: =SUM(V25:V36) -> 0 | X24: =SUM(X25:X36) -> 0 | Z24: =SUM(Z25:Z36) -> 0 | AA24: =SUM(AA25:AA36) -> 0 | AB24: =SUM(AB25:AB36) -> 0 | AD24: =SUM(AD25:AD36) -> 0
A25: ASC/ATA Reallocation | B25: 0 | C25: 0 | D25: 0 | F25: 0 | H25: 0 | I25: 0 | J25: 0 | L25: 0 | N25: 0 | O25: 0 | P25: 0 | R25: 0 | T25: 0 | U25: 0 | V25: 0 | X25: 0 | Z25: 0 | AA25: 0 | AB25: 0 | AD25: 0
A26: ATA Monthly Billing | B26: 0 | C26: 0 | D26: 0 | F26: 0 | H26: 0 | I26: 0 | J26: 0 | L26: 0 | N26: 0 | O26: 0 | P26: 0 | R26: 0 | T26: 0 | U26: 0 | V26: 0 | X26: 0 | Z26: 0 | AA26: 0 | AB26: 0 | AD26: 0
A27: Accrued Vacation | B27: 0 | C27: 0 | D27: 0 | F27: 0 | H27: 0 | I27: 0 | J27: 0 | L27: 0 | N27: 0 | O27: 0 | P27: 0 | R27: 0 | T27: 0 | U27: 0 | V27: 0 | X27: 0 | Z27: 0 | AA27: 0 | AB27: 0 | AD27: 0
A28: Depreciation - Ordinary | B28: 0 | C28: 0 | D28: 0 | F28: 0 | H28: 0 | I28: 0 | J28: 0 | L28: 0 | N28: 0 | O28: 0 | P28: 0 | R28: 0 | T28: 0 | U28: 0 | V28: 0 | X28: 0 | Z28: 0 | AA28: 0 | AB28: 0 | AD28: 0
A29: LD Telephone Distr | B29: 0 | C29: 0 | D29: 0 | F29: 0 | H29: 0 | I29: 0 | J29: 0 | L29: 0 | N29: 0 | O29: 0 | P29: 0 | R29: 0 | T29: 0 | U29: 0 | V29: 0 | X29: 0 | Z29: 0 | AA29: 0 | AB29: 0 | AD29: 0
A30: Miscellaneous Allocations | B30: 0 | C30: 0 | D30: 0 | F30: 0 | H30: 0 | I30: 0 | J30: 0 | L30: 0 | N30: 0 | O30: 0 | P30: 0 | R30: 0 | T30: 0 | U30: 0 | V30: 0 | X30: 0 | Z30: 0 | AA30: 0 | AB30: 0 | AD30: 0
A31: ASC/SRI Reallocations | B31: 0 | C31: 0 | D31: 0 | F31: 0 | H31: 0 | I31: 0 | J31: 0 | L31: 0 | N31: 0 | O31: 0 | P31: 0 | R31: 0 | T31: 0 | U31: 0 | V31: 0 | X31: 0 | Z31: 0 | AA31: 0 | AB31: 0 | AD31: 0
A32: ASC/R&D Allocations | B32: 0 | C32: 0 | D32: 0 | F32: 0 | H32: 0 | I32: 0 | J32: 0 | L32: 0 | N32: 0 | O32: 0 | P32: 0 | R32: 0 | T32: 0 | U32: 0 | V32: 0 | X32: 0 | Z32: 0 | AA32: 0 | AB32: 0 | AD32: 0
A33: ASC/AAC Reallocations | B33: 0 | C33: 0 | D33: 0 | F33: 0 | H33: 0 | I33: 0 | J33: 0 | L33: 0 | N33: 0 | O33: 0 | P33: 0 | R33: 0 | T33: 0 | U33: 0 | V33: 0 | X33: 0 | Z33: 0 | AA33: 0 | AB33: 0 | AD33: 0
A34: ASC/SAEV Reallocations | B34: 0 | C34: 0 | D34: 0 | F34: 0 | H34: 0 | I34: 0 | J34: 0 | L34: 0 | N34: 0 | O34: 0 | P34: 0 | R34: 0 | T34: 0 | U34: 0 | V34: 0 | X34: 0 | Z34: 0 | AA34: 0 | AB34: 0 | AD34: 0
A35: ASC/ASBCO Reallocation | B35: 0 | C35: 0 | D35: 0 | F35: 0 | H35: 0 | I35: 0 | J35: 0 | L35: 0 | N35: 0 | O35: 0 | P35: 0 | R35: 0 | T35: 0 | U35: 0 | V35: 0 | X35: 0 | Z35: 0 | AA35: 0 | AB35: 0 | AD35: 0
A36: ASC/AVMCC Reallocation | B36: 0 | C36: 0 | D36: 0 | F36: 0 | H36: 0 | I36: 0 | J36: 0 | L36: 0 | N36: 0 | O36: 0 | P36: 0 | R36: 0 | T36: 0 | U36: 0 | V36: 0 | X36: 0 | Z36: 0 | AA36: 0 | AB36: 0 | AD36: 0
A37: Total Controllable Expenses | B37: =SUM(B23:B24) -> 4153000 | C37: =SUM(C23:C24) -> 4795000 | D37: =SUM(D23:D24) -> 5496500 | F37: =SUM(F23:F24) -> 5339400 | H37: =SUM(H23:H24) -> 0 | I37: =SUM(I23:I24) -> 0 | J37: =SUM(J23:J24) -> 734500 | L37: =SUM(L23:L24) -> 743500 | N37: =SUM(N23:N24) -> 1512800 | O37: =SUM(O23:O24) -> 1768600 | P37: =SUM(P23:P24) -> 1906000 | R37: =SUM(R23:R24) -> 2029000 | T37: =SUM(T23:T24) -> 580800 | U37: =SUM(U23:U24) -> 821300 | V37: =SUM(V23:V24) -> 860900 | X37: =SUM(X23:X24) -> 660000 | Z37: =SUM(Z23:Z24) -> 870800 | AA37: =SUM(AA23:AA24) -> 940000 | AB37: =SUM(AB23:AB24) -> 1055700 | AD37: =SUM(AD23:AD24) -> 682200
A39: Total Headcount | B39: =SUM(B40:B42) -> 25 | C39: =SUM(C40:C42) -> 30 | D39: =SUM(D40:D42) -> 33 | F39: =SUM(F40:F42) -> 33 | H39: =SUM(H40:H42) -> 0 | I39: =SUM(I40:I42) -> 0 | J39: =SUM(J40:J42) -> 4 | L39: =SUM(L40:L42) -> 4 | N39: =SUM(N40:N42) -> 12 | O39: =SUM(O40:O42) -> 14 | P39: =SUM(P40:P42) -> 14 | R39: =SUM(R40:R42) -> 14 | T39: =SUM(T40:T42) -> 3 | U39: =SUM(U40:U42) -> 5 | V39: =SUM(V40:V42) -> 5 | X39: =SUM(X40:X42) -> 4 | Z39: =SUM(Z40:Z42) -> 7 | AA39: =SUM(AA40:AA42) -> 8 | AB39: =SUM(AB40:AB42) -> 9 | AD39: =SUM(AD40:AD42) -> 7
A40: Regular+Excl. Regular | B40: 19 | C40: 20 | D40: 22 | F40: 22 | H40: 0 | I40: 0 | J40: 2 | L40: 2 | N40: 8 | O40: 9 | P40: 10 | R40: 10 | T40: 3 | U40: 3 | V40: 4 | X40: 3 | Z40: 6 | AA40: 6 | AB40: 6 | AD40: 4
A41: Saudi Riyal Chapter 8 | B41: 5 | C41: 6 | D41: 5 | F41: 5 | H41: 0 | I41: 0 | J41: 0 | L41: 0 | N41: 3 | O41: 4 | P41: 3 | R41: 3 | T41: 0 | U41: 0 | V41: 0 | X41: 0 | Z41: 1 | AA41: 1 | AB41: 1 | AD41: 2
A42: Supplemental | B42: 1 | C42: 4 | D42: 6 | F42: 6 | H42: 0 | I42: 0 | J42: 2 | L42: 2 | N42: 1 | O42: 1 | P42: 1 | R42: 1 | T42: 0 | U42: 2 | V42: 1 | X42: 1 | Z42: 0 | AA42: 1 | AB42: 2 | AD42: 1
A43: Special Employee | B43: 2 | C43: 2 | D43: 1 | F43: 1 | H43: 0 | I43: 0 | J43: 0 | L43: 0 | N43: 2 | O43: 3 | P43: 2 | R43: 3 | T43: 2 | U43: 3 | V43: 2 | X43: 2 | Z43: 1 | AA43: 1 | AB43: 1 | AD43: 1

Sheet BUDGET-2023-25 HR Department
A1: GL Description | B1: Human Resources Department 2023 Actual | C1: Human Resources Department 2024 Actual | D1: Human Resources Department 2025 Plan | E1: Human Resources Department 2025 Actual | G1: Human Resources Services Dept 2023 Actual | H1: Human Resources Services Dept 2024 Actual | I1: Human Resources Services Dept 2025 Plan | J1: Human Resources Services Dept 2025 Actual | K1: 2 | L1: Staffing Services 2023 Actual | M1: Staffing Services 2024 Actual | N1: Staffing Services 2025 Plan | O1: Staffing Services 2025 Actual | P1: 3 | Q1: Academic & Technical Programs 2023 Actual | R1: Academic & Technical Programs 2024 Actual | S1: Academic & Technical Programs 2025 Plan | T1: Academic & Technical Programs 2025 Actual | U1: 4 | V1: Human Resources Adm/Planning Group 2023 Actual | W1: Human Resources Adm/Planning Group 2024 Actual | X1: Human Resources Adm/Planning Group 2025 Plan | Y1: Human Resources Adm/Planning Group 2025 Actual | Z1: 5 | AA1: Human Resources Adm/Planning Group 2023 Actual6 | AB1: Human Resources Adm/Planning Group 2024 Actual7 | AC1: Human Resources Adm/Planning Group 2025 Plan8 | AD1: Human Resources Adm/Planning Group 2025 Actual9
A2: Labor - US Company Regular
A3: Labor - Regular Accrual
A4: Labor - Incentive Plan
A5: Labor - Special Employees
A6: Loaned Employees Cost
A7: Salary overtime expenses
A8: Total Labor
A9: Total Materials
A10: Consultants Compensation
A11: Temporary Labor
A12: Invoiced Labor
A13: Corporate Obligations
... A60: Special Employee
